Workbook
Name _1.: April!$C$3:$I$41
Name _1.S: April!$C$41:$I$41
Name _10.: April!$L$3:$R$41
Name _10.s: April!$M$41:$R$41
Name _11.: April!$M$3:$S$41
Name _11.s: April!$N$41:$S$41
Name _12.: April!$N$3:$T$41
Name _12.s: April!$O$41:$T$41
Name _13.: April!$O$3:$U$41
Name _13.s: April!$P$41:$U$41
Name _14.: April!$P$3:$V$41
Name _14.s: April!$Q$41:$V$41
Name _15.: April!$Q$3:$W$41
Name _15.s: April!$R$41:$W$41
Name _16.: April!$R$3:$X$41
Name _16.s: April!$S$41:$X$41
Name _17.: April!$S$3:$Y$41
Name _17.s: April!$T$41:$Y$41
Name _18.: April!$T$3:$Z$41
Name _18.s: April!$U$41:$Z$41
Name _19.: April!$U$3:$AA$41
Name _19.s: April!$V$41:$AA$41
Name _2.: April!$D$3:$J$41
Name _2.s: April!$E$41:$J$41
Name _20.: April!$V$3:$AB$41
Name _20.s: April!$W$41:$AB$41
Name _21.: April!$W$3:$AC$41
Name _21.s: April!$X$41:$AC$41
Name _22.: April!$X$3:$AD$41
Name _22.s: April!$Y$41:$AD$41
Name _23.: April!$Y$3:$AE$41
Name _23.s: April!$Z$41:$AE$41
Name _24.: April!$Z$3:$AF$41
Name _24.s: April!$AA$41:$AF$41
Name _25.a: April!$AA$3:$AF$41
Name _25.b: April!$C$3:$C$41
Name _25.s: [1]April!$AB$41:$AF$41,[1]April!$C$41:$C$41
Name _25.s: April!$AB$41:$AF$41,April!$C$41:$C$41
Name _26.a: April!$AB$3:$AF$41
Name _26.b: April!$C$3:$D$41
Name _26.s: [1]April!$C$41:$D$41,[1]April!$AC$41:$AF$41
Name _26.s: April!$C$41:$D$41,April!$AC$41:$AF$41
Name _27.a: April!$AC$3:$AF$41
Name _27.b: April!$C$3:$E$41
Name _27.s: [1]April!$AD$41:$AF$41,[1]April!$C$41:$E$41
Name _27.s: April!$AD$41:$AF$41,April!$C$41:$E$41
Name _28.a: April!$AD$3:$AF$41
Name _28.b: April!$C$3:$F$41
Name _28.s: [1]April!$AE$41:$AF$41,[1]April!$C$41:$F$41
Name _28.s: April!$AE$41:$AF$41,April!$C$41:$F$41
Name _29.a: April!$AE$3:$AF$41
Name _29.b: April!$C$3:$G$41
Name _29.s: [1]April!$AF$41:$AF$41,[1]April!$C$41:$G$41
Name _29.s: April!$AF$41:$AF$41,April!$C$41:$G$41
Name _3.: April!$E$3:$K$41
Name _3.s: April!$F$41:$K$41
Name _30.a: April!$AF$3:$AF$41
Name _30.b: April!$C$3:$H$41
Name _30.s: [1]April!$C$41:$H$41,[1]April!#REF!
Name _30.s: April!$C$41:$H$41,April!#REF!

Sheet Phased P&L Budget (2)
B2: Phased P&L Summary Report (Budget)
B3: Hotel Set: LH AG 2024
B4: Year: 2025
B5: With allocation
B6: P&L: Hotel Totals
B7: Currency: Euro
B8: Amounts: Full
B10: Budget | C10: Total Year | F10: Jan | I10: Feb | L10: Mar | O10: Apr | R10: May | U10: Jun | X10: Jul | AA10: Aug | AD10: Sep | AG10: Oct | AJ10: Nov | AM10: Dec
B11: Hotel Revenue | C11: 1.2198848e+08 | D11: 1 | F11: 7240087.4 | G11: 1 | I11: 8314846.3 | J11: 1 | L11: 11118561 | M11: 1 | O11: 8842420.1 | P11: 1 | R11: 11077677 | S11: 1 | U11: 10908122 | V11: 1 | X11: 9390566.3 | Y11: 1 | AA11: 10250151 | AB11: 1 | AD11: 12897676 | AE11: 1 | AG11: 12387225 | AH11: 1 | AJ11: 10794719 | AK11: 1 | AM11: 8766425.1 | AN11: 1
B12: P/R & Related Expenses | C12: 46975896 | D12: 0.3850847 | F12: 3792365.1 | G12: 0.52380101 | I12: 3908626 | J12: 0.47007796 | L12: 4046732.6 | M12: 0.36396191 | O12: 3846189 | P12: 0.43497018 | R12: 3937724.8 | S12: 0.35546484 | U12: 4039104.3 | V12: 0.37028412 | X12: 3752530.1 | Y12: 0.39960637 | AA12: 3776933.8 | AB12: 0.36847591 | AD12: 3995896.8 | AE12: 0.30981526 | AG12: 3933104.2 | AH12: 0.31751293 | AJ12: 4146594.9 | AK12: 0.38413181 | AM12: 3800094.4 | AN12: 0.43348279
B13: Gross Operating Profit | C13: 30075829 | D13: 0 | F13: 290044.42 | G13: 0 | I13: 889605.51 | J13: 0 | L13: 2812348.5 | M13: 0 | O13: 1496788.2 | P13: 0 | R13: 3386770.1 | S13: 0 | U13: 2841946.4 | V13: 0 | X13: 2276610.5 | Y13: 0 | AA13: 2905225.8 | AB13: 0 | AD13: 4624136 | AE13: 0 | AG13: 4442699.8 | AH13: 0 | AJ13: 2818991.9 | AK13: 0 | AM13: 1290661.9 | AN13: 0
B14: Available Rooms | C14: 824900 | D14: 0 | F14: 70060 | G14: 0 | I14: 63280 | J14: 0 | L14: 70060 | M14: 0 | O14: 67800 | P14: 0 | R14: 70060 | S14: 0 | U14: 67800 | V14: 0 | X14: 70060 | Y14: 0 | AA14: 70060 | AB14: 0 | AD14: 67800 | AE14: 0 | AG14: 70060 | AH14: 0 | AJ14: 67800 | AK14: 0 | AM14: 70060 | AN14: 0
B15: Rooms Sold | C15: 540060 | D15: 0 | F15: 36033 | G15: 0 | I15: 39507 | J15: 0 | L15: 49055 | M15: 0 | O15: 41789 | P15: 0 | R15: 47550 | S15: 0 | U15: 47041 | V15: 0 | X15: 42384 | Y15: 0 | AA15: 46032 | AB15: 0 | AD15: 52526 | AE15: 0 | AG15: 49112 | AH15: 0 | AJ15: 48568 | AK15: 0 | AM15: 40463 | AN15: 0
B16: Occupancy % | C16: 65.813311 | D16: 0 | F16: 51.772766 | G16: 0 | I16: 62.923515 | J16: 0 | L16: 70.342564 | M16: 0 | O16: 62.010324 | P16: 0 | R16: 68.305738 | S16: 0 | U16: 69.824484 | V16: 0 | X16: 60.852127 | Y16: 0 | AA16: 66.074793 | AB16: 0 | AD16: 77.817109 | AE16: 0 | AG16: 70.324008 | AH16: 0 | AJ16: 71.883481 | AK16: 0 | AM16: 57.93891 | AN16: 0
B17: Average Daily Rate | C17: 132.71698 | D17: 0 | F17: 114.80619 | G17: 0 | I17: 121.51362 | J17: 0 | L17: 138.74132 | M17: 0 | O17: 123.40963 | P17: 0 | R17: 141.99155 | S17: 0 | U17: 132.54899 | V17: 0 | X17: 123.94446 | Y17: 0 | AA17: 127.6863 | AB17: 0 | AD17: 142.64024 | AE17: 0 | AG17: 157.60431 | AH17: 0 | AJ17: 133.28359 | AK17: 0 | AM17: 122.35399 | AN17: 0
B18: Revenue Per Available Room | C18: 85.627391 | D18: 0 | F18: 57.891971 | G18: 0 | I18: 74.54233 | J18: 0 | L18: 95.72945 | M18: 0 | O18: 74.821758 | P18: 0 | R18: 95.038515 | S18: 0 | U18: 90.696713 | V18: 0 | X18: 73.926808 | Y18: 0 | AA18: 82.742015 | AB18: 0 | AD18: 109.06964 | AE18: 0 | AG18: 109.01174 | AH18: 0 | AJ18: 94.157338 | AK18: 0 | AM18: 69.673985 | AN18: 0
B19: Total Revenue Per Available Room | C19: 147.88274 | D19: 0 | F19: 103.34124 | G19: 0 | I19: 131.3977 | J19: 0 | L19: 158.70055 | M19: 0 | O19: 130.41917 | P19: 0 | R19: 158.117 | S19: 0 | U19: 160.88676 | V19: 0 | X19: 134.03606 | Y19: 0 | AA19: 146.30533 | AB19: 0 | AD19: 190.23121 | AE19: 0 | AG19: 176.80881 | AH19: 0 | AJ19: 159.21414 | AK19: 0 | AM19: 125.12739 | AN19: 0
B20: Number of Guests | C20: 744636.92 | D20: 0 | F20: 46243.555 | G20: 0 | I20: 51902.211 | J20: 0 | L20: 65871.502 | M20: 0 | O20: 56416.151 | P20: 0 | R20: 65738.666 | S20: 0 | U20: 64694.092 | V20: 0 | X20: 62619.382 | Y20: 0 | AA20: 68425.839 | AB20: 0 | AD20: 71191.698 | AE20: 0 | AG20: 69161.3 | AH20: 0 | AJ20: 63404.9 | AK20: 0 | AM20: 58967.63 | AN20: 0
B21: Room Density | C21: 1.3716065 | D21: 0 | F21: 1.2749105 | G21: 0 | I21: 1.3034861 | J21: 0 | L21: 1.336624 | M21: 0 | O21: 1.3418679 | P21: 0 | R21: 1.3737053 | S21: 0 | U21: 1.3665553 | V21: 0 | X21: 1.4688007 | Y21: 0 | AA21: 1.4781353 | AB21: 0 | AD21: 1.3493499 | AE21: 0 | AG21: 1.4037488 | AH21: 0 | AJ21: 1.3009603 | AK21: 0 | AM21: 1.4526909 | AN21: 0
B22: Covers | C22: 887397.83 | D22: 0 | F22: 57581.77 | G22: 0 | I22: 64906.699 | J22: 0 | L22: 76338.346 | M22: 0 | O22: 68538.039 | P22: 0 | R22: 76858.808 | S22: 0 | U22: 74693.977 | V22: 0 | X22: 69081.764 | Y22: 0 | AA22: 79196.073 | AB22: 0 | AD22: 88605.096 | AE22: 0 | AG22: 85343.551 | AH22: 0 | AJ22: 79676.765 | AK22: 0 | AM22: 66576.942 | AN22: 0
B23: FTE | C23: 626.5569 | D23: 0 | F23: 628.0784 | G23: 0 | I23: 636.6784 | J23: 0 | L23: 637.1784 | M23: 0 | O23: 629.8284 | P23: 0 | R23: 632.3284 | S23: 0 | U23: 629.3284 | V23: 0 | X23: 624.6684 | Y23: 0 | AA23: 624.3184 | AB23: 0 | AD23: 618.3184 | AE23: 0 | AG23: 619.3184 | AH23: 0 | AJ23: 619.3184 | AK23: 0 | AM23: 619.3184 | AN23: 0
B25: Hotel Totals
B27: Hotel Revenue | C27: 1.2198848e+08 | D27: 1 | F27: 7240087.4 | G27: 1 | I27: 8314846.3 | J27: 1 | L27: 11118561 | M27: 1 | O27: 8842420.1 | P27: 1 | R27: 11077677 | S27: 1 | U27: 10908122 | V27: 1 | X27: 9390566.3 | Y27: 1 | AA27: 10250151 | AB27: 1 | AD27: 12897676 | AE27: 1 | AG27: 12387225 | AH27: 1 | AJ27: 10794719 | AK27: 1 | AM27: 8766425.1 | AN27: 1
B28: Rooms Revenue | C28: 71675135 | D28: 0.5875566 | F28: 4136811.5 | G28: 0.57137591 | I28: 4800638.6 | J28: 0.57735747 | L28: 6805955.3 | M28: 0.61212557 | O28: 5157165.2 | P28: 0.58323006 | R28: 6751698.4 | S28: 0.60948683 | U28: 6235237.1 | V28: 0.57161417 | X28: 5253262.2 | Y28: 0.5594191 | AA28: 5877655.6 | AB28: 0.57342135 | AD28: 7492321.3 | AE28: 0.58090476 | AG28: 7740262.6 | AH28: 0.62485847 | AJ28: 6473317.5 | AK28: 0.59967449 | AM28: 4950809.4 | AN28: 0.56474667
B29: F&B Revenue | C29: 27110904 | D29: 0.22224152 | F29: 1845934.3 | G29: 0.25496023 | I29: 2166474.9 | J29: 0.26055501 | L29: 2499682.7 | M29: 0.22482071 | O29: 2111881.7 | P29: 0.23883526 | R29: 2284825.8 | S29: 0.20625495 | U29: 2341321.6 | V29: 0.21464021 | X29: 1757392.8 | Y29: 0.1871445 | AA29: 1960046.4 | AB29: 0.19122122 | AD29: 2945980.5 | AE29: 0.22841174 | AG29: 2550905 | AH29: 0.2059303 | AJ29: 2675403 | AK29: 0.24784369 | AM29: 1971055.6 | AN29: 0.22484143
B30: OOD Revenue | C30: 4283822.8 | D30: 0.03511662 | F30: 286832.35 | G30: 0.03961725 | I30: 324057.59 | J30: 0.03897337 | L30: 363546.36 | M30: 0.03269725 | O30: 338467.57 | P30: 0.03827771 | R30: 398241.14 | S30: 0.03594988 | U30: 383543.99 | V30: 0.03516132 | X30: 368802.63 | Y30: 0.03927374 | AA30: 378084.88 | AB30: 0.03688579 | AD30: 408861.68 | AE30: 0.03170042 | AG30: 375262.87 | AH30: 0.03029434 | AJ30: 348985.92 | AK30: 0.03232932 | AM30: 309135.81 | AN30: 0.03526361
B31: Other Income | C31: 1174894.8 | D31: 0.00963119 | F31: 75497.384 | G31: 0.01042769 | I31: 76366.258 | J31: 0.00918433 | L31: 140783.64 | M31: 0.01266204 | O31: 81646.668 | P31: 0.00923352 | R31: 84491.499 | S31: 0.00762719 | U31: 98406.032 | V31: 0.00902135 | X31: 69740.03 | Y31: 0.00742661 | AA31: 74394.707 | AB31: 0.00725791 | AD31: 130622.83 | AE31: 0.01012763 | AG31: 145234.84 | AH31: 0.01172457 | AJ31: 123977.66 | AK31: 0.01148503 | AM31: 73733.238 | AN31: 0.00841087
B33: Rooms
B34: Rooms Revenue | C34: 71675135 | D34: 1 | F34: 4136811.5 | G34: 1 | I34: 4800638.6 | J34: 1 | L34: 6805955.3 | M34: 1 | O34: 5157165.2 | P34: 1 | R34: 6751698.4 | S34: 1 | U34: 6235237.1 | V34: 1 | X34: 5253262.2 | Y34: 1 | AA34: 5877655.6 | AB34: 1 | AD34: 7492321.3 | AE34: 1 | AG34: 7740262.6 | AH34: 1 | AJ34: 6473317.5 | AK34: 1 | AM34: 4950809.4 | AN34: 1
B35: P/R & Related Expenses | C35: 14927382 | D35: 0.20826445 | F35: 1150985.7 | G35: 0.27823015 | I35: 1195591.5 | J35: 0.24904843 | L35: 1263390.6 | M35: 0.18563017 | O35: 1199755.4 | P35: 0.23263854 | R35: 1254052.2 | S35: 0.18573878 | U35: 1308248 | V35: 0.20981527 | X35: 1209968 | Y35: 0.23032697 | AA35: 1224281.5 | AB35: 0.20829419 | AD35: 1308659.8 | AE35: 0.1746668 | AG35: 1265785.9 | AH35: 0.16353268 | AJ35: 1331244.6 | AK35: 0.20565106 | AM35: 1215419.4 | AN35: 0.24549913
B36: Other Expenses | C36: 11316500 | D36: 0.15788599 | F36: 699808.76 | G36: 0.16916622 | I36: 798402.26 | J36: 0.16631168 | L36: 1064316.5 | M36: 0.15638018 | O36: 833095.11 | P36: 0.16154129 | R36: 1008530.1 | S36: 0.14937429 | U36: 1009980.4 | V36: 0.16197947 | X36: 892610.81 | Y36: 0.16991553 | AA36: 975216.27 | AB36: 0.16591926 | AD36: 1141191.3 | AE36: 0.15231478 | AG36: 1124487.9 | AH36: 0.14527774 | AJ36: 978351.73 | AK36: 0.15113606 | AM36: 790508.56 | AN36: 0.15967259
B37: Dept Profit/(Loss) | C37: 45431253 | D37: 0.63384956 | F37: 2286017.1 | G37: 0.55260363 | I37: 2806644.8 | J37: 0.58463989 | L37: 4478248.2 | M37: 0.65798965 | O37: 3124314.7 | P37: 0.60582017 | R37: 4489116.1 | S37: 0.66488694 | U37: 3917008.7 | V37: 0.62820525 | X37: 3150683.4 | Y37: 0.59975751 | AA37: 3678157.8 | AB37: 0.62578655 | AD37: 5042470.2 | AE37: 0.67301842 | AG37: 5349988.9 | AH37: 0.69118958 | AJ37: 4163721.2 | AK37: 0.64321288 | AM37: 2944881.4 | AN37: 0.59482828
B39: Food & Beverage
B40: Food Revenue | C40: 16634038 | D40: 0.61355526 | F40: 1107459.2 | G40: 0.59994508 | I40: 1274039.1 | J40: 0.58807011 | L40: 1523950.2 | M40: 0.60965746 | O40: 1288151.7 | P40: 0.60995448 | R40: 1414044.2 | S40: 0.61888493 | U40: 1445661.4 | V40: 0.61745528 | X40: 1107692.2 | Y40: 0.6303043 | AA40: 1242505.1 | AB40: 0.63391618 | AD40: 1825679.6 | AE40: 0.61971883 | AG40: 1583715 | AH40: 0.62084437 | AJ40: 1603559.3 | AK40: 0.59937114 | AM40: 1217580.8 | AN40: 0.61773031
B41: Beverage Revenue | C41: 7486725.1 | D41: 0.2761518 | F41: 500796.29 | G41: 0.27129692 | I41: 639110.17 | J41: 0.29500004 | L41: 714857.09 | M41: 0.28597913 | O41: 597059.2 | P41: 0.28271433 | R41: 623253.13 | S41: 0.27277928 | U41: 629867.8 | V41: 0.26902233 | X41: 497756.89 | Y41: 0.28323599 | AA41: 570157 | AB41: 0.29088954 | AD41: 765251.86 | AE41: 0.25976134 | AG41: 677870.49 | AH41: 0.26573726 | AJ41: 727029.87 | AK41: 0.27174593 | AM41: 543715.3 | AN41: 0.27584981
B42: Other Revenue | C42: 2990141.2 | D42: 0.11029294 | F42: 237678.82 | G42: 0.12875801 | I42: 253325.58 | J42: 0.11692985 | L42: 260875.43 | M42: 0.10436342 | O42: 226670.78 | P42: 0.10733119 | R42: 247528.4 | S42: 0.10833579 | U42: 265792.42 | V42: 0.11352239 | X42: 151943.67 | Y42: 0.08645971 | AA42: 147384.28 | AB42: 0.07519428 | AD42: 355049.07 | AE42: 0.12051983 | AG42: 289319.49 | AH42: 0.11341837 | AJ42: 344813.78 | AK42: 0.12888293 | AM42: 209759.51 | AN42: 0.10641989
B43: F&B Revenue | C43: 27110904 | D43: 1 | F43: 1845934.3 | G43: 1 | I43: 2166474.9 | J43: 1 | L43: 2499682.7 | M43: 1 | O43: 2111881.7 | P43: 1 | R43: 2284825.8 | S43: 1 | U43: 2341321.6 | V43: 1 | X43: 1757392.8 | Y43: 1 | AA43: 1960046.4 | AB43: 1 | AD43: 2945980.5 | AE43: 1 | AG43: 2550905 | AH43: 1 | AJ43: 2675403 | AK43: 1 | AM43: 1971055.6 | AN43: 1
B44: Cost of Sales Food | C44: 5085929.5 | D44: 0.30575436 | F44: 333187.26 | G44: 0.30085737 | I44: 391538.56 | J44: 0.30732067 | L44: 465349.65 | M44: 0.30535752 | O44: 393745.48 | P44: 0.30566702 | R44: 431554.11 | S44: 0.30519138 | U44: 438140.12 | V44: 0.30307244 | X44: 347743.09 | Y44: 0.31393475 | AA44: 391621.19 | AB44: 0.31518678 | AD44: 552937.66 | AE44: 0.30286676 | AG44: 484700.43 | AH44: 0.30605282 | AJ44: 485892.95 | AK44: 0.30300903 | AM44: 369519.01 | AN44: 0.30348624
B45: Cost of Sales Beverage | C45: 1338622.2 | D45: 0.17879944 | F45: 88165.581 | G45: 0.17605079 | I45: 113913.77 | J45: 0.17823808 | L45: 127404.49 | M45: 0.17822372 | O45: 106416.21 | P45: 0.17823393 | R45: 112350.47 | S45: 0.1802646 | U45: 113728.08 | V45: 0.18055865 | X45: 90660.094 | Y45: 0.1821373 | AA45: 103337.54 | AB45: 0.181244 | AD45: 136041.7 | AE45: 0.17777376 | AG45: 120505.79 | AH45: 0.17777111 | AJ45: 128344.9 | AK45: 0.17653319 | AM45: 97753.636 | AN45: 0.17978828
B46: Other Cost | C46: 209170 | D46: 0.06995322 | F46: 17577 | G46: 0.07395274 | I46: 18470 | J46: 0.07291013 | L46: 21130 | M46: 0.08099651 | O46: 15530 | P46: 0.06851346 | R46: 15740 | S46: 0.06358866 | U46: 20265 | V46: 0.07624371 | X46: 12265 | Y46: 0.08072071 | AA46: 10018 | AB46: 0.06797197 | AD46: 25790 | AE46: 0.07263785 | AG46: 17110 | AH46: 0.05913877 | AJ46: 21720 | AK46: 0.06299052 | AM46: 13555 | AN46: 0.06462162
B47: Cost of Sales | C47: 6633721.8 | D47: 0.24468833 | F47: 438929.84 | G47: 0.23778194 | I47: 523922.32 | J47: 0.24183171 | L47: 613884.14 | M47: 0.24558482 | O47: 515691.69 | P47: 0.24418588 | R47: 559644.58 | S47: 0.24493972 | U47: 572133.2 | V47: 0.24436336 | X47: 450668.18 | Y47: 0.25644135 | AA47: 504976.72 | AB47: 0.25763509 | AD47: 714769.36 | AE47: 0.24262528 | AG47: 622316.22 | AH47: 0.243959 | AJ47: 635957.86 | AK47: 0.23770545 | AM47: 480827.65 | AN47: 0.24394424
B48: P/R & Related Expenses | C48: 13286922 | D48: 0.49009514 | F48: 1062408.8 | G48: 0.57553986 | I48: 1103781.1 | J48: 0.50948253 | L48: 1146025.6 | M48: 0.4584684 | O48: 1093535.4 | P48: 0.51780144 | R48: 1096980.3 | S48: 0.48011552 | U48: 1143363.4 | V48: 0.48834102 | X48: 1026101.3 | Y48: 0.58387705 | AA48: 1038345.5 | AB48: 0.52975556 | AD48: 1138210 | AE48: 0.38636032 | AG48: 1112443.2 | AH48: 0.43609747 | AJ48: 1243016.7 | AK48: 0.46460914 | AM48: 1082711.3 | AN48: 0.5493053
B49: Other Expenses | C49: 1192925.3 | D49: 0.04400168 | F49: 89119.326 | G49: 0.04827871 | I49: 102029.49 | J49: 0.0470947 | L49: 117551.68 | M49: 0.04702664 | O49: 91479.5 | P49: 0.04331658 | R49: 109869.25 | S49: 0.04808649 | U49: 103611.7 | V49: 0.04425351 | X49: 77884.568 | Y49: 0.04431825 | AA49: 86531.902 | AB49: 0.04414788 | AD49: 122022.04 | AE49: 0.04141984 | AG49: 97260.822 | AH49: 0.03812797 | AJ49: 105924.86 | AK49: 0.03959211 | AM49: 89640.18 | AN49: 0.04547826
B50: Dept Profit/(Loss) | C50: 5997334.6 | D50: 0.22121485 | F50: 255476.37 | G50: 0.13839949 | I50: 436741.95 | J50: 0.20159105 | L50: 622221.36 | M50: 0.24892013 | O50: 411175.11 | P50: 0.1946961 | R50: 518331.62 | S50: 0.22685827 | U50: 522213.31 | V50: 0.22304211 | X50: 202738.72 | Y50: 0.11536335 | AA50: 330192.29 | AB50: 0.16846147 | AD50: 970979.14 | AE50: 0.32959455 | AG50: 718884.71 | AH50: 0.28181556 | AJ50: 690503.59 | AK50: 0.2580933 | AM50: 317876.47 | AN50: 0.1612722
B52: Other Departments
B53: OOD Revenue | C53: 4283822.8 | D53: 1 | F53: 286832.35 | G53: 1 | I53: 324057.59 | J53: 1 | L53: 363546.36 | M53: 1 | O53: 338467.57 | P53: 1 | R53: 398241.14 | S53: 1 | U53: 383543.99 | V53: 1 | X53: 368802.63 | Y53: 1 | AA53: 378084.88 | AB53: 1 | AD53: 408861.68 | AE53: 1 | AG53: 375262.87 | AH53: 1 | AJ53: 348985.92 | AK53: 1 | AM53: 309135.81 | AN53: 1
B54: Cost of Sales | C54: 416646.96 | D54: 0.09726055 | F54: 20680.179 | G54: 0.07209849 | I54: 33491.709 | J54: 0.1033511 | L54: 31243.797 | M54: 0.08594171 | O54: 63332.372 | P54: 0.18711504 | R54: 38878.294 | S54: 0.09762501 | U54: 40776.304 | V54: 0.10631454 | X54: 35983.223 | Y54: 0.0975677 | AA54: 33253.997 | AB54: 0.08795379 | AD54: 39881.941 | AE54: 0.09754385 | AG54: 36487.345 | AH54: 0.09723143 | AJ54: 22415.028 | AK54: 0.06422903 | AM54: 20222.768 | AN54: 0.0654171
B55: P/R & Related Expenses | C55: 830021.18 | D55: 0.19375712 | F55: 57504.483 | G55: 0.20048116 | I55: 69671.885 | J55: 0.21499847 | L55: 68024.207 | M55: 0.18711288 | O55: 72444.038 | P55: 0.21403539 | R55: 74221.403 | S55: 0.18637302 | U55: 75127.924 | V55: 0.19587824 | X55: 71906.877 | Y55: 0.19497387 | AA55: 72346.635 | AB55: 0.19135025 | AD55: 74455.064 | AE55: 0.18210331 | AG55: 72463.235 | AH55: 0.19309993 | AJ55: 61102.964 | AK55: 0.17508719 | AM55: 60752.462 | AN55: 0.19652354
B56: Other Expenses | C56: 233976.36 | D56: 0.05461859 | F56: 5196.28 | G56: 0.01811609 | I56: 7296.28 | J56: 0.02251538 | L56: 20146.28 | M56: 0.05541599 | O56: 25921.28 | P56: 0.07658424 | R56: 30446.28 | S56: 0.07645187 | U56: 26046.28 | V56: 0.0679095 | X56: 22919.28 | Y56: 0.06214511 | AA56: 21446.28 | AB56: 0.05672345 | AD56: 23946.28 | AE56: 0.05856817 | AG56: 22846.28 | AH56: 0.06088074 | AJ56: 15696.28 | AK56: 0.04497683 | AM56: 12069.28 | AN56: 0.039042
B57: Dept Profit/(Loss) | C57: 2803178.3 | D57: 0.65436374 | F57: 203451.41 | G57: 0.70930426 | I57: 213597.71 | J57: 0.65913504 | L57: 244132.08 | M57: 0.67152942 | O57: 176769.88 | P57: 0.52226534 | R57: 254695.17 | S57: 0.63955011 | U57: 241593.48 | V57: 0.62989772 | X57: 237993.25 | Y57: 0.64531332 | AA57: 251037.97 | AB57: 0.66397251 | AD57: 270578.4 | AE57: 0.66178468 | AG57: 243466.01 | AH57: 0.6487879 | AJ57: 249771.65 | AK57: 0.71570695 | AM57: 216091.3 | AN57: 0.69901736
B59: Other Income
B60: Other Income | C60: 1174894.8 | D60: 0.27426316 | F60: 75497.384 | G60: 0.26321084 | I60: 76366.258 | J60: 0.23565644 | L60: 140783.64 | M60: 0.38725086 | O60: 81646.668 | P60: 0.24122449 | R60: 84491.499 | S60: 0.21216165 | U60: 98406.032 | V60: 0.25657039 | X60: 69740.03 | Y60: 0.18909852 | AA60: 74394.707 | AB60: 0.19676721 | AD60: 130622.83 | AE60: 0.31947926 | AG60: 145234.84 | AH60: 0.38702162 | AJ60: 123977.66 | AK60: 0.35525118 | AM60: 73733.238 | AN60: 0.23851406
B62: Gross Operating Income
B63: GOI | C63: 55406660 | D63: 0.45419586 | F63: 2820442.2 | G63: 0.38955914 | I63: 3533350.8 | J63: 0.42494481 | L63: 5485385.2 | M63: 0.4933539 | O63: 3793906.4 | P63: 0.42905747 | R63: 5346634.4 | S63: 0.48264941 | U63: 4779221.5 | V63: 0.43813422 | X63: 3661155.4 | Y63: 0.38987589 | AA63: 4333782.8 | AB63: 0.42280184 | AD63: 6414650.6 | AE63: 0.49734934 | AG63: 6457574.4 | AH63: 0.5213092 | AJ63: 5227974.1 | AK63: 0.4843085 | AM63: 3552582.4 | AN63: 0.4052487
B65: Admin & General
B66: P/R & Related Expenses | C66: 7929088.1 | D66: 0.06499866 | F66: 660477.87 | G66: 0.09122512 | I66: 668925.51 | J66: 0.08044953 | L66: 676408.85 | M66: 0.06083601 | O66: 671255.5 | P66: 0.0759131 | R66: 665671.07 | S66: 0.06009121 | U66: 661370.39 | V66: 0.060631 | X66: 649525.85 | Y66: 0.06916791 | AA66: 651699.65 | AB66: 0.06357951 | AD66: 636463.34 | AE66: 0.04934713 | AG66: 653247.43 | AH66: 0.05273557 | AJ66: 660568.39 | AK66: 0.06119366 | AM66: 673474.19 | AN66: 0.07682427
B67: Other Expenses | C67: 6428748.4 | D67: 0.05269964 | F67: 389592.53 | G67: 0.05381047 | I67: 432294.37 | J67: 0.05199066 | L67: 640303.83 | M67: 0.05758873 | O67: 431062.94 | P67: 0.04874943 | R67: 453868.34 | S67: 0.04097144 | U67: 762894.02 | V67: 0.06993816 | X67: 430059.87 | Y67: 0.04579701 | AA67: 425340.61 | AB67: 0.04149603 | AD67: 584592.82 | AE67: 0.04532544 | AG67: 482259.85 | AH67: 0.03893203 | AJ67: 527652.72 | AK67: 0.04888064 | AM67: 868826.44 | AN67: 0.09910841
B68: Dept Profit/(Loss) | C68: -14357836 | D68: -0.1176983 | F68: -1050070.4 | G68: -0.1450356 | I68: -1101219.9 | J68: -0.1324402 | L68: -1316712.7 | M68: -0.11842474 | O68: -1102318.4 | P68: -0.12466253 | R68: -1119539.4 | S68: -0.10106265 | U68: -1424264.4 | V68: -0.13056917 | X68: -1079585.7 | Y68: -0.11496492 | AA68: -1077040.3 | AB68: -0.10507555 | AD68: -1221056.2 | AE68: -0.09467257 | AG68: -1135507.3 | AH68: -0.09166761 | AJ68: -1188221.1 | AK68: -0.1100743 | AM68: -1542300.6 | AN68: -0.17593268
B70: IT Systems
B71: Cost of Services | C71: 326313.72 | D71: 0.00267496 | F71: 27211.81 | G71: 0.00375849 | I71: 27211.81 | J71: 0.00327268 | L71: 27211.81 | M71: 0.00244742 | O71: 26911.81 | P71: 0.00304349 | R71: 27211.81 | S71: 0.00245645 | U71: 27247.81 | V71: 0.00249794 | X71: 27247.81 | Y71: 0.00290162 | AA71: 27211.81 | AB71: 0.00265477 | AD71: 27211.81 | AE71: 0.00210982 | AG71: 27211.81 | AH71: 0.00219676 | AJ71: 27211.81 | AK71: 0.00252084 | AM71: 27211.81 | AN71: 0.00310409
B72: System Expenses | C72: 2464615 | D72: 0.02020367 | F72: 239328.28 | G72: 0.03305599 | I72: 210187.79 | J72: 0.02527861 | L72: 206203.27 | M72: 0.01854586 | O72: 222616.27 | P72: 0.02517594 | R72: 198190.11 | S72: 0.01789094 | U72: 200852.02 | V72: 0.01841307 | X72: 218616.27 | Y72: 0.02328041 | AA72: 189541.61 | AB72: 0.01849159 | AD72: 189760.78 | AE72: 0.01471279 | AG72: 209792.26 | AH72: 0.01693618 | AJ72: 189541.63 | AK72: 0.01755874 | AM72: 189984.78 | AN72: 0.02167186
B73: Other Expenses | C73: 432061 | D73: 0.00354182 | F73: 39779.25 | G73: 0.00549431 | I73: 95074.25 | J73: 0.01143428 | L73: 60404.25 | M73: 0.00543274 | O73: 56579.25 | P73: 0.00639862 | R73: 49284.25 | S73: 0.00444897 | U73: 26404.25 | V73: 0.0024206 | X73: 14579.25 | Y73: 0.00155254 | AA73: 29284.25 | AB73: 0.00285696 | AD73: 15404.25 | AE73: 0.00119434 | AG73: 15579.25 | AH73: 0.00125769 | AJ73: 14284.25 | AK73: 0.00132326 | AM73: 15404.25 | AN73: 0.00175719
B74: Dept Profit/(Loss) | C74: -3481996.1 | D74: -0.02854365 | F74: -328797.17 | G74: -0.04541343 | I74: -352091.68 | J74: -0.04234494 | L74: -312037.16 | M74: -0.02806453 | O74: -325025.16 | P74: -0.03675749 | R74: -292904 | S74: -0.02644092 | U74: -272721.91 | V74: -0.02500173 | X74: -284333.21 | Y74: -0.0302786 | AA74: -269927.56 | AB74: -0.02633401 | AD74: -256266.72 | AE74: -0.01986922 | AG74: -276473.2 | AH74: -0.02231922 | AJ74: -254927.57 | AK74: -0.02361595 | AM74: -256490.72 | AN74: -0.0292583
B76: Sales & Marketing
B77: P/R & Related Expenses | C77: 6048217 | D77: 0.04958023 | F77: 527846.79 | G77: 0.07290614 | I77: 538872.81 | J77: 0.06480851 | L77: 568510.14 | M77: 0.05113163 | O77: 496466.73 | P77: 0.05614602 | R77: 523734.64 | S77: 0.04727838 | U77: 515792.01 | V77: 0.04728513 | X77: 467824.16 | Y77: 0.04981852 | AA77: 469391.38 | AB77: 0.04579361 | AD77: 501181.18 | AE77: 0.03885826 | AG77: 500068.36 | AH77: 0.04036968 | AJ77: 492674.73 | AK77: 0.04564035 | AM77: 445854.06 | AN77: 0.05085928
B78: Other Expenses | C78: 6980384.4 | D78: 0.05722167 | F78: 510364.3 | G78: 0.07049146 | I78: 583074.15 | J78: 0.07012446 | L78: 669689.84 | M78: 0.0602317 | O78: 531159.24 | P78: 0.06006944 | R78: 594841.56 | S78: 0.05369732 | U78: 572156.23 | V78: 0.05245231 | X78: 517380.82 | Y78: 0.05509581 | AA78: 615541.45 | AB78: 0.06005194 | AD78: 645034.92 | AE78: 0.05001172 | AG78: 640110.74 | AH78: 0.05167507 | AJ78: 591203.36 | AK78: 0.05476783 | AM78: 509827.84 | AN78: 0.05815687
B79: Dept Profit/(Loss) | C79: -13028601 | D79: -0.1068019 | F79: -1038211.1 | G79: -0.14339759 | I79: -1121947 | J79: -0.13493298 | L79: -1238200 | M79: -0.11136333 | O79: -1027626 | P79: -0.11621547 | R79: -1118576.2 | S79: -0.1009757 | U79: -1087948.2 | V79: -0.09973745 | X79: -985204.98 | Y79: -0.10491433 | AA79: -1084932.8 | AB79: -0.10584554 | AD79: -1146216.1 | AE79: -0.08886997 | AG79: -1140179.1 | AH79: -0.09204475 | AJ79: -1083878.1 | AK79: -0.10040818 | AM79: -955681.89 | AN79: -0.10901615
B81: Repair & Maintenance
B82: P/R & Related Expenses | C82: 1902289 | D82: 0.01559401 | F82: 158750.09 | G82: 0.02192654 | I82: 161375.88 | J82: 0.01940816 | L82: 159623.25 | M82: 0.01435647 | O82: 151966.17 | P82: 0.01718604 | R82: 148673.78 | S82: 0.01342102 | U82: 159811.25 | V82: 0.01465067 | X82: 159765.98 | Y82: 0.01701346 | AA82: 153431.26 | AB82: 0.01496868 | AD82: 155864 | AE82: 0.01208466 | AG82: 157674.13 | AH82: 0.01272877 | AJ82: 176924.11 | AK82: 0.01638988 | AM82: 158429.13 | AN82: 0.01807226
B83: Other Expenses | C83: 3062245.8 | D83: 0.02510275 | F83: 253628.9 | G83: 0.03503119 | I83: 260474.07 | J83: 0.03132638 | L83: 286685.71 | M83: 0.02578443 | O83: 260610.03 | P83: 0.0294727 | R83: 244648.84 | S83: 0.02208485 | U83: 254791.71 | V83: 0.02335798 | X83: 240734.5 | Y83: 0.02563578 | AA83: 229329.07 | AB83: 0.02237324 | AD83: 299105.11 | AE83: 0.02319062 | AG83: 268581.58 | AH83: 0.02168214 | AJ83: 224246.52 | AK83: 0.02077373 | AM83: 239409.71 | AN83: 0.02730985
B84: Dept Profit/(Loss) | C84: -4964534.8 | D84: -0.04069675 | F84: -412378.99 | G84: -0.05695774 | I84: -421849.96 | J84: -0.05073455 | L84: -446308.97 | M84: -0.04014089 | O84: -412576.2 | P84: -0.04665874 | R84: -393322.62 | S84: -0.03550588 | U84: -414602.96 | V84: -0.03800865 | X84: -400500.49 | Y84: -0.04264924 | AA84: -382760.33 | AB84: -0.03734192 | AD84: -454969.12 | AE84: -0.03527528 | AG84: -426255.71 | AH84: -0.03441091 | AJ84: -401170.63 | AK84: -0.0371636 | AM84: -397838.84 | AN84: -0.04538211
B86: Energy
B87: Dept Profit/(Loss) | C87: -4885590.7 | D87: -0.04004961 | F87: -401369.41 | G87: -0.05543709 | I87: -398281.28 | J87: -0.04790002 | L87: -469168.37 | M87: -0.04219686 | O87: -389152.38 | P87: -0.04400971 | R87: -387278.83 | S87: -0.03496029 | U87: -383317.37 | V87: -0.03514055 | X87: -389494.2 | Y87: -0.04147718 | AA87: -392467.7 | AB87: -0.03828897 | AD87: -427122.41 | AE87: -0.03311623 | AG87: -417907.22 | AH87: -0.03373695 | AJ87: -433145.92 | AK87: -0.04012573 | AM87: -396885.57 | AN87: -0.04527337
B89: Gross Operating Profit | C89: 30075829 | D89: 0.24654648 | F89: 290044.42 | G89: 0.0400609 | I89: 889605.51 | J89: 0.10699001 | L89: 2812348.5 | M89: 0.25294178 | O89: 1496788.2 | P89: 0.16927359 | R89: 3386770.1 | S89: 0.30572927 | U89: 2841946.4 | V89: 0.26053489 | X89: 2276610.5 | Y89: 0.24243591 | AA89: 2905225.8 | AB89: 0.28343248 | AD89: 4624136 | AE89: 0.35852475 | AG89: 4442699.8 | AH89: 0.35865173 | AJ89: 2818991.9 | AK89: 0.26114547 | AM89: 1290661.9 | AN89: 0.14722785
B91: Non Operating Income below GOP | C91: 6619916.5 | D91: 0.05426674 | F91: 554149.53 | G91: 0.07653907 | I91: 532677 | J91: 0.06406336 | L91: 538309 | M91: 0.04841535 | O91: 538309 | P91: 0.06087802 | R91: 538309 | S91: 0.04859403 | U91: 538309 | V91: 0.04934937 | X91: 688309 | Y91: 0.07329792 | AA91: 538309 | AB91: 0.05251718 | AD91: 538309 | AE91: 0.0417369 | AG91: 538309 | AH91: 0.04345679 | AJ91: 538309 | AK91: 0.04986781 | AM91: 538309 | AN91: 0.06140576
B92: Rent Income Third Parties below GOP | C92: 5599504.5 | D92: 0.04590191 | F92: 486308.53 | G92: 0.06716888 | I92: 464836 | J92: 0.05590434 | L92: 464836 | M92: 0.04180721 | O92: 464836 | P92: 0.05256887 | R92: 464836 | S92: 0.0419615 | U92: 464836 | V92: 0.04261375 | X92: 464836 | Y92: 0.04950032 | AA92: 464836 | AB92: 0.04534918 | AD92: 464836 | AE92: 0.03604029 | AG92: 464836 | AH92: 0.03752543 | AJ92: 464836 | AK92: 0.04306143 | AM92: 464836 | AN92: 0.05302458
B93: Other Income Third Parties below GOP | C93: 206320 | D93: 0.00169131 | F93: 0 | G93: 0 | I93: 0 | J93: 0 | L93: 5632 | M93: 0.00050654 | O93: 5632 | P93: 0.00063693 | R93: 5632 | S93: 0.00050841 | U93: 5632 | V93: 0.00051631 | X93: 155632 | Y93: 0.01657323 | AA93: 5632 | AB93: 0.00054946 | AD93: 5632 | AE93: 0.00043667 | AG93: 5632 | AH93: 0.00045466 | AJ93: 5632 | AK93: 0.00052174 | AM93: 5632 | AN93: 0.00064245
B94: Interest Income | C94: 814092 | D94: 0.00667352 | F94: 67841 | G94: 0.00937019 | I94: 67841 | J94: 0.00815902 | L94: 67841 | M94: 0.0061016 | O94: 67841 | P94: 0.00767222 | R94: 67841 | S94: 0.00612412 | U94: 67841 | V94: 0.00621931 | X94: 67841 | Y94: 0.00722438 | AA94: 67841 | AB94: 0.00661854 | AD94: 67841 | AE94: 0.00525994 | AG94: 67841 | AH94: 0.00547669 | AJ94: 67841 | AK94: 0.00628465 | AM94: 67841 | AN94: 0.00773873
B95: Other Income Pre-Opening | C95: 0 | D95: 0 | F95: 0 | G95: 0 | I95: 0 | J95: 0 | L95: 0 | M95: 0 | O95: 0 | P95: 0 | R95: 0 | S95: 0 | U95: 0 | V95: 0 | X95: 0 | Y95: 0 | AA95: 0 | AB95: 0 | AD95: 0 | AE95: 0 | AG95: 0 | AH95: 0 | AJ95: 0 | AK95: 0 | AM95: 0 | AN95: 0
B97: Non Operating Expenses below GOP | C97: 6788960 | D97: 0.05565247 | F97: 548220 | G97: 0.07572008 | I97: 548220 | J97: 0.06593267 | L97: 553852 | M97: 0.04981328 | O97: 553852 | P97: 0.06263579 | R97: 553852 | S97: 0.04999712 | U97: 553852 | V97: 0.05077428 | X97: 707852 | Y97: 0.07537905 | AA97: 553852 | AB97: 0.05403354 | AD97: 553852 | AE97: 0.042942 | AG97: 553852 | AH97: 0.04471155 | AJ97: 553852 | AK97: 0.05130768 | AM97: 553852 | AN97: 0.06317877
B98: Rent Expenses Third Parties below GOP | C98: 5568000 | D98: 0.04564366 | F98: 464000 | G98: 0.06408762 | I98: 464000 | J98: 0.0558038 | L98: 464000 | M98: 0.04173202 | O98: 464000 | P98: 0.05247432 | R98: 464000 | S98: 0.04188604 | U98: 464000 | V98: 0.04253711 | X98: 464000 | Y98: 0.04941129 | AA98: 464000 | AB98: 0.04526762 | AD98: 464000 | AE98: 0.03597547 | AG98: 464000 | AH98: 0.03745794 | AJ98: 464000 | AK98: 0.04298398 | AM98: 464000 | AN98: 0.05292921
B99: Other Expenses Third Parties below GOP | C99: 1220960 | D99: 0.01000881 | F99: 84220 | G99: 0.01163246 | I99: 84220 | J99: 0.01012887 | L99: 89852 | M99: 0.00808126 | O99: 89852 | P99: 0.01016147 | R99: 89852 | S99: 0.00811109 | U99: 89852 | V99: 0.00823716 | X99: 243852 | Y99: 0.02596776 | AA99: 89852 | AB99: 0.00876592 | AD99: 89852 | AE99: 0.00696653 | AG99: 89852 | AH99: 0.0072536 | AJ99: 89852 | AK99: 0.0083237 | AM99: 89852 | AN99: 0.01024956
B101: Non Operating Profit/Loss of Dept. below GOP | C101: -169043.47 | D101: -0.00138573 | F101: 5929.53 | G101: 0.00081899 | I101: -15543 | J101: -0.00186931 | L101: -15543 | M101: -0.00139793 | O101: -15543 | P101: -0.00175778 | R101: -15543 | S101: -0.00140309 | U101: -15543 | V101: -0.0014249 | X101: -19543 | Y101: -0.00208113 | AA101: -15543 | AB101: -0.00151637 | AD101: -15543 | AE101: -0.0012051 | AG101: -15543 | AH101: -0.00125476 | AJ101: -15543 | AK101: -0.00143987 | AM101: -15543 | AN101: -0.00177301
B103: Profit/Loss before NOP Expenses | C103: 29906785 | D103: 0.24516074 | F103: 295973.95 | G103: 0.04087989 | I103: 874062.51 | J103: 0.10512071 | L103: 2796805.5 | M103: 0.25154385 | O103: 1481245.2 | P103: 0.16751581 | R103: 3371227.1 | S103: 0.30432617 | U103: 2826403.4 | V103: 0.25910999 | X103: 2257067.5 | Y103: 0.24035477 | AA103: 2889682.8 | AB103: 0.28191611 | AD103: 4608593 | AE103: 0.35731965 | AG103: 4427156.8 | AH103: 0.35739697 | AJ103: 2803448.9 | AK103: 0.2597056 | AM103: 1275118.9 | AN103: 0.14545483
... B150: NET PROFIT/LOSS | C150: -3374290.7 | D150: -0.02766073 | F150: -2306059 | G150: -0.31851259 | I150: -1784813.9 | J150: -0.21465387 | L150: -153484.13 | M150: -0.01380432 | O150: -1160559 | P150: -0.13124902 | R150: 544144.21 | S150: 0.04912079 | U150: 109574.91 | V150: 0.01004526 | X150: -334042.88 | Y150: -0.03557218 | AA150: 192960.36 | AB150: 0.01882512 | AD150: 1614012.2 | AE150: 0.12513977 | AG150: 1359896.3 | AH150: 0.10978216 | AJ150: -137237.01 | AK150: -0.01271335 | AM150: -1318682.7 | AN150: -0.15042423
B152: Key Data
B153: EBITDA | C153: -3120046.1 | D153: -0.02557656 | F153: -2284871.9 | G153: -0.31558624 | I153: -1763626.9 | J153: -0.21210577 | L153: -132297.08 | M153: -0.01189876 | O153: -1139371.9 | P153: -0.12885295 | R153: 565331.26 | S153: 0.05103338 | U153: 130761.96 | V153: 0.01198758 | X153: -312855.83 | Y153: -0.03331597 | AA153: 214147.41 | AB153: 0.02089212 | AD153: 1635199.2 | AE153: 0.12678247 | AG153: 1381083.4 | AH153: 0.11149255 | AJ153: -116049.96 | AK153: -0.01075062 | AM153: -1297495.7 | AN153: -0.14800739
B154: EBIT | C154: -3845110.1 | D154: -0.03152027 | F154: -2345293.9 | G154: -0.32393172 | I154: -1824048.9 | J154: -0.21937253 | L154: -192719.08 | M154: -0.0173331 | O154: -1199793.9 | P154: -0.13568615 | R154: 504909.26 | S154: 0.04557898 | U154: 70339.955 | V154: 0.0064484 | X154: -373277.83 | Y154: -0.0397503 | AA154: 153725.41 | AB154: 0.01499738 | AD154: 1574777.2 | AE154: 0.12209775 | AG154: 1320661.4 | AH154: 0.10661479 | AJ154: -176471.96 | AK154: -0.01634799 | AM154: -1357917.7 | AN154: -0.15489982
B155: Fees Details intern | C155: 4160395.5 | D155: 0.03410482 | F155: 254149.82 | G155: 0.03510314 | I155: 294153.17 | J155: 0.03537686 | L155: 391859.56 | M155: 0.03524373 | O155: 307497.56 | P155: 0.03477527 | R155: 379857.78 | S155: 0.03429038 | U155: 361279.76 | V155: 0.03312025 | X155: 297345.39 | Y155: 0.03166427 | AA155: 331319.21 | AB155: 0.03232335 | AD155: 435788.14 | AE155: 0.03378811 | AG155: 431239.47 | AH155: 0.03481324 | AJ155: 383534.56 | AK155: 0.03552983 | AM155: 292371.07 | AN155: 0.03335123
B156: CSC (KST 5) | C156: 0 | D156: 0 | F156: 0 | G156: 0 | I156: 0 | J156: 0 | L156: 0 | M156: 0 | O156: 0 | P156: 0 | R156: 0 | S156: 0 | U156: 0 | V156: 0 | X156: 0 | Y156: 0 | AA156: 0 | AB156: 0 | AD156: 0 | AE156: 0 | AG156: 0 | AH156: 0 | AJ156: 0 | AK156: 0 | AM156: 0 | AN156: 0
B157: RDT (KST 1) | C157: 0 | D157: 0 | F157: 0 | G157: 0 | I157: 0 | J157: 0 | L157: 0 | M157: 0 | O157: 0 | P157: 0 | R157: 0 | S157: 0 | U157: 0 | V157: 0 | X157: 0 | Y157: 0 | AA157: 0 | AB157: 0 | AD157: 0 | AE157: 0 | AG157: 0 | AH157: 0 | AJ157: 0 | AK157: 0 | AM157: 0 | AN157: 0
B158: SSC (KST 60) | C158: 1033052.8 | D158: 0.00846845 | F158: 63797.549 | G158: 0.00881171 | I158: 73127.054 | J158: 0.00879476 | L158: 97560.516 | M158: 0.00877456 | O158: 76822.732 | P158: 0.00868798 | R158: 94280.077 | S158: 0.00851082 | U158: 89524.497 | V158: 0.00820714 | X158: 73869.465 | Y158: 0.00786635 | AA158: 82613.762 | AB158: 0.00805976 | AD158: 106454.55 | AE158: 0.00825378 | AG158: 106889.51 | AH158: 0.00862901 | AJ158: 94884.041 | AK158: 0.00878986 | AM158: 73229.047 | AN158: 0.00835335
B159: Commercial Cluster | C159: 2418669 | D159: 0.01982703 | F159: 150337.35 | G159: 0.02076458 | I159: 171866.75 | J159: 0.02066987 | L159: 230236.88 | M159: 0.02070744 | O159: 177410.19 | P159: 0.02006353 | R159: 219844.95 | S159: 0.01984576 | U159: 207896.76 | V159: 0.0190589 | X159: 169280.7 | Y159: 0.01802668 | AA159: 188180.59 | AB159: 0.01835881 | AD159: 252314.79 | AE159: 0.01956281 | AG159: 252575.04 | AH159: 0.02038996 | AJ159: 227133.1 | AK159: 0.02104113 | AM159: 171591.9 | AN159: 0.01957376
B160: Management Fee (KST 90) | C160: 3127342.7 | D160: 0.02563638 | F160: 190352.27 | G160: 0.02629143 | I160: 221026.12 | J160: 0.02658211 | L160: 294299.04 | M160: 0.02646917 | O160: 230674.83 | P160: 0.0260873 | R160: 285577.7 | S160: 0.02577957 | U160: 271755.26 | V160: 0.02491311 | X160: 223475.93 | Y160: 0.02379792 | AA160: 248705.45 | AB160: 0.02426359 | AD160: 329333.59 | AE160: 0.02553434 | AG160: 324349.96 | AH160: 0.02618423 | AJ160: 288650.52 | AK160: 0.02673998 | AM160: 219142.02 | AN160: 0.02499788
B161: Marketing Fee (KST 62) | C161: 0 | D161: 0 | F161: 0 | G161: 0 | I161: 0 | J161: 0 | L161: 0 | M161: 0 | O161: 0 | P161: 0 | R161: 0 | S161: 0 | U161: 0 | V161: 0 | X161: 0 | Y161: 0 | AA161: 0 | AB161: 0 | AD161: 0 | AE161: 0 | AG161: 0 | AH161: 0 | AJ161: 0 | AK161: 0 | AM161: 0 | AN161: 0
B162: Fees Details extern | C162: 5421528.3 | D162: 0.04444295 | F162: 321800.78 | G162: 0.04444709 | I162: 370816.68 | J162: 0.04459694 | L162: 508313.23 | M162: 0.04571754 | O162: 396081.39 | P162: 0.04479332 | R162: 509182.46 | S162: 0.04596473 | U162: 469049.61 | V162: 0.04300003 | X162: 398502.17 | Y162: 0.04243644 | AA162: 442441.45 | AB162: 0.04316438 | AD162: 559171.65 | AE162: 0.04335445 | AG162: 572548.69 | AH162: 0.0462209 | AJ162: 490725.74 | AK162: 0.0454598 | AM162: 382894.45 | AN162: 0.04367738
B163: Commercial System Fee (KST 1) | C163: 2502065.4 | D163: 0.02051067 | F163: 144249.63 | G163: 0.01992374 | I163: 167507.98 | J163: 0.02014565 | L163: 237601.24 | M163: 0.02136978 | O163: 179874.04 | P163: 0.02034217 | R163: 235614.09 | S163: 0.02126927 | U163: 217667.42 | V163: 0.01995462 | X163: 183219.53 | Y163: 0.01951102 | AA163: 204951 | AB163: 0.01999492 | AD163: 261490.61 | AE163: 0.02027424 | AG163: 270150.91 | AH163: 0.02180883 | AJ163: 226947.76 | AK163: 0.02102396 | AM163: 172791.13 | AN163: 0.01971056
B164: Franchise Fees (KST 62) | C164: 1755859.3 | D164: 0.01439365 | F164: 102437.74 | G164: 0.01414869 | I164: 119315.45 | J164: 0.01434969 | L164: 167411.34 | M164: 0.01505693 | O164: 126269.81 | P164: 0.01428001 | R164: 164536.08 | S164: 0.01485294 | U164: 151240.55 | V164: 0.01386495 | X164: 126618.88 | Y164: 0.01348363 | AA164: 141832.37 | AB164: 0.0138371 | AD164: 183333.52 | AE164: 0.01421446 | AG164: 189808.14 | AH164: 0.01532289 | AJ164: 160826.74 | AK164: 0.01489865 | AM164: 122228.65 | AN164: 0.01394282
... B166: Loyalty Fee (KST 62) | C166: 571514.41 | D166: 0.00468499 | F166: 34005.262 | G166: 0.0046968 | I166: 40279.43 | J166: 0.00484428 | L166: 53194.912 | M166: 0.00478433 | O166: 42762.072 | P166: 0.00483601 | R166: 52977.21 | S166: 0.00478234 | U166: 50024.162 | V166: 0.00458596 | X166: 40972.412 | Y166: 0.00436315 | AA166: 44546.867 | AB166: 0.00434597 | AD166: 59648.585 | AE166: 0.00462475 | AG166: 59295.436 | AH166: 0.00478682 | AJ166: 52691.744 | AK166: 0.00488125 | AM166: 41116.319 | AN166: 0.0046902
B168: Run Date: 2024-12-14 14:35:05

Sheet Reporting
A1: Reporting zur Liquidität | B1: 45800
A2: LH AG 2025 | B2: December | F2: January | J2: February | N2: March | R2: April | V2: Mai | Z2: June | AD2: Sum
B3: Actual | C3: Plan | D3: Diff | F3: Actual | G3: Plan | H3: Diff | J3: Actual | K3: Plan | L3: Diff | N3: Actual | O3: Plan | P3: Diff | R3: Actual | S3: Plan | T3: Diff | V3: Actual | W3: Plan | X3: Diff | Z3: Actual | AA3: Plan | AB3: Diff | AD3: Diff
A5: Opening Balance | B5: =Dezember24!R4 -> 3000000 | C5: 3000000 | D5: =B5-'Exec.Summary_Liquiplanung ORG'!B4 -> 0 | F5: =Januar!B4 -> 3442499.7 | G5: 4761468.8 | H5: =F5-'Exec.Summary_Liquiplanung ORG'!C4 -> -1318969 | J5: =Februar!B4 -> 4095387.8 | K5: 6114525.2 | L5: =J5-'Exec.Summary_Liquiplanung ORG'!D4 -> -2019137.4 | N5: =März!B6 -> 4710438.2 | O5: 6704388.9 | P5: =N5-'Exec.Summary_Liquiplanung ORG'!E4 -> -1993950.7 | R5: =April!B4 -> 8081456.3 | S5: 5525812.8 | T5: =R5-'Exec.Summary_Liquiplanung ORG'!F4 -> 2555643.5 | V5: =Mai!B4 -> 10995169 | W5: 4526136.2 | X5: =V5-'Exec.Summary_Liquiplanung ORG'!G4 -> 6469033.1 | Z5: =Juni!B4 -> 9104878.3 | AA5: 4258286.9 | AB5: =Z5-'Exec.Summary_Liquiplanung ORG'!H4 -> 4846591.4
A6: Tagesgeld | B6: =Dezember24!AH5 -> 0 | C6: 0 | D6: =B6-'Exec.Summary_Liquiplanung ORG'!B5 -> 0 | F6: =Januar!AH5 -> 0 | G6: 0 | H6: =F6-'Exec.Summary_Liquiplanung ORG'!C5 -> 0 | J6: =Februar!AH5 -> 0 | K6: 0 | L6: =J6-'Exec.Summary_Liquiplanung ORG'!D5 -> 0 | N6: =März!AH5 -> 0 | O6: 0 | P6: =N6-'Exec.Summary_Liquiplanung ORG'!E5 -> 0 | R6: =April!AH5 -> 0 | S6: 0 | T6: =R6-'Exec.Summary_Liquiplanung ORG'!F5 -> 0 | V6: =Mai!AH5 -> 0 | W6: 0 | X6: =V6-'Exec.Summary_Liquiplanung ORG'!G5 -> 0 | Z6: =Juni!AH5 -> 0 | AA6: 0 | AB6: =Z6-'Exec.Summary_Liquiplanung ORG'!H5 -> 0
A7: Summe | B7: =Dezember24!AH6 -> 0 | C7: 0 | D7: =B7-'Exec.Summary_Liquiplanung ORG'!B6 -> 0 | F7: =Januar!AH6 -> 3442499.7 | G7: 4761468.8 | H7: =F7-'Exec.Summary_Liquiplanung ORG'!C6 -> -1318969 | J7: =Februar!AH6 -> 4095387.8 | K7: 6114525.2 | L7: =J7-'Exec.Summary_Liquiplanung ORG'!D6 -> -2019137.4 | N7: =März!AH6 -> 4710438.2 | O7: 6704388.9 | P7: =N7-'Exec.Summary_Liquiplanung ORG'!E6 -> -1993950.7 | R7: =April!AH6 -> 8081456.3 | S7: 5525812.8 | T7: =R7-'Exec.Summary_Liquiplanung ORG'!F6 -> 2555643.5 | V7: =Mai!AH6 -> 10995169 | W7: 4526136.2 | X7: =V7-'Exec.Summary_Liquiplanung ORG'!G6 -> 6469033.1 | Z7: =Juni!AH6 -> 9104878.3 | AA7: 4258286.9 | AB7: =Z7-'Exec.Summary_Liquiplanung ORG'!H6 -> 4846591.4
A8: AUSGABEN | V8: =Mai!AH7 | Z8: =Juni!AH7
A9: Pacht | B9: =Dezember24!AH8 -> 0 | C9: 0 | D9: =B9-'Exec.Summary_Liquiplanung ORG'!B8 -> 0 | F9: =Januar!AH8 -> 1336978.3 | G9: 1985625.6 | H9: =F9-'Exec.Summary_Liquiplanung ORG'!C8 -> -648647.27 | J9: =Februar!AH8 -> -227726.6 | K9: 0 | L9: =J9-'Exec.Summary_Liquiplanung ORG'!D8 -> -227726.6 | N9: =März!AH8 -> 1756520.4 | O9: 2155965.1 | P9: =N9-'Exec.Summary_Liquiplanung ORG'!E8 -> -399444.71 | R9: =April!AH8 -> 2715108 | S9: 1910266.6 | T9: =R9-'Exec.Summary_Liquiplanung ORG'!F8 -> 804841.39 | V9: =Mai!AH8 -> 3884517 | W9: 2025043.1 | X9: =V9-'Exec.Summary_Liquiplanung ORG'!G8 -> 1859473.9 | Z9: =Juni!AH8 -> 0 | AA9: 1910725.9 | AB9: =Z9-'Exec.Summary_Liquiplanung ORG'!H8 -> -1910725.9 | AD9: -621610.88 | AF9: Reduktion der Pachtzahlungen
A10: Annuität ext. | B10: =Dezember24!AH9 -> 0 | C10: 0 | D10: =B10-'Exec.Summary_Liquiplanung ORG'!B9 -> 0 | F10: =Januar!AH9 -> 0 | G10: 0 | H10: =F10-'Exec.Summary_Liquiplanung ORG'!C9 -> 0 | J10: =Februar!AH9 -> 0 | K10: 0 | L10: =J10-'Exec.Summary_Liquiplanung ORG'!D9 -> 0 | N10: =März!AH9 -> 0 | O10: 0 | P10: =N10-'Exec.Summary_Liquiplanung ORG'!E9 -> 0 | R10: =April!AH9 -> 0 | S10: 0 | T10: =R10-'Exec.Summary_Liquiplanung ORG'!F9 -> 0 | V10: =Mai!AH9 -> 0 | W10: 0 | X10: =V10-'Exec.Summary_Liquiplanung ORG'!G9 -> 0 | Z10: =Juni!AH9 -> 0 | AA10: 0 | AB10: =Z10-'Exec.Summary_Liquiplanung ORG'!H9 -> 0 | AD10: 0
A11: Kreditorenzahlungen | B11: =Dezember24!AH10 -> 65390 | C11: 1250000 | D11: =B11-'Exec.Summary_Liquiplanung ORG'!B10 -> -1184610 | F11: =Januar!AH10 -> 2712411.1 | G11: 4050000 | H11: =F11-'Exec.Summary_Liquiplanung ORG'!C10 -> -1337588.9 | J11: =Februar!AH10 -> 5020228.1 | K11: 5142904.9 | L11: =J11-'Exec.Summary_Liquiplanung ORG'!D10 -> -122676.8 | N11: =März!AH10 -> 3209571.6 | O11: 6097028.3 | P11: =N11-'Exec.Summary_Liquiplanung ORG'!E10 -> -2887456.6 | R11: =April!AH10 -> 1978234.2 | S11: 4826493.1 | T11: =R11-'Exec.Summary_Liquiplanung ORG'!F10 -> -2848258.9 | V11: =Mai!AH10 -> 4806305 | W11: 5720424.9 | X11: =V11-'Exec.Summary_Liquiplanung ORG'!G10 -> -914119.98 | Z11: =Juni!AH10 -> 5122538.2 | AA11: 6099134.1 | AB11: =Z11-'Exec.Summary_Liquiplanung ORG'!H10 -> -976595.92 | AD11: -1397337.4 | AF11: Anpassung Kreditoren
A12: Aktivbank/Progros | B12: =Dezember24!AH11 -> 0 | C12: 0 | D12: =B12-'Exec.Summary_Liquiplanung ORG'!B11 -> 0 | F12: =Januar!AH11 -> 80069 | G12: 0 | H12: =F12-'Exec.Summary_Liquiplanung ORG'!C11 -> 80069 | J12: =Februar!AH11 -> 0 | K12: 0 | L12: =J12-'Exec.Summary_Liquiplanung ORG'!D11 -> 0 | N12: =März!AH11 -> 0 | O12: 0 | P12: =N12-'Exec.Summary_Liquiplanung ORG'!E11 -> 0 | R12: =April!AH11 -> 0 | S12: 0 | T12: =R12-'Exec.Summary_Liquiplanung ORG'!F11 -> 0 | V12: =Mai!AH11 -> 0 | W12: 0 | X12: =V12-'Exec.Summary_Liquiplanung ORG'!G11 -> 0 | Z12: =Juni!AH11 -> 0 | AA12: 0 | AB12: =Z12-'Exec.Summary_Liquiplanung ORG'!H11 -> 0 | AD12: 80069
A13: Lastschriften | B13: =Dezember24!AH12 -> 0 | C13: 0 | D13: =B13-'Exec.Summary_Liquiplanung ORG'!B12 -> 0 | F13: =Januar!AH12 -> 541051.79 | G13: 0 | H13: =F13-'Exec.Summary_Liquiplanung ORG'!C12 -> 541051.79 | J13: =Februar!AH12 -> 0 | K13: 0 | L13: =J13-'Exec.Summary_Liquiplanung ORG'!D12 -> 0 | N13: =März!AH12 -> 0 | O13: 0 | P13: =N13-'Exec.Summary_Liquiplanung ORG'!E12 -> 0 | R13: =April!AH12 -> 0 | S13: 0 | T13: =R13-'Exec.Summary_Liquiplanung ORG'!F12 -> 0 | V13: =Mai!AH12 -> 0 | W13: 0 | X13: =V13-'Exec.Summary_Liquiplanung ORG'!G12 -> 0 | Z13: =Juni!AH12 -> 0 | AA13: 0 | AB13: =Z13-'Exec.Summary_Liquiplanung ORG'!H12 -> 0 | AD13: 541051.79
A14: Energiedienstleister | B14: =Dezember24!AH13 -> 0 | C14: 0 | D14: =B14-'Exec.Summary_Liquiplanung ORG'!B13 -> 0 | F14: =Januar!AH13 -> 148000 | G14: 0 | H14: =F14-'Exec.Summary_Liquiplanung ORG'!C13 -> 148000 | J14: =Februar!AH13 -> 0 | K14: 0 | L14: =J14-'Exec.Summary_Liquiplanung ORG'!D13 -> 0 | N14: =März!AH13 -> 0 | O14: 0 | P14: =N14-'Exec.Summary_Liquiplanung ORG'!E13 -> 0 | R14: =April!AH13 -> 0 | S14: 0 | T14: =R14-'Exec.Summary_Liquiplanung ORG'!F13 -> 0 | V14: =Mai!AH13 -> 0 | W14: 0 | X14: =V14-'Exec.Summary_Liquiplanung ORG'!G13 -> 0 | Z14: =Juni!AH13 -> 0 | AA14: 0 | AB14: =Z14-'Exec.Summary_Liquiplanung ORG'!H13 -> 0 | AD14: 148000
A15: Telekommunikation | B15: =Dezember24!AH14 -> 0 | C15: 0 | D15: =B15-'Exec.Summary_Liquiplanung ORG'!B14 -> 0 | F15: =Januar!AH14 -> 393051.79 | G15: 0 | H15: =F15-'Exec.Summary_Liquiplanung ORG'!C14 -> 393051.79 | J15: =Februar!AH14 -> 0 | K15: 0 | L15: =J15-'Exec.Summary_Liquiplanung ORG'!D14 -> 0 | N15: =März!AH14 -> 0 | O15: 0 | P15: =N15-'Exec.Summary_Liquiplanung ORG'!E14 -> 0 | R15: =April!AH14 -> 0 | S15: 0 | T15: =R15-'Exec.Summary_Liquiplanung ORG'!F14 -> 0 | V15: =Mai!AH14 -> 0 | W15: 0 | X15: =V15-'Exec.Summary_Liquiplanung ORG'!G14 -> 0 | Z15: =Juni!AH14 -> 0 | AA15: 0 | AB15: =Z15-'Exec.Summary_Liquiplanung ORG'!H14 -> 0 | AD15: 393051.79
A16: Gebühren CC | B16: =Dezember24!AH15 -> 0 | C16: 0 | D16: =B16-'Exec.Summary_Liquiplanung ORG'!B15 -> 0 | F16: =Januar!AH15 -> 0 | G16: 0 | H16: =F16-'Exec.Summary_Liquiplanung ORG'!C15 -> 0 | J16: =Februar!AH15 -> 0 | K16: 0 | L16: =J16-'Exec.Summary_Liquiplanung ORG'!D15 -> 0 | N16: =März!AH15 -> 0 | O16: 0 | P16: =N16-'Exec.Summary_Liquiplanung ORG'!E15 -> 0 | R16: =April!AH15 -> 0 | S16: 0 | T16: =R16-'Exec.Summary_Liquiplanung ORG'!F15 -> 0 | V16: =Mai!AH15 -> 0 | W16: 0 | X16: =V16-'Exec.Summary_Liquiplanung ORG'!G15 -> 0 | Z16: =Juni!AH15 -> 0 | AA16: 0 | AB16: =Z16-'Exec.Summary_Liquiplanung ORG'!H15 -> 0 | AD16: 0
A17: Provisonen( Booking, Expedia | B17: =Dezember24!AH16 -> 0 | C17: 0 | D17: =B17-'Exec.Summary_Liquiplanung ORG'!B16 -> 0 | F17: =Januar!AH16 -> 0 | G17: 0 | H17: =F17-'Exec.Summary_Liquiplanung ORG'!C16 -> 0 | J17: =Februar!AH16 -> 0 | K17: 0 | L17: =J17-'Exec.Summary_Liquiplanung ORG'!D16 -> 0 | N17: =März!AH16 -> 0 | O17: 0 | P17: =N17-'Exec.Summary_Liquiplanung ORG'!E16 -> 0 | R17: =April!AH16 -> 0 | S17: 0 | T17: =R17-'Exec.Summary_Liquiplanung ORG'!F16 -> 0 | V17: =Mai!AH16 -> 0 | W17: 0 | X17: =V17-'Exec.Summary_Liquiplanung ORG'!G16 -> 0 | Z17: =Juni!AH16 -> 0 | AA17: 0 | AB17: =Z17-'Exec.Summary_Liquiplanung ORG'!H16 -> 0 | AD17: 0
A18: KFZ Leasing | B18: =Dezember24!AH17 -> 0 | C18: 0 | D18: =B18-'Exec.Summary_Liquiplanung ORG'!B17 -> 0 | F18: =Januar!AH17 -> 0 | G18: 0 | H18: =F18-'Exec.Summary_Liquiplanung ORG'!C17 -> 0 | J18: =Februar!AH17 -> 0 | K18: 0 | L18: =J18-'Exec.Summary_Liquiplanung ORG'!D17 -> 0 | N18: =März!AH17 -> 0 | O18: 0 | P18: =N18-'Exec.Summary_Liquiplanung ORG'!E17 -> 0 | R18: =April!AH17 -> 0 | S18: 0 | T18: =R18-'Exec.Summary_Liquiplanung ORG'!F17 -> 0 | V18: =Mai!AH17 -> 0 | W18: 0 | X18: =V18-'Exec.Summary_Liquiplanung ORG'!G17 -> 0 | Z18: =Juni!AH17 -> 0 | AA18: 0 | AB18: =Z18-'Exec.Summary_Liquiplanung ORG'!H17 -> 0 | AD18: 0
A19: Jobtickets | B19: =Dezember24!AH18 -> 0 | C19: 0 | D19: =B19-'Exec.Summary_Liquiplanung ORG'!B18 -> 0 | F19: =Januar!AH18 -> 0 | G19: 0 | H19: =F19-'Exec.Summary_Liquiplanung ORG'!C18 -> 0 | J19: =Februar!AH18 -> 0 | K19: 0 | L19: =J19-'Exec.Summary_Liquiplanung ORG'!D18 -> 0 | N19: =März!AH18 -> 0 | O19: 0 | P19: =N19-'Exec.Summary_Liquiplanung ORG'!E18 -> 0 | R19: =April!AH18 -> 0 | S19: 0 | T19: =R19-'Exec.Summary_Liquiplanung ORG'!F18 -> 0 | V19: =Mai!AH18 -> 0 | W19: 0 | X19: =V19-'Exec.Summary_Liquiplanung ORG'!G18 -> 0 | Z19: =Juni!AH18 -> 0 | AA19: 0 | AB19: =Z19-'Exec.Summary_Liquiplanung ORG'!H18 -> 0 | AD19: 0
A20: Leasing | B20: =Dezember24!AH19 -> 0 | C20: 0 | D20: =B20-'Exec.Summary_Liquiplanung ORG'!B19 -> 0 | F20: =Januar!AH19 -> 0 | G20: 0 | H20: =F20-'Exec.Summary_Liquiplanung ORG'!C19 -> 0 | J20: =Februar!AH19 -> 0 | K20: 0 | L20: =J20-'Exec.Summary_Liquiplanung ORG'!D19 -> 0 | N20: =März!AH19 -> 0 | O20: 0 | P20: =N20-'Exec.Summary_Liquiplanung ORG'!E19 -> 0 | R20: =April!AH19 -> 0 | S20: 0 | T20: =R20-'Exec.Summary_Liquiplanung ORG'!F19 -> 0 | V20: =Mai!AH19 -> 0 | W20: 0 | X20: =V20-'Exec.Summary_Liquiplanung ORG'!G19 -> 0 | Z20: =Juni!AH19 -> 0 | AA20: 0 | AB20: =Z20-'Exec.Summary_Liquiplanung ORG'!H19 -> 0 | AD20: 0
A21: Gema/GEZ/Sky | B21: =Dezember24!AH20 -> 0 | C21: 0 | D21: =B21-'Exec.Summary_Liquiplanung ORG'!B20 -> 0 | F21: =Januar!AH20 -> 0 | G21: 0 | H21: =F21-'Exec.Summary_Liquiplanung ORG'!C20 -> 0 | J21: =Februar!AH20 -> 0 | K21: 0 | L21: =J21-'Exec.Summary_Liquiplanung ORG'!D20 -> 0 | N21: =März!AH20 -> 0 | O21: 0 | P21: =N21-'Exec.Summary_Liquiplanung ORG'!E20 -> 0 | R21: =April!AH20 -> 0 | S21: 0 | T21: =R21-'Exec.Summary_Liquiplanung ORG'!F20 -> 0 | V21: =Mai!AH20 -> 0 | W21: 0 | X21: =V21-'Exec.Summary_Liquiplanung ORG'!G20 -> 0 | Z21: =Juni!AH20 -> 0 | AA21: 0 | AB21: =Z21-'Exec.Summary_Liquiplanung ORG'!H20 -> 0 | AD21: 0
A22: Sonepar/Haustechnik | B22: =Dezember24!AH21 -> 0 | C22: 0 | D22: =B22-'Exec.Summary_Liquiplanung ORG'!B21 -> 0 | F22: =Januar!AH21 -> 0 | G22: 0 | H22: =F22-'Exec.Summary_Liquiplanung ORG'!C21 -> 0 | J22: =Februar!AH21 -> 0 | K22: 0 | L22: =J22-'Exec.Summary_Liquiplanung ORG'!D21 -> 0 | N22: =März!AH21 -> 0 | O22: 0 | P22: =N22-'Exec.Summary_Liquiplanung ORG'!E21 -> 0 | R22: =April!AH21 -> 0 | S22: 0 | T22: =R22-'Exec.Summary_Liquiplanung ORG'!F21 -> 0 | V22: =Mai!AH21 -> 0 | W22: 0 | X22: =V22-'Exec.Summary_Liquiplanung ORG'!G21 -> 0 | Z22: =Juni!AH21 -> 0 | AA22: 0 | AB22: =Z22-'Exec.Summary_Liquiplanung ORG'!H21 -> 0 | AD22: 0
A23: Airplus | B23: =Dezember24!AH22 -> 0 | C23: 0 | D23: =B23-'Exec.Summary_Liquiplanung ORG'!B22 -> 0 | F23: =Januar!AH22 -> 0 | G23: 0 | H23: =F23-'Exec.Summary_Liquiplanung ORG'!C22 -> 0 | J23: =Februar!AH22 -> 0 | K23: 0 | L23: =J23-'Exec.Summary_Liquiplanung ORG'!D22 -> 0 | N23: =März!AH22 -> 0 | O23: 0 | P23: =N23-'Exec.Summary_Liquiplanung ORG'!E22 -> 0 | R23: =April!AH22 -> 0 | S23: 0 | T23: =R23-'Exec.Summary_Liquiplanung ORG'!F22 -> 0 | V23: =Mai!AH22 -> 0 | W23: 0 | X23: =V23-'Exec.Summary_Liquiplanung ORG'!G22 -> 0 | Z23: =Juni!AH22 -> 0 | AA23: 0 | AB23: =Z23-'Exec.Summary_Liquiplanung ORG'!H22 -> 0 | AD23: 0
A24: BGN/Schwerbeh.abgabe | B24: =Dezember24!AH23 -> 0 | C24: 0 | D24: =B24-'Exec.Summary_Liquiplanung ORG'!B23 -> 0 | F24: =Januar!AH23 -> 0 | G24: 60000 | H24: =F24-'Exec.Summary_Liquiplanung ORG'!C23 -> -60000 | J24: =Februar!AH23 -> 0 | K24: 0 | L24: =J24-'Exec.Summary_Liquiplanung ORG'!D23 -> 0 | N24: =März!AH23 -> 60000 | O24: 60000 | P24: =N24-'Exec.Summary_Liquiplanung ORG'!E23 -> 0 | R24: =April!AH23 -> 0 | S24: 0 | T24: =R24-'Exec.Summary_Liquiplanung ORG'!F23 -> 0 | V24: =Mai!AH23 -> 60000 | W24: 60000 | X24: =V24-'Exec.Summary_Liquiplanung ORG'!G23 -> 0 | Z24: =Juni!AH23 -> 0 | AA24: 0 | AB24: =Z24-'Exec.Summary_Liquiplanung ORG'!H23 -> 0 | AD24: -60000
A25: interne Zahlungen | B25: =Dezember24!AH24 -> 0 | C25: 0 | D25: =B25-'Exec.Summary_Liquiplanung ORG'!B24 -> 0 | F25: =Januar!AH24 -> 0 | G25: 100000 | H25: =F25-'Exec.Summary_Liquiplanung ORG'!C24 -> -100000 | J25: =Februar!AH24 -> 0 | K25: 100000 | L25: =J25-'Exec.Summary_Liquiplanung ORG'!D24 -> -100000 | N25: =März!AH24 -> 0 | O25: 100000 | P25: =N25-'Exec.Summary_Liquiplanung ORG'!E24 -> -100000 | R25: =April!AH24 -> 50000 | S25: 100000 | T25: =R25-'Exec.Summary_Liquiplanung ORG'!F24 -> -50000 | V25: =Mai!AH24 -> 50000 | W25: 100000 | X25: =V25-'Exec.Summary_Liquiplanung ORG'!G24 -> -50000 | Z25: =Juni!AH24 -> 50000 | AA25: 100000 | AB25: =Z25-'Exec.Summary_Liquiplanung ORG'!H24 -> -50000 | AD25: -300000 | AF25: Finanzierung von Tochtergesellschaften reduziert
A26: City Taxes | B26: =Dezember24!AH25 -> 0 | C26: 0 | D26: =B26-'Exec.Summary_Liquiplanung ORG'!B25 -> 0 | F26: =Januar!AH25 -> 0 | G26: 180000 | H26: =F26-'Exec.Summary_Liquiplanung ORG'!C25 -> -180000 | J26: =Februar!AH25 -> 0 | K26: 10000 | L26: =J26-'Exec.Summary_Liquiplanung ORG'!D25 -> -10000 | N26: =März!AH25 -> 0 | O26: 10000 | P26: =N26-'Exec.Summary_Liquiplanung ORG'!E25 -> -10000 | R26: =April!AH25 -> 250000 | S26: 250000 | T26: =R26-'Exec.Summary_Liquiplanung ORG'!F25 -> 0 | V26: =Mai!AH25 -> 265000 | W26: 20000 | X26: =V26-'Exec.Summary_Liquiplanung ORG'!G25 -> 245000 | Z26: =Juni!AH25 -> 0 | AA26: 0 | AB26: =Z26-'Exec.Summary_Liquiplanung ORG'!H25 -> 0 | AD26: -50000 | AF26: Anpassung an Umsatzerwartung
A27: L&G | B27: =Dezember24!AH26 -> 0 | C27: 170000 | D27: =B27-'Exec.Summary_Liquiplanung ORG'!B26 -> -170000 | F27: =Januar!AH26 -> 42140 | G27: 170000 | H27: =F27-'Exec.Summary_Liquiplanung ORG'!C26 -> -127860 | J27: =Februar!AH26 -> 170000 | K27: 170000 | L27: =J27-'Exec.Summary_Liquiplanung ORG'!D26 -> 0 | N27: =März!AH26 -> 1429283.5 | O27: 1550000 | P27: =N27-'Exec.Summary_Liquiplanung ORG'!E26 -> -120716.51 | R27: =April!AH26 -> 1500000 | S27: 1550000 | T27: =R27-'Exec.Summary_Liquiplanung ORG'!F26 -> -50000 | V27: =Mai!AH26 -> 1500000 | W27: 1550000 | X27: =V27-'Exec.Summary_Liquiplanung ORG'!G26 -> -50000 | Z27: =Juni!AH26 -> 1500000 | AA27: 1550000 | AB27: =Z27-'Exec.Summary_Liquiplanung ORG'!H26 -> -50000 | AD27: -359860 | AF27: Anpassung an Umsatzerwartung
A28: Krankenkasse | B28: =Dezember24!AH27 -> 0 | C28: 0 | D28: =B28-'Exec.Summary_Liquiplanung ORG'!B27 -> 0 | F28: =Januar!AH27 -> 0 | G28: 0 | H28: =F28-'Exec.Summary_Liquiplanung ORG'!C27 -> 0 | J28: =Februar!AH27 -> 0 | K28: 0 | L28: =J28-'Exec.Summary_Liquiplanung ORG'!D27 -> 0 | N28: =März!AH27 -> 805613.08 | O28: 850000 | P28: =N28-'Exec.Summary_Liquiplanung ORG'!E27 -> -44386.92 | R28: =April!AH27 -> 850000 | S28: 850000 | T28: =R28-'Exec.Summary_Liquiplanung ORG'!F27 -> 0 | V28: =Mai!AH27 -> 850000 | W28: 850000 | X28: =V28-'Exec.Summary_Liquiplanung ORG'!G27 -> 0 | Z28: =Juni!AH27 -> 850000 | AA28: 850000 | AB28: =Z28-'Exec.Summary_Liquiplanung ORG'!H27 -> 0 | AD28: 0
A29: Lohnsteuer | B29: =Dezember24!AH28 -> 0 | C29: 0 | D29: =B29-'Exec.Summary_Liquiplanung ORG'!B28 -> 0 | F29: =Januar!AH28 -> 0 | G29: 0 | H29: =F29-'Exec.Summary_Liquiplanung ORG'!C28 -> 0 | J29: =Februar!AH28 -> 0 | K29: 0 | L29: =J29-'Exec.Summary_Liquiplanung ORG'!D28 -> 0 | N29: =März!AH28 -> 551000 | O29: 350000 | P29: =N29-'Exec.Summary_Liquiplanung ORG'!E28 -> 201000 | R29: =April!AH28 -> 350000 | S29: 350000 | T29: =R29-'Exec.Summary_Liquiplanung ORG'!F28 -> 0 | V29: =Mai!AH28 -> 350000 | W29: 350000 | X29: =V29-'Exec.Summary_Liquiplanung ORG'!G28 -> 0 | Z29: =Juni!AH28 -> 350000 | AA29: 350000 | AB29: =Z29-'Exec.Summary_Liquiplanung ORG'!H28 -> 0 | AD29: 230000 | AF29: Anpassung an Umsatzerwartung
A30: UST | B30: =Dezember24!AH29 -> 0 | C30: 0 | D30: =B30-'Exec.Summary_Liquiplanung ORG'!B29 -> 0 | F30: =Januar!AH29 -> 0 | G30: -350314.99 | H30: =F30-'Exec.Summary_Liquiplanung ORG'!C29 -> 350314.99 | J30: =Februar!AH29 -> 0 | K30: -73565.065 | L30: =J30-'Exec.Summary_Liquiplanung ORG'!D29 -> 73565.065 | N30: =März!AH29 -> 0 | O30: -327098.98 | P30: =N30-'Exec.Summary_Liquiplanung ORG'!E29 -> 327098.98 | R30: =April!AH29 -> 166115.03 | S30: -318831.01 | T30: =R30-'Exec.Summary_Liquiplanung ORG'!F29 -> 484946.04 | V30: =Mai!AH29 -> 150000 | W30: -251345.76 | X30: =V30-'Exec.Summary_Liquiplanung ORG'!G29 -> 401345.76 | Z30: =Juni!AH29 -> 150000 | AA30: -296063.43 | AB30: =Z30-'Exec.Summary_Liquiplanung ORG'!H29 -> 446063.43 | AD30: 750980.23 | AF30: Ust Erstattung in Januar bis März nicht zu erwarten
A31: Berater-/ Verfahrenskosten Insolvenzverfahren | B31: =Dezember24!AH30 -> 0 | C31: 0 | D31: =B31-'Exec.Summary_Liquiplanung ORG'!B30 -> 0 | F31: =Januar!AH30 -> 0 | G31: 0 | H31: =F31-'Exec.Summary_Liquiplanung ORG'!C30 -> 0 | J31: =Februar!AH30 -> 1500000 | K31: 1500000 | L31: =J31-'Exec.Summary_Liquiplanung ORG'!D30 -> 0 | N31: =März!AH30 -> 0 | O31: 0 | P31: =N31-'Exec.Summary_Liquiplanung ORG'!E30 -> 0 | R31: =April!AH30 -> 0 | S31: 0 | T31: =R31-'Exec.Summary_Liquiplanung ORG'!F30 -> 0 | V31: =Mai!AH30 -> 0 | W31: 0 | X31: =V31-'Exec.Summary_Liquiplanung ORG'!G30 -> 0 | Z31: =Juni!AH30 -> 0 | AA31: 2400000 | AB31: =Z31-'Exec.Summary_Liquiplanung ORG'!H30 -> -2400000 | AD31: 0
A32: div. Abbuchungen | B32: =Dezember24!AH31 -> 0 | C32: 0 | D32: =B32-'Exec.Summary_Liquiplanung ORG'!B31 -> 0 | F32: =Januar!AH31 -> 0 | G32: 0 | H32: =F32-'Exec.Summary_Liquiplanung ORG'!C31 -> 0 | J32: =Februar!AH31 -> 98500 | K32: 0 | L32: =J32-'Exec.Summary_Liquiplanung ORG'!D31 -> 98500 | N32: =März!AH31 -> 0 | O32: 0 | P32: =N32-'Exec.Summary_Liquiplanung ORG'!E31 -> 0 | R32: =April!AH31 -> 0 | S32: 0 | T32: =R32-'Exec.Summary_Liquiplanung ORG'!F31 -> 0 | V32: =Mai!AH31 -> 0 | W32: 0 | X32: =V32-'Exec.Summary_Liquiplanung ORG'!G31 -> 0 | Z32: =Juni!AH31 -> 0 | AA32: 0 | AB32: =Z32-'Exec.Summary_Liquiplanung ORG'!H31 -> 0 | AD32: 0
A33: Summe Ausgaben | B33: =Dezember24!AH32 -> 65390 | C33: 1420000 | D33: =B33-'Exec.Summary_Liquiplanung ORG'!B32 -> -1354610 | F33: =Januar!AH32 -> 4712650.2 | G33: 6195310.6 | H33: =F33-'Exec.Summary_Liquiplanung ORG'!C32 -> -1482660.4 | J33: =Februar!AH32 -> 6561001.5 | K33: 6849339.9 | L33: =J33-'Exec.Summary_Liquiplanung ORG'!D32 -> -288338.33 | N33: =März!AH32 -> 7811988.6 | O33: 10845894 | P33: =N33-'Exec.Summary_Liquiplanung ORG'!E32 -> -3033905.8 | R33: =April!AH32 -> 7859457.2 | S33: 9517928.7 | T33: =R33-'Exec.Summary_Liquiplanung ORG'!F32 -> -1658471.4 | V33: =Mai!AH32 -> 11915822 | W33: 10424122 | X33: =V33-'Exec.Summary_Liquiplanung ORG'!G32 -> 1491699.7 | Z33: =Juni!AH32 -> 8022538.2 | AA33: 12963797 | AB33: =Z33-'Exec.Summary_Liquiplanung ORG'!H32 -> -4941258.4 | AD33: -1186707.3
D34: =B34-'Exec.Summary_Liquiplanung ORG'!B33 -> 0 | H34: =F34-'Exec.Summary_Liquiplanung ORG'!C33 -> 0 | L34: =J34-'Exec.Summary_Liquiplanung ORG'!D33 -> 0 | P34: =N34-'Exec.Summary_Liquiplanung ORG'!E33 -> 0 | T34: =R34-'Exec.Summary_Liquiplanung ORG'!F33 -> 0 | X34: =V34-'Exec.Summary_Liquiplanung ORG'!G33 -> 0 | AB34: =Z34-'Exec.Summary_Liquiplanung ORG'!H33 -> 0 | AD34: 0
A35: EINNAHMEN
A36: Vorauszahlungen | B36: =Dezember24!AH35 -> 0 | C36: 0 | D36: =B36-'Exec.Summary_Liquiplanung ORG'!B35 -> 0 | F36: =Januar!AH35 -> 0 | G36: 0 | H36: =F36-'Exec.Summary_Liquiplanung ORG'!C35 -> 0 | J36: =Februar!AH35 -> 0 | K36: 0 | L36: =J36-'Exec.Summary_Liquiplanung ORG'!D35 -> 0 | N36: =März!AH35 -> 0 | O36: 0 | P36: =N36-'Exec.Summary_Liquiplanung ORG'!E35 -> 0 | R36: =April!AH35 -> 0 | S36: 0 | T36: =R36-'Exec.Summary_Liquiplanung ORG'!F35 -> 0 | V36: =Mai!AH35 -> 0 | W36: 0 | X36: =V36-'Exec.Summary_Liquiplanung ORG'!G35 -> 0 | Z36: =Juni!AH35 -> 0 | AA36: 0 | AB36: =Z36-'Exec.Summary_Liquiplanung ORG'!H35 -> 0 | AD36: 0
A37: Bareinzahlungen | B37: =Dezember24!AH36 -> 0 | C37: 0 | D37: =B37-'Exec.Summary_Liquiplanung ORG'!B36 -> 0 | F37: =Januar!AH36 -> 0 | G37: 0 | H37: =F37-'Exec.Summary_Liquiplanung ORG'!C36 -> 0 | J37: =Februar!AH36 -> 0 | K37: 0 | L37: =J37-'Exec.Summary_Liquiplanung ORG'!D36 -> 0 | N37: =März!AH36 -> 0 | O37: 0 | P37: =N37-'Exec.Summary_Liquiplanung ORG'!E36 -> 0 | R37: =April!AH36 -> 0 | S37: 0 | T37: =R37-'Exec.Summary_Liquiplanung ORG'!F36 -> 0 | V37: =Mai!AH36 -> 0 | W37: 0 | X37: =V37-'Exec.Summary_Liquiplanung ORG'!G36 -> 0 | Z37: =Juni!AH36 -> 0 | AA37: 0 | AB37: =Z37-'Exec.Summary_Liquiplanung ORG'!H36 -> 0 | AD37: 0
A38: Umbuchungen S-Zentral | B38: =Dezember24!AH37 -> 0 | C38: 0 | D38: =B38-'Exec.Summary_Liquiplanung ORG'!B37 -> 0 | F38: =Januar!AH37 -> 0 | G38: 0 | H38: =F38-'Exec.Summary_Liquiplanung ORG'!C37 -> 0 | J38: =Februar!AH37 -> 0 | K38: 0 | L38: =J38-'Exec.Summary_Liquiplanung ORG'!D37 -> 0 | N38: =März!AH37 -> 0 | O38: 0 | P38: =N38-'Exec.Summary_Liquiplanung ORG'!E37 -> 0 | R38: =April!AH37 -> 0 | S38: 0 | T38: =R38-'Exec.Summary_Liquiplanung ORG'!F37 -> 0 | V38: =Mai!AH37 -> 0 | W38: 0 | X38: =V38-'Exec.Summary_Liquiplanung ORG'!G37 -> 0 | Z38: =Juni!AH37 -> 0 | AA38: 0 | AB38: =Z38-'Exec.Summary_Liquiplanung ORG'!H37 -> 0 | AD38: 0
A39: interne Zahlungen | B39: =Dezember24!AH38 -> 0 | C39: 0 | D39: =B39-'Exec.Summary_Liquiplanung ORG'!B38 -> 0 | F39: =Januar!AH38 -> 0 | G39: 0 | H39: =F39-'Exec.Summary_Liquiplanung ORG'!C38 -> 0 | J39: =Februar!AH38 -> 0 | K39: 0 | L39: =J39-'Exec.Summary_Liquiplanung ORG'!D38 -> 0 | N39: =März!AH38 -> 0 | O39: 0 | P39: =N39-'Exec.Summary_Liquiplanung ORG'!E38 -> 0 | R39: =April!AH38 -> 0 | S39: 0 | T39: =R39-'Exec.Summary_Liquiplanung ORG'!F38 -> 0 | V39: =Mai!AH38 -> 0 | W39: 0 | X39: =V39-'Exec.Summary_Liquiplanung ORG'!G38 -> 0 | Z39: =Juni!AH38 -> 0 | AA39: 0 | AB39: =Z39-'Exec.Summary_Liquiplanung ORG'!H38 -> 0 | AD39: 0
A40: Besonderheiten | B40: =Dezember24!AH39 -> 0 | C40: 0 | D40: =B40-'Exec.Summary_Liquiplanung ORG'!B39 -> 0 | F40: =Januar!AH39 -> 0 | G40: 0 | H40: =F40-'Exec.Summary_Liquiplanung ORG'!C39 -> 0 | J40: =Februar!AH39 -> 20889.36 | K40: 0 | L40: =J40-'Exec.Summary_Liquiplanung ORG'!D39 -> 20889.36 | N40: =März!AH39 -> 2229727.3 | O40: 0 | P40: =N40-'Exec.Summary_Liquiplanung ORG'!E39 -> 2229727.3 | R40: =April!AH39 -> 0 | S40: 0 | T40: =R40-'Exec.Summary_Liquiplanung ORG'!F39 -> 0 | V40: =Mai!AH39 -> 0 | W40: 0 | X40: =V40-'Exec.Summary_Liquiplanung ORG'!G39 -> 0 | Z40: =Juni!AH39 -> 0 | AA40: 0 | AB40: =Z40-'Exec.Summary_Liquiplanung ORG'!H39 -> 0 | AD40: 0
A41: Kreditkarten | B41: =Dezember24!AH40 -> 475599.89 | C41: 967750 | D41: =B41-'Exec.Summary_Liquiplanung ORG'!B40 -> -492150.11 | F41: =Januar!AH40 -> 3810010.6 | G41: 4370953.1 | H41: =F41-'Exec.Summary_Liquiplanung ORG'!C40 -> -560942.47 | J41: =Februar!AH40 -> 4298434.4 | K41: 3908393.5 | L41: =J41-'Exec.Summary_Liquiplanung ORG'!D40 -> 390040.89 | N41: =März!AH40 -> 4815059.8 | O41: 5226279.4 | P41: =N41-'Exec.Summary_Liquiplanung ORG'!E40 -> -411219.6 | R41: =April!AH40 -> 6380242.7 | S41: 4156379.5 | T41: =R41-'Exec.Summary_Liquiplanung ORG'!F40 -> 2223863.1 | V41: =Mai!AH40 -> 4908414.5 | W41: 5207062.2 | X41: =V41-'Exec.Summary_Liquiplanung ORG'!G40 -> -298647.62 | Z41: =Juni!AH40 -> 5222355.2 | AA41: 5127362.8 | AB41: =Z41-'Exec.Summary_Liquiplanung ORG'!H40 -> 94992.426 | AD41: 307359.76
A42: Debitoren | B42: =Dezember24!AH41 -> 32289.84 | C42: 2213718.8 | D42: =B42-'Exec.Summary_Liquiplanung ORG'!B41 -> -2181428.9 | F42: =Januar!AH41 -> 1555527.7 | G42: 3177414 | H42: =F42-'Exec.Summary_Liquiplanung ORG'!C41 -> -1621886.3 | J42: =Februar!AH41 -> 2856728.1 | K42: 3530810 | L42: =J42-'Exec.Summary_Liquiplanung ORG'!D41 -> -674081.88 | N42: =März!AH41 -> 4138219.5 | O42: 4441038.8 | P42: =N42-'Exec.Summary_Liquiplanung ORG'!E41 -> -302819.32 | R42: =April!AH41 -> 4392927.5 | S42: 4361872.5 | T42: =R42-'Exec.Summary_Liquiplanung ORG'!F41 -> 31054.996 | V42: =Mai!AH41 -> 5117116.4 | W42: 4949210.8 | X42: =V42-'Exec.Summary_Liquiplanung ORG'!G41 -> 167905.63 | Z42: =Juni!AH41 -> 4920793.1 | AA42: 4904541.8 | AB42: =Z42-'Exec.Summary_Liquiplanung ORG'!H41 -> 16251.308 | AD42: -1519478.4 | AF42: Verschiebung der Einzahlungen (SSK DUS, Auszahlungen Kreditkarten, Einbehalt Deposit 250 T€)
A43: Summe Einnahmen | B43: =Dezember24!AH42 -> 507889.73 | C43: 3181468.8 | D43: =B43-'Exec.Summary_Liquiplanung ORG'!B42 -> -2673579 | F43: =Januar!AH42 -> 5365538.3 | G43: 7548367.1 | H43: =F43-'Exec.Summary_Liquiplanung ORG'!C42 -> -2182828.8 | J43: =Februar!AH42 -> 7176051.9 | K43: 7439203.5 | L43: =J43-'Exec.Summary_Liquiplanung ORG'!D42 -> -263151.63 | N43: =März!AH42 -> 11183007 | O43: 9667318.2 | P43: =N43-'Exec.Summary_Liquiplanung ORG'!E42 -> 1515688.4 | R43: =April!AH42 -> 10773170 | S43: 8518252.1 | T43: =R43-'Exec.Summary_Liquiplanung ORG'!F42 -> 2254918.1 | V43: =Mai!AH42 -> 10025531 | W43: 10156273 | X43: =V43-'Exec.Summary_Liquiplanung ORG'!G42 -> -130741.99 | Z43: =Juni!AH42 -> 10143148 | AA43: 10031905 | AB43: =Z43-'Exec.Summary_Liquiplanung ORG'!H42 -> 111243.73 | AD43: -1212118.7 | AF43: Anpassung Umsatzerwartung
F44: =Januar!AH43 | J44: =Februar!AH43 | R44: =April!AH43 | V44: =Mai!AH43 | Z44: =Juni!AH43
A45: Zwischensumme | B45: =Dezember24!AH44 -> 442499.73 | C45: 1761468.8 | D45: =B45-'Exec.Summary_Liquiplanung ORG'!B44 -> -1318969 | F45: =Januar!AH44 -> 652888.1 | G45: 1353056.5 | H45: =F45-'Exec.Summary_Liquiplanung ORG'!C44 -> -700168.37 | J45: =Februar!AH44 -> 615050.38 | K45: 589863.68 | L45: =J45-'Exec.Summary_Liquiplanung ORG'!D44 -> 25186.702 | N45: =März!AH44 -> 3371018.1 | O45: -1178576.1 | P45: =N45-'Exec.Summary_Liquiplanung ORG'!E44 -> 4549594.2 | R45: =April!AH44 -> 2913712.9 | S45: -999676.61 | T45: =R45-'Exec.Summary_Liquiplanung ORG'!F44 -> 3913389.5 | V45: =Mai!AH44 -> -1890291 | W45: -267849.29 | X45: =V45-'Exec.Summary_Liquiplanung ORG'!G44 -> -1622441.7 | Z45: =Juni!AH44 -> 2120610.1 | AA45: -2931892.1 | AB45: =Z45-'Exec.Summary_Liquiplanung ORG'!H44 -> 5052502.2 | AD45: -25411.409
D46: =B46-'Exec.Summary_Liquiplanung ORG'!B45 -> 0 | H46: =F46-'Exec.Summary_Liquiplanung ORG'!C45 -> 0 | L46: =J46-'Exec.Summary_Liquiplanung ORG'!D45 -> 0 | P46: =N46-'Exec.Summary_Liquiplanung ORG'!E45 -> 0 | T46: =R46-'Exec.Summary_Liquiplanung ORG'!F45 -> 0 | X46: =V46-'Exec.Summary_Liquiplanung ORG'!G45 -> 0 | AB46: =Z46-'Exec.Summary_Liquiplanung ORG'!H45 -> 0 | AD46: 0
A47: Liquiditätshilfe | D47: =B47-'Exec.Summary_Liquiplanung ORG'!B46 -> 0 | H47: =F47-'Exec.Summary_Liquiplanung ORG'!C46 -> 0 | L47: =J47-'Exec.Summary_Liquiplanung ORG'!D46 -> 0 | P47: =N47-'Exec.Summary_Liquiplanung ORG'!E46 -> 0 | T47: =R47-'Exec.Summary_Liquiplanung ORG'!F46 -> 0 | X47: =V47-'Exec.Summary_Liquiplanung ORG'!G46 -> 0 | AB47: =Z47-'Exec.Summary_Liquiplanung ORG'!H46 -> 0 | AD47: 0
D48: =B48-'Exec.Summary_Liquiplanung ORG'!B47 -> 0 | H48: =F48-'Exec.Summary_Liquiplanung ORG'!C47 -> 0 | L48: =J48-'Exec.Summary_Liquiplanung ORG'!D47 -> 0 | P48: =N48-'Exec.Summary_Liquiplanung ORG'!E47 -> 0 | T48: =R48-'Exec.Summary_Liquiplanung ORG'!F47 -> 0 | X48: =V48-'Exec.Summary_Liquiplanung ORG'!G47 -> 0 | AB48: =Z48-'Exec.Summary_Liquiplanung ORG'!H47 -> 0 | AD48: 0
D49: =B49-'Exec.Summary_Liquiplanung ORG'!B48 -> 0 | H49: =F49-'Exec.Summary_Liquiplanung ORG'!C48 -> 0 | L49: =J49-'Exec.Summary_Liquiplanung ORG'!D48 -> 0 | P49: =N49-'Exec.Summary_Liquiplanung ORG'!E48 -> 0 | T49: =R49-'Exec.Summary_Liquiplanung ORG'!F48 -> 0 | X49: =V49-'Exec.Summary_Liquiplanung ORG'!G48 -> 0 | AB49: =Z49-'Exec.Summary_Liquiplanung ORG'!H48 -> 0 | AD49: 0
D50: =B50-'Exec.Summary_Liquiplanung ORG'!B49 -> 0 | H50: =F50-'Exec.Summary_Liquiplanung ORG'!C49 -> 0 | L50: =J50-'Exec.Summary_Liquiplanung ORG'!D49 -> 0 | P50: =N50-'Exec.Summary_Liquiplanung ORG'!E49 -> 0 | T50: =R50-'Exec.Summary_Liquiplanung ORG'!F49 -> 0 | X50: =V50-'Exec.Summary_Liquiplanung ORG'!G49 -> 0 | AB50: =Z50-'Exec.Summary_Liquiplanung ORG'!H49 -> 0 | AD50: 0
A51: Closing Balance | B51: =Dezember24!AG50 -> 3442499.7 | C51: 4761468.8 | D51: =B51-'Exec.Summary_Liquiplanung ORG'!B50 -> -1318969 | F51: =Januar!AH50 -> 4095387.8 | G51: 6114525.2 | H51: =F51-'Exec.Summary_Liquiplanung ORG'!C50 -> -2019137.4 | J51: =Februar!AH50 -> 4710438.2 | K51: 6704388.9 | L51: =J51-'Exec.Summary_Liquiplanung ORG'!D50 -> -1993950.7 | N51: =März!AG50 -> 8081456.3 | O51: 5525812.8 | P51: =N51-'Exec.Summary_Liquiplanung ORG'!E50 -> 2555643.5 | R51: =April!AH50 -> 10995169 | S51: 4526136.2 | T51: =R51-'Exec.Summary_Liquiplanung ORG'!F50 -> 6469033.1 | V51: =Mai!AH50 -> 9104878.3 | W51: 4258286.9 | X51: =V51-'Exec.Summary_Liquiplanung ORG'!G50 -> 4846591.4 | Z51: =Juni!AH50 -> 11225488 | AA51: 1326394.8 | AB51: =Z51-'Exec.Summary_Liquiplanung ORG'!H50 -> 9899093.5
A52: Closing Balance | B52: 4761468.8 | F52: 6114525.2 | J52: 6704388.9 | N52: 5525812.8 | R52: 4526136.2 | V52: 4258286.9 | Z52: 1326394.8
B53: =B51-B52 -> -1318969 | F53: =F51-F52 -> -2019137.4 | J53: =J51-J52 -> -1993950.7 | N53: =N51-N52 -> 2555643.5 | R53: =R51-R52 -> 6469033.1 | V53: =V51-V52 -> 4846591.4 | Z53: =Z51-Z52 -> 9899093.5
A55: Erläuterung der Veränderungen
A56: Positiver Impakt | B56: Betrag
A60: Negativer Impakt | B60: Betrag
A64: Net Impakt | B64: =SUM(B57:B63) -> 0

Sheet Exec.Summary_Liquiplanung
A1: Liquiditätsplanung | M1: Abweichung zum originalen Finanzplan | V1: Abweichung zum Finanzplan 04.07.25 | AG1: letztes Reporting
B2: December | C2: January | D2: February | E2: March | F2: April | G2: Mai | H2: June | I2: July | J2: August | K2: September | M2: Dec | N2: January | O2: February | P2: March | Q2: April | R2: Mai | S2: June | T2: Sum | V2: Dec | W2: January | X2: February | Y2: March | Z2: April | AA2: Mai | AB2: June | AC2: July | AD2: August | AE2: Sum | AG2: Dec | AH2: January | AI2: February | AJ2: March | AK2: April | AL2: Mai | AM2: June | AN2: July | AO2: August | AP2: Sum
A4: Opening Balance | B4: =Dezember24!R4 -> 3000000 | C4: =Januar!B4 -> 3442499.7 | D4: =Februar!B4 -> 4095387.8 | E4: =März!B6 -> 4710438.2 | F4: =April!B4 -> 8081456.3 | G4: =Mai!B4 -> 10995169 | H4: =Juni!B4 -> 9104878.3 | I4: =Juli!B4 -> 11225488 | J4: =August!B4 -> 8492524.3 | K4: =September!B4 -> 5940023.1 | M4: =B4-'Exec.Summary_Liquiplanung ORG'!B4 -> 0 | N4: =C4-'Exec.Summary_Liquiplanung ORG'!C4 -> -1318969 | O4: =D4-'Exec.Summary_Liquiplanung ORG'!D4 -> -2019137.4 | P4: =E4-'Exec.Summary_Liquiplanung ORG'!E4 -> -1993950.7 | Q4: =F4-'Exec.Summary_Liquiplanung ORG'!F4 -> 2555643.5 | R4: =G4-'Exec.Summary_Liquiplanung ORG'!G4 -> 6469033.1 | S4: =H4-'Exec.Summary_Liquiplanung ORG'!H4 -> 4846591.4 | V4: =B4-AG4 -> 0 | W4: =C4-AH4 -> 0 | X4: =D4-AI4 -> 0 | Y4: =E4-AJ4 -> -29437.152 | Z4: =F4-AK4 -> 173104.08 | AA4: =G4-AL4 -> 465581.91 | AB4: =H4-AM4 -> -1091568.7 | AC4: =I4-AN4 -> 0.43404664 | AD4: =J4-AO4 -> 495887.2 | AG4: 3000000 | AH4: 3442499.7 | AI4: 4095387.8 | AJ4: 4739875.4 | AK4: 7908352.2 | AL4: 10529587 | AM4: 10196447 | AN4: 11225488 | AO4: 7996637.1
A5: Tagesgeld | B5: =Dezember24!AH5 -> 0 | C5: =Januar!AH5 -> 0 | D5: =Februar!AH5 -> 0 | E5: =März!AH5 -> 0 | F5: =April!AH5 -> 0 | G5: =Mai!AH5 -> 0 | H5: =Juni!AH5 -> 0 | I5: =Juli!AH5 -> 0 | J5: =August!AH5 -> 0 | K5: =September!AH5 -> 0 | M5: =B5-'Exec.Summary_Liquiplanung ORG'!B5 -> 0 | N5: =C5-'Exec.Summary_Liquiplanung ORG'!C5 -> 0 | O5: =D5-'Exec.Summary_Liquiplanung ORG'!D5 -> 0 | P5: =E5-'Exec.Summary_Liquiplanung ORG'!E5 -> 0 | Q5: =F5-'Exec.Summary_Liquiplanung ORG'!F5 -> 0 | R5: =G5-'Exec.Summary_Liquiplanung ORG'!G5 -> 0 | S5: =H5-'Exec.Summary_Liquiplanung ORG'!H5 -> 0 | V5: 0 | W5: 0 | X5: 0 | Y5: 0 | Z5: 0 | AA5: 0 | AB5: 0 | AC5: 0 | AD5: 0 | AG5: 0 | AH5: 0 | AI5: 0 | AJ5: 0 | AK5: 0 | AL5: 0 | AM5: 0 | AN5: 0 | AO5: 0
A6: Summe | B6: =Dezember24!AH6 -> 0 | C6: =Januar!AH6 -> 3442499.7 | D6: =Februar!AH6 -> 4095387.8 | E6: =März!AH6 -> 4710438.2 | F6: =April!AH6 -> 8081456.3 | G6: =Mai!AH6 -> 10995169 | H6: =Juni!AH6 -> 9104878.3 | I6: =Juli!AH6 -> 11225488 | J6: =August!AH6 -> 8492524.3 | K6: =September!AH6 -> 5940023.1 | M6: =B6-'Exec.Summary_Liquiplanung ORG'!B6 -> 0 | N6: =C6-'Exec.Summary_Liquiplanung ORG'!C6 -> -1318969 | O6: =D6-'Exec.Summary_Liquiplanung ORG'!D6 -> -2019137.4 | P6: =E6-'Exec.Summary_Liquiplanung ORG'!E6 -> -1993950.7 | Q6: =F6-'Exec.Summary_Liquiplanung ORG'!F6 -> 2555643.5 | R6: =G6-'Exec.Summary_Liquiplanung ORG'!G6 -> 6469033.1 | S6: =H6-'Exec.Summary_Liquiplanung ORG'!H6 -> 4846591.4 | V6: -1318969 | W6: -3360685.9 | X6: -3301536.4 | Y6: -1284799.1 | Z6: -790866 | AA6: -390733.17 | AB6: 0 | AC6: 0 | AD6: 0 | AG6: 0 | AH6: 3442499.7 | AI6: 4095387.8 | AJ6: 4739875.4 | AK6: 7908352.2 | AL6: 10529587 | AM6: 10196447 | AN6: 11225488 | AO6: 7996637.1
A7: AUSGABEN | G7: =Mai!AH7 | H7: =Juni!AH7 | I7: =Juli!AH7 | J7: =August!AH7 | K7: =September!AH7
A8: Pacht | B8: =Dezember24!AH8 -> 0 | C8: =Januar!AH8 -> 1336978.3 | D8: =Februar!AH8 -> -227726.6 | E8: =März!AH8 -> 1756520.4 | F8: =April!AH8 -> 2715108 | G8: =Mai!AH8 -> 3884517 | H8: =Juni!AH8 -> 0 | I8: =Juli!AH8 -> 1723513 | J8: =August!AH8 -> 1723513 | K8: =September!AH8 -> 1723513 | M8: =B8-'Exec.Summary_Liquiplanung ORG'!B8 -> 0 | N8: =C8-'Exec.Summary_Liquiplanung ORG'!C8 -> -648647.27 | O8: =D8-'Exec.Summary_Liquiplanung ORG'!D8 -> -227726.6 | P8: =E8-'Exec.Summary_Liquiplanung ORG'!E8 -> -399444.71 | Q8: =F8-'Exec.Summary_Liquiplanung ORG'!F8 -> 804841.39 | R8: =G8-'Exec.Summary_Liquiplanung ORG'!G8 -> 1859473.9 | S8: =H8-'Exec.Summary_Liquiplanung ORG'!H8 -> -1910725.9 | T8: =SUM(M8:S8) -> -522229.21 | V8: =B8-AG8 -> 0 | W8: =C8-AH8 -> 0 | X8: =D8-AI8 -> 0 | Y8: =E8-AJ8 -> 0 | Z8: =F8-AK8 -> 0 | AA8: =G8-AL8 -> 0 | AB8: =H8-AM8 -> 0 | AC8: =I8-AN8 -> 0 | AD8: =J8-AO8 -> 0 | AE8: =SUM(V8:AD8) -> 0 | AG8: 0 | AH8: 1336978.3 | AI8: -227726.6 | AJ8: 1756520.4 | AK8: 2715108 | AL8: 3884517 | AM8: 0 | AN8: 1723513 | AO8: 1723513 | AP8: =SUM(AG8:AO8) -> 12912423
A9: Annuität ext. | B9: =Dezember24!AH9 -> 0 | C9: =Januar!AH9 -> 0 | D9: =Februar!AH9 -> 0 | E9: =März!AH9 -> 0 | F9: =April!AH9 -> 0 | G9: =Mai!AH9 -> 0 | H9: =Juni!AH9 -> 0 | I9: =Juli!AH9 -> 0 | J9: =August!AH9 -> 0 | K9: =September!AH9 -> 0 | M9: =B9-'Exec.Summary_Liquiplanung ORG'!B9 -> 0 | N9: =C9-'Exec.Summary_Liquiplanung ORG'!C9 -> 0 | O9: =D9-'Exec.Summary_Liquiplanung ORG'!D9 -> 0 | P9: =E9-'Exec.Summary_Liquiplanung ORG'!E9 -> 0 | Q9: =F9-'Exec.Summary_Liquiplanung ORG'!F9 -> 0 | R9: =G9-'Exec.Summary_Liquiplanung ORG'!G9 -> 0 | S9: =H9-'Exec.Summary_Liquiplanung ORG'!H9 -> 0 | T9: =SUM(M9:S9) -> 0 | V9: =B9-AG9 -> 0 | W9: =C9-AH9 -> 0 | X9: =D9-AI9 -> 0 | Y9: =E9-AJ9 -> 0 | Z9: =F9-AK9 -> 0 | AA9: =G9-AL9 -> 0 | AB9: =H9-AM9 -> 0 | AC9: =I9-AN9 -> 0 | AD9: =J9-AO9 -> 0 | AE9: =SUM(V9:AD9) -> 0 | AG9: 0 | AH9: 0 | AI9: 0 | AJ9: 0 | AK9: 0 | AL9: 0 | AM9: 0 | AN9: 0 | AO9: 0 | AP9: =SUM(AG9:AO9) -> 0
A10: Kreditorenzahlungen | B10: =Dezember24!AH10 -> 65390 | C10: =Januar!AH10 -> 2712411.1 | D10: =Februar!AH10 -> 5020228.1 | E10: =März!AH10 -> 3209571.6 | F10: =April!AH10 -> 1978234.2 | G10: =Mai!AH10 -> 4806305 | H10: =Juni!AH10 -> 5122538.2 | I10: =Juli!AH10 -> 7476262 | J10: =August!AH10 -> 7048256.6 | K10: =September!AH10 -> 6664395.2 | M10: =B10-'Exec.Summary_Liquiplanung ORG'!B10 -> -1184610 | N10: =C10-'Exec.Summary_Liquiplanung ORG'!C10 -> -1337588.9 | O10: =D10-'Exec.Summary_Liquiplanung ORG'!D10 -> -122676.8 | P10: =E10-'Exec.Summary_Liquiplanung ORG'!E10 -> -2887456.6 | Q10: =F10-'Exec.Summary_Liquiplanung ORG'!F10 -> -2848258.9 | R10: =G10-'Exec.Summary_Liquiplanung ORG'!G10 -> -914119.98 | S10: =H10-'Exec.Summary_Liquiplanung ORG'!H10 -> -976595.92 | T10: =SUM(M10:S10) -> -10271307 | V10: =B10-AG10 -> 0 | W10: =C10-AH10 -> 0 | X10: =D10-AI10 -> 0 | Y10: =E10-AJ10 -> 0 | Z10: =F10-AK10 -> 0 | AA10: =G10-AL10 -> 486672.09 | AB10: =H10-AM10 -> -1222670.4 | AC10: =I10-AN10 -> -861381.27 | AD10: =J10-AO10 -> -155637.16 | AE10: =SUM(V10:AD10) -> -1753016.7 | AG10: 65390 | AH10: 2712411.1 | AI10: 5020228.1 | AJ10: 3209571.6 | AK10: 1978234.2 | AL10: 4319632.9 | AM10: 6345208.6 | AN10: 8337643.3 | AO10: 7203893.8 | AP10: =SUM(AG10:AO10) -> 39192213
A11: Aktivbank/Progros | B11: =Dezember24!AH11 -> 0 | C11: =Januar!AH11 -> 80069 | D11: =Februar!AH11 -> 0 | E11: =März!AH11 -> 0 | F11: =April!AH11 -> 0 | G11: =Mai!AH11 -> 0 | H11: =Juni!AH11 -> 0 | I11: =Juli!AH11 -> 0 | J11: =August!AH11 -> 0 | K11: =September!AH11 -> 0 | M11: =B11-'Exec.Summary_Liquiplanung ORG'!B11 -> 0 | N11: =C11-'Exec.Summary_Liquiplanung ORG'!C11 -> 80069 | O11: =D11-'Exec.Summary_Liquiplanung ORG'!D11 -> 0 | P11: =E11-'Exec.Summary_Liquiplanung ORG'!E11 -> 0 | Q11: =F11-'Exec.Summary_Liquiplanung ORG'!F11 -> 0 | R11: =G11-'Exec.Summary_Liquiplanung ORG'!G11 -> 0 | S11: =H11-'Exec.Summary_Liquiplanung ORG'!H11 -> 0 | T11: =SUM(M11:S11) -> 80069 | V11: =B11-AG11 -> 0 | W11: =C11-AH11 -> 0 | X11: =D11-AI11 -> 0 | Y11: =E11-AJ11 -> 0 | Z11: =F11-AK11 -> 0 | AA11: =G11-AL11 -> 0 | AB11: =H11-AM11 -> 0 | AC11: =I11-AN11 -> 0 | AD11: =J11-AO11 -> 0 | AE11: =SUM(V11:AD11) -> 0 | AG11: 0 | AH11: 80069 | AI11: 0 | AJ11: 0 | AK11: 0 | AL11: 0 | AM11: 0 | AN11: 0 | AO11: 0 | AP11: =SUM(AG11:AO11) -> 80069
A12: Lastschriften | B12: =Dezember24!AH12 -> 0 | C12: =Januar!AH12 -> 541051.79 | D12: =Februar!AH12 -> 0 | E12: =März!AH12 -> 0 | F12: =April!AH12 -> 0 | G12: =Mai!AH12 -> 0 | H12: =Juni!AH12 -> 0 | I12: =Juli!AH12 -> 0 | J12: =August!AH12 -> 0 | K12: =September!AH12 -> 0 | M12: =B12-'Exec.Summary_Liquiplanung ORG'!B12 -> 0 | N12: =C12-'Exec.Summary_Liquiplanung ORG'!C12 -> 541051.79 | O12: =D12-'Exec.Summary_Liquiplanung ORG'!D12 -> 0 | P12: =E12-'Exec.Summary_Liquiplanung ORG'!E12 -> 0 | Q12: =F12-'Exec.Summary_Liquiplanung ORG'!F12 -> 0 | R12: =G12-'Exec.Summary_Liquiplanung ORG'!G12 -> 0 | S12: =H12-'Exec.Summary_Liquiplanung ORG'!H12 -> 0 | T12: =SUM(M12:S12) -> 541051.79 | V12: =B12-AG12 -> 0 | W12: =C12-AH12 -> 0 | X12: =D12-AI12 -> 0 | Y12: =E12-AJ12 -> 0 | Z12: =F12-AK12 -> 0 | AA12: =G12-AL12 -> 0 | AB12: =H12-AM12 -> 0 | AC12: =I12-AN12 -> 0 | AD12: =J12-AO12 -> 0 | AE12: =SUM(V12:AD12) -> 0 | AG12: 0 | AH12: 541051.79 | AI12: 0 | AJ12: 0 | AK12: 0 | AL12: 0 | AM12: 0 | AN12: 0 | AO12: 0 | AP12: =SUM(AG12:AO12) -> 541051.79
A13: Energiedienstleister | B13: =Dezember24!AH13 -> 0 | C13: =Januar!AH13 -> 148000 | D13: =Februar!AH13 -> 0 | E13: =März!AH13 -> 0 | F13: =April!AH13 -> 0 | G13: =Mai!AH13 -> 0 | H13: =Juni!AH13 -> 0 | I13: =Juli!AH13 -> 0 | J13: =August!AH13 -> 0 | K13: =September!AH13 -> 0 | M13: =B13-'Exec.Summary_Liquiplanung ORG'!B13 -> 0 | N13: =C13-'Exec.Summary_Liquiplanung ORG'!C13 -> 148000 | O13: =D13-'Exec.Summary_Liquiplanung ORG'!D13 -> 0 | P13: =E13-'Exec.Summary_Liquiplanung ORG'!E13 -> 0 | Q13: =F13-'Exec.Summary_Liquiplanung ORG'!F13 -> 0 | R13: =G13-'Exec.Summary_Liquiplanung ORG'!G13 -> 0 | S13: =H13-'Exec.Summary_Liquiplanung ORG'!H13 -> 0 | T13: =SUM(M13:S13) -> 148000 | V13: =B13-AG13 -> 0 | W13: =C13-AH13 -> 0 | X13: =D13-AI13 -> 0 | Y13: =E13-AJ13 -> 0 | Z13: =F13-AK13 -> 0 | AA13: =G13-AL13 -> 0 | AB13: =H13-AM13 -> 0 | AC13: =I13-AN13 -> 0 | AD13: =J13-AO13 -> 0 | AE13: =SUM(V13:AD13) -> 0 | AG13: 0 | AH13: 148000 | AI13: 0 | AJ13: 0 | AK13: 0 | AL13: 0 | AM13: 0 | AN13: 0 | AO13: 0 | AP13: =SUM(AG13:AO13) -> 148000
A14: Telekommunikation | B14: =Dezember24!AH14 -> 0 | C14: =Januar!AH14 -> 393051.79 | D14: =Februar!AH14 -> 0 | E14: =März!AH14 -> 0 | F14: =April!AH14 -> 0 | G14: =Mai!AH14 -> 0 | H14: =Juni!AH14 -> 0 | I14: =Juli!AH14 -> 0 | J14: =August!AH14 -> 0 | K14: =September!AH14 -> 0 | M14: =B14-'Exec.Summary_Liquiplanung ORG'!B14 -> 0 | N14: =C14-'Exec.Summary_Liquiplanung ORG'!C14 -> 393051.79 | O14: =D14-'Exec.Summary_Liquiplanung ORG'!D14 -> 0 | P14: =E14-'Exec.Summary_Liquiplanung ORG'!E14 -> 0 | Q14: =F14-'Exec.Summary_Liquiplanung ORG'!F14 -> 0 | R14: =G14-'Exec.Summary_Liquiplanung ORG'!G14 -> 0 | S14: =H14-'Exec.Summary_Liquiplanung ORG'!H14 -> 0 | T14: =SUM(M14:S14) -> 393051.79 | V14: =B14-AG14 -> 0 | W14: =C14-AH14 -> 0 | X14: =D14-AI14 -> 0 | Y14: =E14-AJ14 -> 0 | Z14: =F14-AK14 -> 0 | AA14: =G14-AL14 -> 0 | AB14: =H14-AM14 -> 0 | AC14: =I14-AN14 -> 0 | AD14: =J14-AO14 -> 0 | AE14: =SUM(V14:AD14) -> 0 | AG14: 0 | AH14: 393051.79 | AI14: 0 | AJ14: 0 | AK14: 0 | AL14: 0 | AM14: 0 | AN14: 0 | AO14: 0 | AP14: =SUM(AG14:AO14) -> 393051.79
A15: Gebühren CC | B15: =Dezember24!AH15 -> 0 | C15: =Januar!AH15 -> 0 | D15: =Februar!AH15 -> 0 | E15: =März!AH15 -> 0 | F15: =April!AH15 -> 0 | G15: =Mai!AH15 -> 0 | H15: =Juni!AH15 -> 0 | I15: =Juli!AH15 -> 0 | J15: =August!AH15 -> 0 | K15: =September!AH15 -> 0 | M15: =B15-'Exec.Summary_Liquiplanung ORG'!B15 -> 0 | N15: =C15-'Exec.Summary_Liquiplanung ORG'!C15 -> 0 | O15: =D15-'Exec.Summary_Liquiplanung ORG'!D15 -> 0 | P15: =E15-'Exec.Summary_Liquiplanung ORG'!E15 -> 0 | Q15: =F15-'Exec.Summary_Liquiplanung ORG'!F15 -> 0 | R15: =G15-'Exec.Summary_Liquiplanung ORG'!G15 -> 0 | S15: =H15-'Exec.Summary_Liquiplanung ORG'!H15 -> 0 | T15: =SUM(M15:S15) -> 0 | V15: =B15-AG15 -> 0 | W15: =C15-AH15 -> 0 | X15: =D15-AI15 -> 0 | Y15: =E15-AJ15 -> 0 | Z15: =F15-AK15 -> 0 | AA15: =G15-AL15 -> 0 | AB15: =H15-AM15 -> 0 | AC15: =I15-AN15 -> 0 | AD15: =J15-AO15 -> 0 | AE15: =SUM(V15:AD15) -> 0 | AG15: 0 | AH15: 0 | AI15: 0 | AJ15: 0 | AK15: 0 | AL15: 0 | AM15: 0 | AN15: 0 | AO15: 0 | AP15: =SUM(AG15:AO15) -> 0
A16: Provisonen( Booking, Expedia | B16: =Dezember24!AH16 -> 0 | C16: =Januar!AH16 -> 0 | D16: =Februar!AH16 -> 0 | E16: =März!AH16 -> 0 | F16: =April!AH16 -> 0 | G16: =Mai!AH16 -> 0 | H16: =Juni!AH16 -> 0 | I16: =Juli!AH16 -> 0 | J16: =August!AH16 -> 0 | K16: =September!AH16 -> 0 | M16: =B16-'Exec.Summary_Liquiplanung ORG'!B16 -> 0 | N16: =C16-'Exec.Summary_Liquiplanung ORG'!C16 -> 0 | O16: =D16-'Exec.Summary_Liquiplanung ORG'!D16 -> 0 | P16: =E16-'Exec.Summary_Liquiplanung ORG'!E16 -> 0 | Q16: =F16-'Exec.Summary_Liquiplanung ORG'!F16 -> 0 | R16: =G16-'Exec.Summary_Liquiplanung ORG'!G16 -> 0 | S16: =H16-'Exec.Summary_Liquiplanung ORG'!H16 -> 0 | T16: =SUM(M16:S16) -> 0 | V16: =B16-AG16 -> 0 | W16: =C16-AH16 -> 0 | X16: =D16-AI16 -> 0 | Y16: =E16-AJ16 -> 0 | Z16: =F16-AK16 -> 0 | AA16: =G16-AL16 -> 0 | AB16: =H16-AM16 -> 0 | AC16: =I16-AN16 -> 0 | AD16: =J16-AO16 -> 0 | AE16: =SUM(V16:AD16) -> 0 | AG16: 0 | AH16: 0 | AI16: 0 | AJ16: 0 | AK16: 0 | AL16: 0 | AM16: 0 | AN16: 0 | AO16: 0 | AP16: =SUM(AG16:AO16) -> 0
A17: KFZ Leasing | B17: =Dezember24!AH17 -> 0 | C17: =Januar!AH17 -> 0 | D17: =Februar!AH17 -> 0 | E17: =März!AH17 -> 0 | F17: =April!AH17 -> 0 | G17: =Mai!AH17 -> 0 | H17: =Juni!AH17 -> 0 | I17: =Juli!AH17 -> 0 | J17: =August!AH17 -> 0 | K17: =September!AH17 -> 0 | M17: =B17-'Exec.Summary_Liquiplanung ORG'!B17 -> 0 | N17: =C17-'Exec.Summary_Liquiplanung ORG'!C17 -> 0 | O17: =D17-'Exec.Summary_Liquiplanung ORG'!D17 -> 0 | P17: =E17-'Exec.Summary_Liquiplanung ORG'!E17 -> 0 | Q17: =F17-'Exec.Summary_Liquiplanung ORG'!F17 -> 0 | R17: =G17-'Exec.Summary_Liquiplanung ORG'!G17 -> 0 | S17: =H17-'Exec.Summary_Liquiplanung ORG'!H17 -> 0 | T17: =SUM(M17:S17) -> 0 | V17: =B17-AG17 -> 0 | W17: =C17-AH17 -> 0 | X17: =D17-AI17 -> 0 | Y17: =E17-AJ17 -> 0 | Z17: =F17-AK17 -> 0 | AA17: =G17-AL17 -> 0 | AB17: =H17-AM17 -> 0 | AC17: =I17-AN17 -> 0 | AD17: =J17-AO17 -> 0 | AE17: =SUM(V17:AD17) -> 0 | AG17: 0 | AH17: 0 | AI17: 0 | AJ17: 0 | AK17: 0 | AL17: 0 | AM17: 0 | AN17: 0 | AO17: 0 | AP17: =SUM(AG17:AO17) -> 0
A18: Jobtickets | B18: =Dezember24!AH18 -> 0 | C18: =Januar!AH18 -> 0 | D18: =Februar!AH18 -> 0 | E18: =März!AH18 -> 0 | F18: =April!AH18 -> 0 | G18: =Mai!AH18 -> 0 | H18: =Juni!AH18 -> 0 | I18: =Juli!AH18 -> 0 | J18: =August!AH18 -> 0 | K18: =September!AH18 -> 0 | M18: =B18-'Exec.Summary_Liquiplanung ORG'!B18 -> 0 | N18: =C18-'Exec.Summary_Liquiplanung ORG'!C18 -> 0 | O18: =D18-'Exec.Summary_Liquiplanung ORG'!D18 -> 0 | P18: =E18-'Exec.Summary_Liquiplanung ORG'!E18 -> 0 | Q18: =F18-'Exec.Summary_Liquiplanung ORG'!F18 -> 0 | R18: =G18-'Exec.Summary_Liquiplanung ORG'!G18 -> 0 | S18: =H18-'Exec.Summary_Liquiplanung ORG'!H18 -> 0 | T18: =SUM(M18:S18) -> 0 | V18: =B18-AG18 -> 0 | W18: =C18-AH18 -> 0 | X18: =D18-AI18 -> 0 | Y18: =E18-AJ18 -> 0 | Z18: =F18-AK18 -> 0 | AA18: =G18-AL18 -> 0 | AB18: =H18-AM18 -> 0 | AC18: =I18-AN18 -> 0 | AD18: =J18-AO18 -> 0 | AE18: =SUM(V18:AD18) -> 0 | AG18: 0 | AH18: 0 | AI18: 0 | AJ18: 0 | AK18: 0 | AL18: 0 | AM18: 0 | AN18: 0 | AO18: 0 | AP18: =SUM(AG18:AO18) -> 0
A19: Leasing | B19: =Dezember24!AH19 -> 0 | C19: =Januar!AH19 -> 0 | D19: =Februar!AH19 -> 0 | E19: =März!AH19 -> 0 | F19: =April!AH19 -> 0 | G19: =Mai!AH19 -> 0 | H19: =Juni!AH19 -> 0 | I19: =Juli!AH19 -> 0 | J19: =August!AH19 -> 0 | K19: =September!AH19 -> 0 | M19: =B19-'Exec.Summary_Liquiplanung ORG'!B19 -> 0 | N19: =C19-'Exec.Summary_Liquiplanung ORG'!C19 -> 0 | O19: =D19-'Exec.Summary_Liquiplanung ORG'!D19 -> 0 | P19: =E19-'Exec.Summary_Liquiplanung ORG'!E19 -> 0 | Q19: =F19-'Exec.Summary_Liquiplanung ORG'!F19 -> 0 | R19: =G19-'Exec.Summary_Liquiplanung ORG'!G19 -> 0 | S19: =H19-'Exec.Summary_Liquiplanung ORG'!H19 -> 0 | T19: =SUM(M19:S19) -> 0 | V19: =B19-AG19 -> 0 | W19: =C19-AH19 -> 0 | X19: =D19-AI19 -> 0 | Y19: =E19-AJ19 -> 0 | Z19: =F19-AK19 -> 0 | AA19: =G19-AL19 -> 0 | AB19: =H19-AM19 -> 0 | AC19: =I19-AN19 -> 0 | AD19: =J19-AO19 -> 0 | AE19: =SUM(V19:AD19) -> 0 | AG19: 0 | AH19: 0 | AI19: 0 | AJ19: 0 | AK19: 0 | AL19: 0 | AM19: 0 | AN19: 0 | AO19: 0 | AP19: =SUM(AG19:AO19) -> 0
... A30: Berater-/ Verfahrenskosten Insolvenzverfahren | B30: =Dezember24!AH30 -> 0 | C30: =Januar!AH30 -> 0 | D30: =Februar!AH30 -> 1500000 | E30: =März!AH30 -> 0 | F30: =April!AH30 -> 0 | G30: =Mai!AH30 -> 0 | H30: =Juni!AH30 -> 0 | I30: =Juli!AH30 -> 0 | J30: =August!AH30 -> 0 | K30: =September!AH30 -> 2400000 | M30: =B30-'Exec.Summary_Liquiplanung ORG'!B30 -> 0 | N30: =C30-'Exec.Summary_Liquiplanung ORG'!C30 -> 0 | O30: =D30-'Exec.Summary_Liquiplanung ORG'!D30 -> 0 | P30: =E30-'Exec.Summary_Liquiplanung ORG'!E30 -> 0 | Q30: =F30-'Exec.Summary_Liquiplanung ORG'!F30 -> 0 | R30: =G30-'Exec.Summary_Liquiplanung ORG'!G30 -> 0 | S30: =H30-'Exec.Summary_Liquiplanung ORG'!H30 -> -2400000 | T30: =SUM(M30:S30) -> -2400000 | V30: =B30-AG30 -> 0 | W30: =C30-AH30 -> 0 | X30: =D30-AI30 -> 0 | Y30: =E30-AJ30 -> 0 | Z30: =F30-AK30 -> 0 | AA30: =G30-AL30 -> 0 | AB30: =H30-AM30 -> 0 | AC30: =I30-AN30 -> 0 | AD30: =J30-AO30 -> -2400000 | AE30: =SUM(V30:AD30) -> -2400000 | AG30: 0 | AH30: 0 | AI30: 1500000 | AJ30: 0 | AK30: 0 | AL30: 0 | AM30: 0 | AN30: 0 | AO30: 2400000 | AP30: =SUM(AG30:AO30) -> 3900000
A31: div. Abbuchungen | B31: =Dezember24!AH31 -> 0 | C31: =Januar!AH31 -> 0 | D31: =Februar!AH31 -> 98500 | E31: =März!AH31 -> 0 | F31: =April!AH31 -> 0 | G31: =Mai!AH31 -> 0 | H31: =Juni!AH31 -> 0 | I31: =Juli!AH31 -> 0 | J31: =August!AH31 -> 0 | K31: =September!AH31 -> 0 | M31: =B31-'Exec.Summary_Liquiplanung ORG'!B31 -> 0 | N31: =C31-'Exec.Summary_Liquiplanung ORG'!C31 -> 0 | O31: =D31-'Exec.Summary_Liquiplanung ORG'!D31 -> 98500 | P31: =E31-'Exec.Summary_Liquiplanung ORG'!E31 -> 0 | Q31: =F31-'Exec.Summary_Liquiplanung ORG'!F31 -> 0 | R31: =G31-'Exec.Summary_Liquiplanung ORG'!G31 -> 0 | S31: =H31-'Exec.Summary_Liquiplanung ORG'!H31 -> 0 | T31: =SUM(M31:S31) -> 98500 | V31: 0 | W31: 0 | X31: 0 | Y31: 0 | Z31: 0 | AA31: 0 | AB31: 0 | AC31: 0 | AD31: 0 | AE31: 0 | AG31: 0 | AH31: 0 | AI31: 98500 | AJ31: 0 | AK31: 0 | AL31: 0 | AM31: 0 | AN31: 0 | AO31: 0 | AP31: 0
A32: Summe Ausgaben | B32: =Dezember24!AH32 -> 65390 | C32: =Januar!AH32 -> 4712650.2 | D32: =Februar!AH32 -> 6561001.5 | E32: =März!AH32 -> 7811988.6 | F32: =April!AH32 -> 7859457.2 | G32: =Mai!AH32 -> 11915822 | H32: =Juni!AH32 -> 8022538.2 | I32: =Juli!AH32 -> 12099775 | J32: =August!AH32 -> 11671770 | K32: =September!AH32 -> 13687908 | M32: =B32-'Exec.Summary_Liquiplanung ORG'!B32 -> -1354610 | N32: =C32-'Exec.Summary_Liquiplanung ORG'!C32 -> -1482660.4 | O32: =D32-'Exec.Summary_Liquiplanung ORG'!D32 -> -288338.33 | P32: =E32-'Exec.Summary_Liquiplanung ORG'!E32 -> -3033905.8 | Q32: =F32-'Exec.Summary_Liquiplanung ORG'!F32 -> -1658471.4 | R32: =G32-'Exec.Summary_Liquiplanung ORG'!G32 -> 1491699.7 | S32: =H32-'Exec.Summary_Liquiplanung ORG'!H32 -> -4941258.4 | T32: =SUM(M32:S32) -> -11267545 | V32: =SUM(V8:V30) -> 0 | W32: =SUM(W8:W30) -> 0 | X32: =SUM(X8:X30) -> 0 | Y32: =SUM(Y8:Y30) -> 0 | Z32: =SUM(Z8:Z30) -> 0 | AA32: =SUM(AA8:AA30) -> 486672.09 | AB32: =SUM(AB8:AB30) -> -1222670.4 | AC32: =SUM(AC8:AC30) -> -861381.27 | AD32: =SUM(AD8:AD30) -> -2555637.2 | AE32: =SUM(V32:AD32) -> -4153016.7 | AG32: 65390 | AH32: 4712650.2 | AI32: 6561001.5 | AJ32: 7811988.6 | AK32: 7859457.2 | AL32: 11429150 | AM32: 9245208.6 | AN32: 12961156 | AO32: 14227407 | AP32: =SUM(AG32:AO32) -> 74873409
M33: =B33-'Exec.Summary_Liquiplanung ORG'!B33 -> 0 | N33: =C33-'Exec.Summary_Liquiplanung ORG'!C33 -> 0 | O33: =D33-'Exec.Summary_Liquiplanung ORG'!D33 -> 0 | P33: =E33-'Exec.Summary_Liquiplanung ORG'!E33 -> 0 | Q33: =F33-'Exec.Summary_Liquiplanung ORG'!F33 -> 0 | R33: =G33-'Exec.Summary_Liquiplanung ORG'!G33 -> 0 | S33: =H33-'Exec.Summary_Liquiplanung ORG'!H33 -> 0 | T33: =SUM(M33:S33) -> 0
A34: EINNAHMEN
A35: Vorauszahlungen | B35: =Dezember24!AH35 -> 0 | C35: =Januar!AH35 -> 0 | D35: =Februar!AH35 -> 0 | E35: =März!AH35 -> 0 | F35: =April!AH35 -> 0 | G35: =Mai!AH35 -> 0 | H35: =Juni!AH35 -> 0 | I35: =Juli!AH35 -> 0 | J35: =August!AH35 -> 0 | K35: =September!AH35 -> 0 | M35: =B35-'Exec.Summary_Liquiplanung ORG'!B35 -> 0 | N35: =C35-'Exec.Summary_Liquiplanung ORG'!C35 -> 0 | O35: =D35-'Exec.Summary_Liquiplanung ORG'!D35 -> 0 | P35: =E35-'Exec.Summary_Liquiplanung ORG'!E35 -> 0 | Q35: =F35-'Exec.Summary_Liquiplanung ORG'!F35 -> 0 | R35: =G35-'Exec.Summary_Liquiplanung ORG'!G35 -> 0 | S35: =H35-'Exec.Summary_Liquiplanung ORG'!H35 -> 0 | T35: =SUM(M35:S35) -> 0 | V35: 0 | W35: 0 | X35: 0 | Y35: 0 | Z35: 0 | AA35: 0 | AB35: 0 | AC35: 0 | AD35: 0 | AE35: 0 | AG35: 0 | AH35: 0 | AI35: 0 | AJ35: 0 | AK35: 0 | AL35: 0 | AM35: 0 | AN35: 0 | AO35: 0 | AP35: 0
A36: Bareinzahlungen | B36: =Dezember24!AH36 -> 0 | C36: =Januar!AH36 -> 0 | D36: =Februar!AH36 -> 0 | E36: =März!AH36 -> 0 | F36: =April!AH36 -> 0 | G36: =Mai!AH36 -> 0 | H36: =Juni!AH36 -> 0 | I36: =Juli!AH36 -> 0 | J36: =August!AH36 -> 0 | K36: =September!AH36 -> 0 | M36: =B36-'Exec.Summary_Liquiplanung ORG'!B36 -> 0 | N36: =C36-'Exec.Summary_Liquiplanung ORG'!C36 -> 0 | O36: =D36-'Exec.Summary_Liquiplanung ORG'!D36 -> 0 | P36: =E36-'Exec.Summary_Liquiplanung ORG'!E36 -> 0 | Q36: =F36-'Exec.Summary_Liquiplanung ORG'!F36 -> 0 | R36: =G36-'Exec.Summary_Liquiplanung ORG'!G36 -> 0 | S36: =H36-'Exec.Summary_Liquiplanung ORG'!H36 -> 0 | T36: =SUM(M36:S36) -> 0 | V36: 0 | W36: 0 | X36: 0 | Y36: 0 | Z36: 0 | AA36: 0 | AB36: 0 | AC36: 0 | AD36: 0 | AE36: 0 | AG36: 0 | AH36: 0 | AI36: 0 | AJ36: 0 | AK36: 0 | AL36: 0 | AM36: 0 | AN36: 0 | AO36: 0 | AP36: 0
A37: Umbuchungen S-Zentral | B37: =Dezember24!AH37 -> 0 | C37: =Januar!AH37 -> 0 | D37: =Februar!AH37 -> 0 | E37: =März!AH37 -> 0 | F37: =April!AH37 -> 0 | G37: =Mai!AH37 -> 0 | H37: =Juni!AH37 -> 0 | I37: =Juli!AH37 -> 0 | J37: =August!AH37 -> 0 | K37: =September!AH37 -> 0 | M37: =B37-'Exec.Summary_Liquiplanung ORG'!B37 -> 0 | N37: =C37-'Exec.Summary_Liquiplanung ORG'!C37 -> 0 | O37: =D37-'Exec.Summary_Liquiplanung ORG'!D37 -> 0 | P37: =E37-'Exec.Summary_Liquiplanung ORG'!E37 -> 0 | Q37: =F37-'Exec.Summary_Liquiplanung ORG'!F37 -> 0 | R37: =G37-'Exec.Summary_Liquiplanung ORG'!G37 -> 0 | S37: =H37-'Exec.Summary_Liquiplanung ORG'!H37 -> 0 | T37: =SUM(M37:S37) -> 0 | V37: 0 | W37: 0 | X37: 0 | Y37: 0 | Z37: 0 | AA37: 0 | AB37: 0 | AC37: 0 | AD37: 0 | AE37: 0 | AG37: 0 | AH37: 0 | AI37: 0 | AJ37: 0 | AK37: 0 | AL37: 0 | AM37: 0 | AN37: 0 | AO37: 0 | AP37: 0
A38: interne Zahlungen | B38: =Dezember24!AH38 -> 0 | C38: =Januar!AH38 -> 0 | D38: =Februar!AH38 -> 0 | E38: =März!AH38 -> 0 | F38: =April!AH38 -> 0 | G38: =Mai!AH38 -> 0 | H38: =Juni!AH38 -> 0 | I38: =Juli!AH38 -> 0 | J38: =August!AH38 -> 0 | K38: =September!AH38 -> 0 | M38: =B38-'Exec.Summary_Liquiplanung ORG'!B38 -> 0 | N38: =C38-'Exec.Summary_Liquiplanung ORG'!C38 -> 0 | O38: =D38-'Exec.Summary_Liquiplanung ORG'!D38 -> 0 | P38: =E38-'Exec.Summary_Liquiplanung ORG'!E38 -> 0 | Q38: =F38-'Exec.Summary_Liquiplanung ORG'!F38 -> 0 | R38: =G38-'Exec.Summary_Liquiplanung ORG'!G38 -> 0 | S38: =H38-'Exec.Summary_Liquiplanung ORG'!H38 -> 0 | T38: =SUM(M38:S38) -> 0 | V38: 0 | W38: 0 | X38: 0 | Y38: 0 | Z38: 0 | AA38: 0 | AB38: 0 | AC38: 0 | AD38: 0 | AE38: 0 | AG38: 0 | AH38: 0 | AI38: 0 | AJ38: 0 | AK38: 0 | AL38: 0 | AM38: 0 | AN38: 0 | AO38: 0 | AP38: 0
A39: Besonderheiten | B39: =Dezember24!AH39 -> 0 | C39: =Januar!AH39 -> 0 | D39: =Februar!AH39 -> 20889.36 | E39: =März!AH39 -> 2229727.3 | F39: =April!AH39 -> 0 | G39: =Mai!AH39 -> 0 | H39: =Juni!AH39 -> 0 | I39: =Juli!AH39 -> 0 | J39: =August!AH39 -> 0 | K39: =September!AH39 -> 0 | M39: =B39-'Exec.Summary_Liquiplanung ORG'!B39 -> 0 | N39: =C39-'Exec.Summary_Liquiplanung ORG'!C39 -> 0 | O39: =D39-'Exec.Summary_Liquiplanung ORG'!D39 -> 20889.36 | P39: =E39-'Exec.Summary_Liquiplanung ORG'!E39 -> 2229727.3 | Q39: =F39-'Exec.Summary_Liquiplanung ORG'!F39 -> 0 | R39: =G39-'Exec.Summary_Liquiplanung ORG'!G39 -> 0 | S39: =H39-'Exec.Summary_Liquiplanung ORG'!H39 -> 0 | T39: =SUM(M39:S39) -> 2250616.7 | V39: 0 | W39: 0 | X39: 0 | Y39: 0 | Z39: 0 | AA39: 0 | AB39: 0 | AC39: 0 | AD39: 0 | AE39: 0 | AG39: 0 | AH39: 0 | AI39: 20889.36 | AJ39: 2229727.3 | AK39: 0 | AL39: 0 | AM39: 0 | AN39: 0 | AO39: 0 | AP39: 0
A40: Kreditkarten | B40: =Dezember24!AH40 -> 475599.89 | C40: =Januar!AH40 -> 3810010.6 | D40: =Februar!AH40 -> 4298434.4 | E40: =März!AH40 -> 4815059.8 | F40: =April!AH40 -> 6380242.7 | G40: =Mai!AH40 -> 4908414.5 | H40: =Juni!AH40 -> 5222355.2 | I40: =Juli!AH40 -> 4421086.2 | J40: =August!AH40 -> 4580229.7 | K40: =September!AH40 -> 6659730.2 | M40: =B40-'Exec.Summary_Liquiplanung ORG'!B40 -> -492150.11 | N40: =C40-'Exec.Summary_Liquiplanung ORG'!C40 -> -560942.47 | O40: =D40-'Exec.Summary_Liquiplanung ORG'!D40 -> 390040.89 | P40: =E40-'Exec.Summary_Liquiplanung ORG'!E40 -> -411219.6 | Q40: =F40-'Exec.Summary_Liquiplanung ORG'!F40 -> 2223863.1 | R40: =G40-'Exec.Summary_Liquiplanung ORG'!G40 -> -298647.62 | S40: =H40-'Exec.Summary_Liquiplanung ORG'!H40 -> 94992.426 | T40: =SUM(M40:S40) -> 945936.61 | V40: =B40-AG40 -> 0 | W40: =C40-AH40 -> 0 | X40: =D40-AI40 -> -19642.755 | Y40: =E40-AJ40 -> 154508.38 | Z40: =F40-AK40 -> 305211.42 | AA40: =G40-AL40 -> -1127310.7 | AB40: =H40-AM40 -> -131101.21 | AC40: =I40-AN40 -> -297951.82 | AD40: =J40-AO40 -> -183826.53 | AE40: =SUM(V40:AD40) -> -1300113.2 | AG40: 475599.89 | AH40: 3810010.6 | AI40: 4318077.2 | AJ40: 4660551.4 | AK40: 6075031.2 | AL40: 6035725.2 | AM40: 5353456.4 | AN40: 4719038 | AO40: 4764056.2 | AP40: =SUM(AG40:AO40) -> 40211546
A41: Debitoren | B41: =Dezember24!AH41 -> 32289.84 | C41: =Januar!AH41 -> 1555527.7 | D41: =Februar!AH41 -> 2856728.1 | E41: =März!AH41 -> 4138219.5 | F41: =April!AH41 -> 4392927.5 | G41: =Mai!AH41 -> 5117116.4 | H41: =Juni!AH41 -> 4920793.1 | I41: =Juli!AH41 -> 4945724.8 | J41: =August!AH41 -> 4539038.7 | K41: =September!AH41 -> 5557050 | M41: =B41-'Exec.Summary_Liquiplanung ORG'!B41 -> -2181428.9 | N41: =C41-'Exec.Summary_Liquiplanung ORG'!C41 -> -1621886.3 | O41: =D41-'Exec.Summary_Liquiplanung ORG'!D41 -> -674081.88 | P41: =E41-'Exec.Summary_Liquiplanung ORG'!E41 -> -302819.32 | Q41: =F41-'Exec.Summary_Liquiplanung ORG'!F41 -> 31054.996 | R41: =G41-'Exec.Summary_Liquiplanung ORG'!G41 -> 167905.63 | S41: =H41-'Exec.Summary_Liquiplanung ORG'!H41 -> 16251.308 | T41: =SUM(M41:S41) -> -4565004.5 | V41: =B41-AG41 -> 0 | W41: =C41-AH41 -> 0 | X41: =D41-AI41 -> -9794.3967 | Y41: =E41-AJ41 -> 48032.857 | Z41: =F41-AK41 -> -12733.599 | AA41: =G41-AL41 -> 56832.146 | AB41: =H41-AM41 -> 0 | AC41: =I41-AN41 -> -67542.682 | AD41: =J41-AO41 -> -129265.75 | AE41: =SUM(V41:AD41) -> -114471.42 | AG41: 32289.84 | AH41: 1555527.7 | AI41: 2866522.5 | AJ41: 4090186.7 | AK41: 4405661.1 | AL41: 5060284.3 | AM41: 4920793.1 | AN41: 5013267.4 | AO41: 4668304.5 | AP41: =SUM(AG41:AO41) -> 32612837
A42: Summe Einnahmen | B42: =Dezember24!AH42 -> 507889.73 | C42: =Januar!AH42 -> 5365538.3 | D42: =Februar!AH42 -> 7176051.9 | E42: =März!AH42 -> 11183007 | F42: =April!AH42 -> 10773170 | G42: =Mai!AH42 -> 10025531 | H42: =Juni!AH42 -> 10143148 | I42: =Juli!AH42 -> 9366811 | J42: =August!AH42 -> 9119268.4 | K42: =September!AH42 -> 12216780 | M42: =B42-'Exec.Summary_Liquiplanung ORG'!B42 -> -2673579 | N42: =C42-'Exec.Summary_Liquiplanung ORG'!C42 -> -2182828.8 | O42: =D42-'Exec.Summary_Liquiplanung ORG'!D42 -> -263151.63 | P42: =E42-'Exec.Summary_Liquiplanung ORG'!E42 -> 1515688.4 | Q42: =F42-'Exec.Summary_Liquiplanung ORG'!F42 -> 2254918.1 | R42: =G42-'Exec.Summary_Liquiplanung ORG'!G42 -> -130741.99 | S42: =H42-'Exec.Summary_Liquiplanung ORG'!H42 -> 111243.73 | T42: =SUM(M42:S42) -> -1368451.2 | V42: =SUM(V40:V41) -> 0 | W42: =SUM(W40:W41) -> 0 | X42: =SUM(X40:X41) -> -29437.152 | Y42: =SUM(Y40:Y41) -> 202541.23 | Z42: =SUM(Z40:Z41) -> 292477.82 | AA42: =SUM(AA40:AA41) -> -1070478.5 | AB42: =SUM(AB40:AB41) -> -131101.21 | AC42: =SUM(AC40:AC41) -> -365494.5 | ... AE42: =SUM(AE40:AE41) -> -1414584.6 | AG42: 507889.73 | AH42: 5365538.3 | AI42: 7205489.1 | AJ42: 10980465 | AK42: 10480692 | AL42: 11096010 | AM42: 10274250 | AN42: 9732305.5 | AO42: 9432360.7 | AP42: =SUM(AP40:AP41) -> 72824383
C43: =Januar!AH43 | D43: =Februar!AH43 | F43: =April!AH43 | G43: =Mai!AH43 | H43: =Juni!AH43 | I43: =Juli!AH43 | J43: =August!AH43 | K43: =September!AH43 | T43: =SUM(M43:S43) -> 0 | AE43: 0 | AP43: 0
A44: Zwischensumme | B44: =Dezember24!AH44 -> 442499.73 | C44: =Januar!AH44 -> 652888.1 | D44: =Februar!AH44 -> 615050.38 | E44: =März!AH44 -> 3371018.1 | F44: =April!AH44 -> 2913712.9 | G44: =Mai!AH44 -> -1890291 | H44: =Juni!AH44 -> 2120610.1 | I44: =Juli!AH44 -> -2732964 | J44: =August!AH44 -> -2552501.2 | K44: =September!AH44 -> -1471128 | M44: =B44-'Exec.Summary_Liquiplanung ORG'!B44 -> -1318969 | N44: =C44-'Exec.Summary_Liquiplanung ORG'!C44 -> -700168.37 | O44: =D44-'Exec.Summary_Liquiplanung ORG'!D44 -> 25186.702 | P44: =E44-'Exec.Summary_Liquiplanung ORG'!E44 -> 4549594.2 | Q44: =F44-'Exec.Summary_Liquiplanung ORG'!F44 -> 3913389.5 | R44: =G44-'Exec.Summary_Liquiplanung ORG'!G44 -> -1622441.7 | S44: =H44-'Exec.Summary_Liquiplanung ORG'!H44 -> 5052502.2 | T44: =SUM(M44:S44) -> 9899093.5 | V44: =B44-AG44 -> 0 | W44: =C44-AH44 -> 0 | X44: =D44-AI44 -> -29437.152 | Y44: =E44-AJ44 -> 202541.23 | Z44: =F44-AK44 -> 292477.82 | AA44: =G44-AL44 -> -1557150.6 | AB44: =H44-AM44 -> 1091569.2 | AC44: =I44-AN44 -> 495886.77 | AD44: =J44-AO44 -> 2242544.9 | AE44: =SUM(V44:AD44) -> 2738432.1 | AG44: 442499.73 | AH44: 652888.1 | AI44: 644487.53 | AJ44: 3168476.9 | AK44: 2621235.1 | AL44: -333140.35 | AM44: 1029040.9 | AN44: -3228850.8 | AO44: -4795046.1 | AP44: =SUM(AG44:AO44) -> 201591.02
M45: =B45-'Exec.Summary_Liquiplanung ORG'!B45 -> 0 | N45: =C45-'Exec.Summary_Liquiplanung ORG'!C45 -> 0 | O45: =D45-'Exec.Summary_Liquiplanung ORG'!D45 -> 0 | P45: =E45-'Exec.Summary_Liquiplanung ORG'!E45 -> 0 | Q45: =F45-'Exec.Summary_Liquiplanung ORG'!F45 -> 0 | R45: =G45-'Exec.Summary_Liquiplanung ORG'!G45 -> 0 | S45: =H45-'Exec.Summary_Liquiplanung ORG'!H45 -> 0 | T45: =SUM(M45:S45) -> 0 | V45: 0 | W45: 0 | X45: 0 | Y45: 0 | Z45: 0 | AA45: 0 | AB45: 0 | AC45: 0 | AD45: 0 | AE45: 0 | AP45: 0
A46: Liquiditätshilfe | M46: =B46-'Exec.Summary_Liquiplanung ORG'!B46 -> 0 | N46: =C46-'Exec.Summary_Liquiplanung ORG'!C46 -> 0 | O46: =D46-'Exec.Summary_Liquiplanung ORG'!D46 -> 0 | P46: =E46-'Exec.Summary_Liquiplanung ORG'!E46 -> 0 | Q46: =F46-'Exec.Summary_Liquiplanung ORG'!F46 -> 0 | R46: =G46-'Exec.Summary_Liquiplanung ORG'!G46 -> 0 | S46: =H46-'Exec.Summary_Liquiplanung ORG'!H46 -> 0 | T46: =SUM(M46:S46) -> 0 | V46: 0 | W46: 0 | X46: 0 | Y46: 0 | Z46: 0 | AA46: 0 | AB46: 0 | AC46: 0 | AD46: 0 | AE46: 0 | AP46: 0
M47: =B47-'Exec.Summary_Liquiplanung ORG'!B47 -> 0 | N47: =C47-'Exec.Summary_Liquiplanung ORG'!C47 -> 0 | O47: =D47-'Exec.Summary_Liquiplanung ORG'!D47 -> 0 | P47: =E47-'Exec.Summary_Liquiplanung ORG'!E47 -> 0 | Q47: =F47-'Exec.Summary_Liquiplanung ORG'!F47 -> 0 | R47: =G47-'Exec.Summary_Liquiplanung ORG'!G47 -> 0 | S47: =H47-'Exec.Summary_Liquiplanung ORG'!H47 -> 0 | T47: =SUM(M47:S47) -> 0 | V47: 0 | W47: 0 | X47: 0 | Y47: 0 | Z47: 0 | AA47: 0 | AB47: 0 | AC47: 0 | AD47: 0 | AE47: 0 | AP47: 0
M48: =B48-'Exec.Summary_Liquiplanung ORG'!B48 -> 0 | N48: =C48-'Exec.Summary_Liquiplanung ORG'!C48 -> 0 | O48: =D48-'Exec.Summary_Liquiplanung ORG'!D48 -> 0 | P48: =E48-'Exec.Summary_Liquiplanung ORG'!E48 -> 0 | Q48: =F48-'Exec.Summary_Liquiplanung ORG'!F48 -> 0 | R48: =G48-'Exec.Summary_Liquiplanung ORG'!G48 -> 0 | S48: =H48-'Exec.Summary_Liquiplanung ORG'!H48 -> 0 | T48: =SUM(M48:S48) -> 0 | V48: 0 | W48: 0 | X48: 0 | Y48: 0 | Z48: 0 | AA48: 0 | AB48: 0 | AC48: 0 | AD48: 0 | AE48: 0 | AP48: 0
M49: =B49-'Exec.Summary_Liquiplanung ORG'!B49 -> 0 | N49: =C49-'Exec.Summary_Liquiplanung ORG'!C49 -> 0 | O49: =D49-'Exec.Summary_Liquiplanung ORG'!D49 -> 0 | P49: =E49-'Exec.Summary_Liquiplanung ORG'!E49 -> 0 | Q49: =F49-'Exec.Summary_Liquiplanung ORG'!F49 -> 0 | R49: =G49-'Exec.Summary_Liquiplanung ORG'!G49 -> 0 | S49: =H49-'Exec.Summary_Liquiplanung ORG'!H49 -> 0 | T49: =SUM(M49:S49) -> 0 | V49: 0 | W49: 0 | X49: 0 | Y49: 0 | Z49: 0 | AA49: 0 | AB49: 0 | AC49: 0 | AD49: 0 | AE49: 0 | AP49: 0
A50: Closing Balance | B50: =Dezember24!AG50 -> 3442499.7 | C50: =Januar!AH50 -> 4095387.8 | D50: =Februar!AH50 -> 4710438.2 | E50: =März!AG50 -> 8081456.3 | F50: =April!AH50 -> 10995169 | G50: =Mai!AH50 -> 9104878.3 | H50: =Juni!AH50 -> 11225488 | I50: =Juli!AH50 -> 8492524.3 | J50: =August!AH50 -> 5940023.1 | K50: =September!AH50 -> 4468895.1 | M50: =B50-'Exec.Summary_Liquiplanung ORG'!B50 -> -1318969 | N50: =C50-'Exec.Summary_Liquiplanung ORG'!C50 -> -2019137.4 | O50: =D50-'Exec.Summary_Liquiplanung ORG'!D50 -> -1993950.7 | P50: =E50-'Exec.Summary_Liquiplanung ORG'!E50 -> 2555643.5 | Q50: =F50-'Exec.Summary_Liquiplanung ORG'!F50 -> 6469033.1 | R50: =G50-'Exec.Summary_Liquiplanung ORG'!G50 -> 4846591.4 | S50: =H50-'Exec.Summary_Liquiplanung ORG'!H50 -> 9899093.5 | T50: =S50 -> 9899093.5 | V50: =B50-AG50 -> 0 | W50: =C50-AH50 -> 0 | X50: =D50-AI50 -> -29437.152 | Y50: =E50-AJ50 -> 173104.08 | Z50: =F50-AK50 -> 465581.91 | AA50: =G50-AL50 -> -1091568.7 | AB50: =H50-AM50 -> 0.43404665 | AC50: =I50-AN50 -> 495887.2 | AD50: =J50-AO50 -> 2738432.1 | AE50: =AD50 -> 2738432.1 | AG50: 3442499.7 | AH50: 4095387.8 | AI50: 4739875.4 | AJ50: 7908352.2 | AK50: 10529587 | AL50: 10196447 | AM50: 11225488 | AN50: 7996637.1 | AO50: 3201591 | AP50: =AO50 -> 3201591
A51: Closing Balance | B51: 4761468.8 | C51: 6114525.2 | D51: 6704388.9 | E51: 5525812.8 | F51: 4526136.2 | G51: 4258286.9 | H51: 1326394.8 | I51: 1326394.8 | J51: 1326394.8 | K51: 1326394.8 | AN51: 1326394.8 | AO51: 1326394.8
B52: =B50-B51 -> -1318969 | C52: =C50-C51 -> -2019137.4 | D52: =D50-D51 -> -1993950.7 | E52: =E50-E51 -> 2555643.5 | F52: =F50-F51 -> 6469033.1 | G52: =G50-G51 -> 4846591.4 | H52: =H50-H51 -> 9899093.5 | I52: =I50-I51 -> 7166129.5 | ... K52: =K50-K51 -> 3142500.3 | AN52: =AN50-AN51 -> 6670242.3 | AO52: =AO50-AO51 -> 1875196.2
A54: Erläuterung der Veränderungen
A55: Positiver Impakt Juni | B55: Betrag
A59: Negativer Impakt | B59: Betrag
A63: Net Impakt | B63: =SUM(B56:B62) -> 0

Sheet Exec Summary_Sanierung
A1: Ausblick 2. HJ 2025 Sanierung
A2: LH AG 2025 | B2: Budget | C2: Total Year | D2: Jan | E2: Feb | F2: Mar | G2: Apr | H2: May | I2: Jun | J2: Jul | K2: Aug | L2: Sep | M2: Oct | N2: Nov | O2: Dec | P2: Subtotals First Half | Q2: Subtotals Second Half
A3: Umsätze | B3: Revenues budget | C3: ='Budget 25 LH AG'!C11 -> 1.2198848e+08 | D3: ='Budget 25 LH AG'!D11 -> 7240087.4 | E3: ='Budget 25 LH AG'!E11 -> 8314846.3 | F3: ='Budget 25 LH AG'!F11 -> 11118561 | G3: ='Budget 25 LH AG'!G11 -> 8842420.1 | H3: ='Budget 25 LH AG'!H11 -> 11077677 | I3: ='Budget 25 LH AG'!I11 -> 10908122 | J3: ='Budget 25 LH AG'!J11 -> 9390566.3 | ... Q3: ='Budget 25 LH AG'!Q11 -> 64486763
B4: Hotels only budget | C4: ='Hotels Only'!C11 -> 93365067 | D4: ='Hotels Only'!D11 -> 5324462.5 | E4: ='Hotels Only'!E11 -> 6311402.5 | F4: ='Hotels Only'!F11 -> 8569487.7 | G4: ='Hotels Only'!G11 -> 6313744 | H4: ='Hotels Only'!H11 -> 8687115.7 | I4: ='Hotels Only'!I11 -> 7353274.8 | J4: ='Hotels Only'!J11 -> 6427992.7 | ... O4: ='Hotels Only'!O11 -> 6798545.1 | P4: =SUM(D4:I4) -> 42559487 | Q4: =SUM(E4:J4) -> 43663017
B5: HV budget | C5: ='HQ only'!C11 -> 15256234 | D5: ='HQ only'!D11 -> 552614.45 | E5: ='HQ only'!E11 -> 528587.06 | F5: ='HQ only'!F11 -> 1070583 | G5: ='HQ only'!G11 -> 610468.18 | H5: ='HQ only'!H11 -> 1537438.9 | I5: ='HQ only'!I11 -> 1012045.7 | J5: ='HQ only'!J11 -> 1924757.9 | ... O5: ='HQ only'!O11 -> 1454934.3 | P5: =SUM(D5:I5) -> 5311737.3 | Q5: =SUM(E5:J5) -> 6683880.8
B6: Risk Adjustment Hotels | C6: 0.15 | D6: =-D71*$C$6 -> -798669.38 | E6: =-E71*$C$6 -> -946710.37 | F6: =-F71*$C$6 -> -1285423.2 | G6: =-G71*$C$6 -> -947061.61 | H6: =-H71*$C$6 -> -1303067.3 | I6: =-I71*$C$6 -> -1102991.2 | J6: =-J71*$R$6 -> -321399.64 | K6: =-K71*$R$6 -> -355291.06 | L6: =-L71*$R$6 -> -527493.27 | M6: =-M71*$R$6 -> -521608.94 | N6: =-N71*$R$6 -> -474558.82 | O6: =-O71*$R$6 -> -339927.26 | P6: =SUM(D6:I6) -> -6383923.1 | Q6: =SUM(E6:J6) -> -5906653.3 | R6: 0.05
B7: Risk Adjustment HQ | C7: 0.15 | D7: =-D72*$C$7 -> -82892.167 | E7: =-E72*$C$7 -> -79288.059 | F7: =-F72*$C$7 -> -160587.44 | G7: =-G72*$C$7 -> -91570.227 | H7: =-H72*$C$7 -> -230615.83 | I7: =-I72*$C$7 -> -151806.86 | J7: =-J72*$R$7 -> -96237.897 | K7: =-K72*$R$7 -> -97105.529 | L7: =-L72*$R$7 -> -95045.808 | M7: =-M72*$R$7 -> -78050.556 | N7: =-N72*$R$7 -> -58038.351 | O7: =-O72*$R$7 -> -72746.714 | P7: =SUM(D7:I7) -> -796760.59 | Q7: =SUM(E7:J7) -> -810106.32 | R7: 0.05
D8: =SUM(D4:D7) -> 4995515.4 | E8: =SUM(E4:E7) -> 5813991.1 | F8: =SUM(F4:F7) -> 8194060 | G8: =SUM(G4:G7) -> 5885580.4 | H8: =SUM(H4:H7) -> 8690871.4 | I8: =SUM(I4:I7) -> 7110522.5 | J8: =SUM(J4:J7) -> 7935113.1 | K8: =SUM(K4:K7) -> 8595535.2 | ... O8: =SUM(O4:O7) -> 7840805.4 | P8: =SUM(D8:I8) -> 40690541 | Q8: =SUM(E8:J8) -> 43630139
A10: EBITDA Budgeted 2025 | B10: EBITDA LH AG | C10: -3120046.1 | D10: -2284871.9 | E10: -1763626.9 | F10: -132297.08 | G10: -1139371.9 | H10: 565331.26 | I10: 130761.96 | J10: -312855.83 | K10: 214147.41 | L10: 1635199.2 | M10: 1381083.4 | N10: -116049.96 | O10: -1297495.7 | P10: =SUM(D10:I10) -> -4624074.6 | Q10: =SUM(J10:O10) -> 1504028.5
B11: EBITDA Hotels | C11: ='Hotels Only'!C153 -> -5924419.9 | D11: ='Hotels Only'!D153 -> -2118525.1 | E11: ='Hotels Only'!E153 -> -1714838.9 | F11: ='Hotels Only'!F153 -> 478508.93 | G11: ='Hotels Only'!G153 -> -1661239.7 | H11: ='Hotels Only'!H153 -> 247414.62 | I11: ='Hotels Only'!I153 -> -564157.2 | J11: ='Hotels Only'!J153 -> -1373154.8 | ... O11: ='Hotels Only'!O153 -> -997739.73 | P11: =SUM(D11:I11) -> -5332837.4 | Q11: =SUM(J11:O11) -> -591582.55
B12: EBITDA HQ | C12: ='HQ only'!C153 -> -4193451.4 | D12: ='HQ only'!D153 -> -468777.36 | E12: ='HQ only'!E153 -> -1268229.6 | F12: ='HQ only'!F153 -> -1457014 | G12: ='HQ only'!G153 -> -483166.92 | H12: ='HQ only'!H153 -> -24692.4 | I12: ='HQ only'!I153 -> -722683.22 | J12: ='HQ only'!J153 -> 405271.35 | ... O12: ='HQ only'!O153 -> -458055.68 | P12: =SUM(D12:I12) -> -4424563.6 | Q12: =SUM(J12:O12) -> 231112.18
A14: Hotels | B14: EBITDA 25 budget | C14: =C11 -> -5924419.9 | D14: =D11 -> -2118525.1 | E14: =E11 -> -1714838.9 | F14: =F11 -> 478508.93 | G14: =G11 -> -1661239.7 | H14: =H11 -> 247414.62 | I14: =I11 -> -564157.2 | J14: =J11 -> -1373154.8 | ... O14: =O11 -> -997739.73 | P14: =SUM(D14:I14) -> -5332837.4 | Q14: =SUM(J14:O14) -> -591582.55
B15: Kudamm | C15: =Kudamm!C153 -> -1063749.1 | D15: =Kudamm!D153 -> -227478.81 | E15: =Kudamm!E153 -> -101805.65 | F15: =Kudamm!F153 -> -95446.9 | G15: =Kudamm!G153 -> -183430.87 | H15: =Kudamm!H153 -> -59454.73 | I15: =Kudamm!I153 -> -47923.902 | J15: =Kudamm!J153 -> -106849.36 | ... O15: =Kudamm!O153 -> -103045.97 | P15: =SUM(D15:I15) -> -715540.86 | Q15: =SUM(J15:O15) -> -348208.2 | R15: =P15+Q15-C15 -> 0
B16: Rent -25%/50% | D16: =226260/1.19*25% -> 47533.613 | E16: =+D16 -> 47533.613 | F16: =226260/1.19*25% -> 47533.613 | G16: =226260/1.19*25% -> 47533.613 | H16: =226260/1.19*25% -> 47533.613 | I16: =226260/1.19*25% -> 47533.613 | J16: =226260/1.19*50% -> 95067.227 | K16: =226260/1.19*50% -> 95067.227 | L16: =226260/1.19*50% -> 95067.227 | M16: =226260/1.19*50% -> 95067.227 | N16: =226260/1.19*50% -> 95067.227 | O16: =226260/1.19*50% -> 95067.227 | P16: =SUM(D16:I16) -> 285201.68 | Q16: =SUM(J16:O16) -> 570403.36 | R16: Eher exit
B17: DUS Airport | C17: =Airport!C153 -> -858544 | D17: =Airport!D153 -> -145619.14 | E17: =Airport!E153 -> -145124.77 | F17: =Airport!F153 -> -8064.78 | G17: =Airport!G153 -> -241808.88 | H17: =Airport!H153 -> -92663.149 | I17: =Airport!I153 -> -150106.31 | J17: =Airport!J153 -> -213821.6 | ... O17: =Airport!O153 -> -84419.19 | P17: =SUM(D17:I17) -> -783387.02 | Q17: =SUM(J17:O17) -> -75156.977 | R17: =P17+Q17-C17 -> 0
B18: Rent -25% | D18: =190110/1.19*25% -> 39939.076 | E18: =+D18 -> 39939.076 | F18: =190110/1.19*25% -> 39939.076 | G18: =190110/1.19*25% -> 39939.076 | H18: =190110/1.19*25% -> 39939.076 | I18: =190110/1.19*25% -> 39939.076 | J18: =190110/1.19*25% -> 39939.076 | K18: =190110/1.19*25% -> 39939.076 | L18: =190110/1.19*25% -> 39939.076 | M18: =190110/1.19*25% -> 39939.076 | ... O18: =190110/1.19*25% -> 39939.076 | P18: =SUM(D18:I18) -> 239634.45 | Q18: =SUM(J18:O18) -> 239634.45 | R18: Eher exit
B19: Höchst | C19: =Höchst!C153 -> -1205030.1 | D19: =Höchst!D153 -> -212155.9 | E19: =Höchst!E153 -> -120714.41 | F19: =Höchst!F153 -> 10949.47 | G19: =Höchst!G153 -> -263290.92 | H19: =Höchst!H153 -> -51561.218 | I19: =Höchst!I153 -> -45336.009 | J19: =Höchst!J153 -> -213719.66 | ... O19: =Höchst!O153 -> -225681.53 | P19: =SUM(D19:I19) -> -682108.99 | Q19: =SUM(J19:O19) -> -522921.09 | R19: =P19+Q19-C19 -> 0
B20: Rent - 30% | D20: =886563.3/3/1.19*30% -> 74501.118 | E20: =+D20 -> 74501.118 | F20: =886563.3/3/1.19*30% -> 74501.118 | G20: =886563.3/3/1.19*30% -> 74501.118 | H20: =886563.3/3/1.19*30% -> 74501.118 | I20: =886563.3/3/1.19*30% -> 74501.118 | J20: =886563.3/3/1.19*30% -> 74501.118 | K20: =886563.3/3/1.19*30% -> 74501.118 | L20: =886563.3/3/1.19*30% -> 74501.118 | M20: =886563.3/3/1.19*30% -> 74501.118 | ... O20: =886563.3/3/1.19*30% -> 74501.118 | P20: =SUM(D20:I20) -> 447006.71 | Q20: =SUM(J20:O20) -> 447006.71 | R20: Eher exit
B21: Main Plaza | C21: ='Main Plaza'!C153 -> -1499349.8 | D21: ='Main Plaza'!D153 -> -274552.14 | E21: ='Main Plaza'!E153 -> -166853.12 | F21: ='Main Plaza'!F153 -> -76400.01 | G21: ='Main Plaza'!G153 -> -272562.79 | H21: ='Main Plaza'!H153 -> -145846.09 | I21: ='Main Plaza'!I153 -> -98949.768 | J21: ='Main Plaza'!J153 -> -162913.04 | ... O21: ='Main Plaza'!O153 -> -109066.93 | P21: =SUM(D21:I21) -> -1035163.9 | Q21: =SUM(J21:O21) -> -464185.87 | R21: =P21+Q21-C21 -> 0
B22: Rent -30% | D22: =189468/1.19*30% -> 47765.042 | E22: =+D22 -> 47765.042 | F22: =189468/1.19*30% -> 47765.042 | G22: =189468/1.19*30% -> 47765.042 | H22: =189468/1.19*30% -> 47765.042 | I22: =189468/1.19*30% -> 47765.042 | J22: =189468/1.19*30% -> 47765.042 | K22: =189468/1.19*30% -> 47765.042 | L22: =189468/1.19*30% -> 47765.042 | M22: =189468/1.19*30% -> 47765.042 | ... O22: =189468/1.19*30% -> 47765.042 | P22: =SUM(D22:I22) -> 286590.25 | Q22: =SUM(J22:O22) -> 286590.25
B23: Leverkusen | C23: =Leverkusen!C153 -> 561711.5 | D23: =Leverkusen!D153 -> 11652.16 | E23: =Leverkusen!E153 -> -16003.8 | F23: =Leverkusen!F153 -> 69980.79 | G23: =Leverkusen!G153 -> -65092.08 | H23: =Leverkusen!H153 -> 55107.465 | I23: =Leverkusen!I153 -> 47326.389 | J23: =Leverkusen!J153 -> -70594.638 | ... O23: =Leverkusen!O153 -> 45519.038 | P23: =SUM(D23:I23) -> 102970.92 | Q23: =SUM(J23:O23) -> 458740.57 | R23: kündigen und nachverhandeln
B24: Seestern | C24: =Seestern!C153 -> 587850.38 | D24: =Seestern!D153 -> -10504.74 | E24: =Seestern!E153 -> -203276.93 | F24: =Seestern!F153 -> 200126.03 | G24: =Seestern!G153 -> -52909.46 | H24: =Seestern!H153 -> 103015.5 | I24: =Seestern!I153 -> -15091.582 | J24: =Seestern!J153 -> -124845.78 | ... O24: =Seestern!O153 -> -24492.333 | P24: =SUM(D24:I24) -> 21358.82 | Q24: =SUM(J24:O24) -> 566491.56 | R24: =P24+Q24-C24 -> 0
B25: Michel | C25: =Michel!C153 -> 1498105.8 | D25: =Michel!D153 -> -164842.28 | E25: =Michel!E153 -> -196350.38 | F25: =Michel!F153 -> 89456.43 | G25: =Michel!G153 -> 100022.62 | H25: =Michel!H153 -> 384065.31 | I25: =Michel!I153 -> 256507.41 | J25: =Michel!J153 -> 101063.78 | ... O25: =Michel!O153 -> 101583.61 | P25: =SUM(D25:I25) -> 468859.11 | Q25: =SUM(J25:O25) -> 1029246.7 | R25: =P25+Q25-C25 -> 0
B26: Köln Dom | C26: ='Köln Dom'!C153 -> 120286.13 | D26: ='Köln Dom'!D153 -> -126132.15 | E26: ='Köln Dom'!E153 -> -38758.06 | F26: ='Köln Dom'!F153 -> 79067.62 | G26: ='Köln Dom'!G153 -> 18302.69 | H26: ='Köln Dom'!H153 -> 21909.56 | I26: ='Köln Dom'!I153 -> -6044.1391 | J26: ='Köln Dom'!J153 -> -28080.17 | ... O26: ='Köln Dom'!O153 -> 12496.867 | P26: =SUM(D26:I26) -> -51654.479 | Q26: =SUM(J26:O26) -> 171940.61 | R26: PIP
B27: City Plaza | C27: ='City Plza'!C153 -> 281020.43 | D27: ='City Plza'!D153 -> -208942.58 | E27: ='City Plza'!E153 -> -147468.01 | F27: ='City Plza'!F153 -> 263639.94 | G27: ='City Plza'!G153 -> -11798.61 | H27: ='City Plza'!H153 -> 32594.665 | I27: ='City Plza'!I153 -> -34034.18 | J27: ='City Plza'!J153 -> -156251.91 | ... O27: ='City Plza'!O153 -> 37185.206 | P27: =SUM(D27:I27) -> -106008.77 | Q27: =SUM(J27:O27) -> 387029.2 | R27: PIP
B28: MAA Mainz | C28: ='MAA Mainz'!C153 -> 445680.01 | D28: ='MAA Mainz'!D153 -> -77260.27 | E28: ='MAA Mainz'!E153 -> -34059.46 | F28: ='MAA Mainz'!F153 -> 174602.72 | G28: ='MAA Mainz'!G153 -> -211350.75 | H28: ='MAA Mainz'!H153 -> 28420.521 | I28: ='MAA Mainz'!I153 -> 99978.832 | J28: ='MAA Mainz'!J153 -> 66832.498 | ... O28: ='MAA Mainz'!O153 -> -7567.6414 | P28: =SUM(D28:I28) -> -19668.407 | Q28: =SUM(J28:O28) -> 465348.42 | R28: =P28+Q28-C28 -> 0
B29: Oberstaufen | C29: =Oberstaufen!C153 -> -1484990 | D29: =Oberstaufen!D153 -> -181371.5 | E29: =Oberstaufen!E153 -> -175734.32 | F29: =Oberstaufen!F153 -> -175302 | G29: =Oberstaufen!G153 -> -206233.27 | H29: =Oberstaufen!H153 -> -104388.86 | I29: =Oberstaufen!I153 -> -116504.15 | J29: =Oberstaufen!J153 -> -27307.282 | ... O29: =Oberstaufen!O153 -> -234313.74 | P29: =SUM(D29:I29) -> -959534.1 | Q29: =SUM(J29:O29) -> -525455.86 | R29: =P29+Q29-C29 -> 0
B30: Schliessung | D30: =-D29 -> 181371.5 | E30: =-E29 -> 175734.32 | F30: =-F29 -> 175302 | G30: =-G29 -> 206233.27 | H30: =-H29 -> 104388.86 | I30: =-I29 -> 116504.15 | J30: =-J29 -> 27307.282 | K30: =-K29 -> -13587.221 | ... O30: =-O29 -> 234313.74 | P30: =SUM(D30:I30) -> 959534.1 | Q30: =SUM(J30:O30) -> 525455.86
B31: Sylt | C31: =Sylt!C153 -> -333105.88 | D31: =Sylt!D153 -> -219368.6 | E31: =Sylt!E153 -> -151835.32 | F31: =Sylt!F153 -> -91474.18 | G31: =Sylt!G153 -> -45523.53 | H31: =Sylt!H153 -> 63583.046 | I31: =Sylt!I153 -> 71983.866 | J31: =Sylt!J153 -> 131600.91 | ... O31: =Sylt!O153 -> -120070.21 | P31: =SUM(D31:I31) -> -372634.72 | Q31: =SUM(J31:O31) -> 39528.835 | R31: =P31+Q31-C31 -> 0
B32: Schliessung | D32: =-D31 -> 219368.6 | E32: =-E31 -> 151835.32 | F32: =-F31 -> 91474.18 | G32: =-G31 -> 45523.53 | H32: =-H31 -> -63583.046 | I32: =-I31 -> -71983.866 | J32: =-J31 -> -131600.91 | K32: =-K31 -> -185128.04 | ... O32: =-O31 -> 120070.21 | P32: =SUM(D32:I32) -> 372634.72 | Q32: =SUM(J32:O32) -> -39528.835
B33: Wiesensee | C33: =Wiesensee!C153 -> -1290897.5 | D33: =Wiesensee!D153 -> -281949.18 | E33: =Wiesensee!E153 -> -216854.64 | F33: =Wiesensee!F153 -> 37373.8 | G33: =Wiesensee!G153 -> -186943.22 | H33: =Wiesensee!H153 -> -77134.587 | I33: =Wiesensee!I153 -> -89014.294 | J33: =Wiesensee!J153 -> -101077.71 | ... O33: =Wiesensee!O153 -> -183791.85 | P33: =SUM(D33:I33) -> -814522.12 | Q33: =SUM(J33:O33) -> -476375.42 | R33: =P33+Q33-C33 -> 0
B34: Schliessung | D34: =-D33 -> 281949.18 | E34: =-E33 -> 216854.64 | F34: =-F33 -> -37373.8 | G34: =-G33 -> 186943.22 | H34: =-H33 -> 77134.587 | I34: =-I33 -> 89014.294 | J34: =-J33 -> 101077.71 | K34: =-K33 -> -4649.9859 | ... O34: =-O33 -> 183791.85 | P34: =SUM(D34:I34) -> 814522.12 | Q34: =SUM(J34:O34) -> 476375.42
B36: Adjusted EBITDA 25 | C36: =SUM(D36:O36) -> -13358.659 | D36: =D11+D16+D18+D20+D22+D30+D32+D34 -> -1226097 | E36: =E11+E16+E18+E20+E22+E30+E32+E34 -> -960675.74 | F36: =F11+F16+F18+F20+F22+F30+F32+F34 -> 917650.16 | G36: =G11+G16+G18+G20+G22+G30+G32+G34 -> -1012800.8 | H36: =H11+H16+H18+H20+H22+H30+H32+H34 -> 575093.87 | I36: =I11+I16+I18+I20+I22+I30+I32+I34 -> -220883.78 | J36: =J11+J16+J18+J20+J22+J30+J32+J34 -> -1119098.2 | K36: =K11+K16+K18+K20+K22+K30+K32+K34 -> -857945.34 | ... O36: =O11+O16+O18+O20+O22+O30+O32+O34 -> -202291.46 | P36: =SUM(D36:I36) -> -1927713.3 | Q36: =SUM(J36:O36) -> 1914354.7
A38: HQ | B38: EBITDA 25 budget | C38: =C12 -> -4193451.4 | D38: =D12 -> -468777.36 | E38: =E12 -> -1268229.6 | F38: =F12 -> -1457014 | G38: =G12 -> -483166.92 | H38: =H12 -> -24692.4 | I38: =I12 -> -722683.22 | J38: =J12 -> 405271.35 | ... O38: =O12 -> -458055.68 | P38: =SUM(D38:I38) -> -4424563.6 | Q38: =SUM(J38:O38) -> 231112.18
B39: Revenue Adj. Mgt. Fee | C39: =-(Oberstaufen!C159+Oberstaufen!C160+Oberstaufen!C158)-(Sylt!C158+Sylt!C159+Sylt!C160)-(Wiesensee!C158+Wiesensee!C159+Wiesensee!C160) -> -664601.57 | D39: =-(Oberstaufen!D159+Oberstaufen!D160+Oberstaufen!D158)-(Sylt!D158+Sylt!D159+Sylt!D160)-(Wiesensee!D158+Wiesensee!D159+Wiesensee!D160) -> -17048.92 | E39: =-(Oberstaufen!E159+Oberstaufen!E160+Oberstaufen!E158)-(Sylt!E158+Sylt!E159+Sylt!E160)-(Wiesensee!E158+Wiesensee!E159+Wiesensee!E160) -> -30913.83 | F39: =-(Oberstaufen!F159+Oberstaufen!F160+Oberstaufen!F158)-(Sylt!F158+Sylt!F159+Sylt!F160)-(Wiesensee!F158+Wiesensee!F159+Wiesensee!F160) -> -36758.11 | G39: =-(Oberstaufen!G159+Oberstaufen!G160+Oberstaufen!G158)-(Sylt!G158+Sylt!G159+Sylt!G160)-(Wiesensee!G158+Wiesensee!G159+Wiesensee!G160) -> -36922.53 | H39: =-(Oberstaufen!H159+Oberstaufen!H160+Oberstaufen!H158)-(Sylt!H158+Sylt!H159+Sylt!H160)-(Wiesensee!H158+Wiesensee!H159+Wiesensee!H160) -> -72040.67 | I39: =-(Oberstaufen!I159+Oberstaufen!I160+Oberstaufen!I158)-(Sylt!I158+Sylt!I159+Sylt!I160)-(Wiesensee!I158+Wiesensee!I159+Wiesensee!I160) -> -79571.455 | J39: =-(Oberstaufen!J159+Oberstaufen!J160+Oberstaufen!J158)-(Sylt!J158+Sylt!J159+Sylt!J160)-(Wiesensee!J158+Wiesensee!J159+Wiesensee!J160) -> -87430.923 | ... O39: =-(Oberstaufen!O159+Oberstaufen!O160+Oberstaufen!O158)-(Sylt!O158+Sylt!O159+Sylt!O160)-(Wiesensee!O158+Wiesensee!O159+Wiesensee!O160) -> -22097.912 | P39: =SUM(D39:I39) -> -273255.51 | Q39: =SUM(J39:O39) -> -391346.05
B40: Payroll | F40: =49800*1.2 -> 59760 | G40: =49800*1.2 -> 59760 | H40: =49800*1.2 -> 59760 | I40: =49800*1.2 -> 59760 | J40: =59800*1.2 -> 71760 | K40: =59800*1.2 -> 71760 | L40: =59800*1.2 -> 71760 | M40: =59800*1.2 -> 71760 | N40: =59800*1.2 -> 71760 | O40: =59800*1.2 -> 71760 | P40: =SUM(D40:I40) -> 239040 | Q40: =SUM(J40:O40) -> 430560 | R40: Technik
B41: Other Expenses | F41: 3000 | G41: 3000 | H41: 3000 | I41: 3000 | J41: 4000 | K41: 4000 | L41: 4000 | M41: 4000 | N41: =3000+1000 -> 4000 | O41: =3000+1000 -> 4000 | P41: =SUM(D41:I41) -> 12000 | Q41: =SUM(J41:O41) -> 24000 | R41: Technik
B42: Payroll | D42: 45000 | E42: 70000 | F42: =3000*1.2+70000 -> 73600 | G42: =3000*1.2+70000 -> 73600 | H42: =3000*1.2+70000 -> 73600 | I42: =3000*1.2+70000 -> 73600 | J42: =3000*1.2+70000 -> 73600 | K42: =3000*1.2+70000 -> 73600 | L42: =3000*1.2+70000 -> 73600 | M42: =3000*1.2+70000 -> 73600 | ... O42: =3000*1.2+70000 -> 73600 | P42: =SUM(D42:I42) -> 409400 | Q42: =SUM(J42:O42) -> 441600 | R42: Verwaltung
B43: Other Expenses | D43: =5000+8000 -> 13000 | E43: =8000+5000 -> 13000 | F43: =9400+8000+5000 -> 22400 | G43: =8000+5000 -> 13000 | H43: =8000+42000+5000 -> 55000 | I43: =9400+8000+5000 -> 22400 | J43: =8000+5000 -> 13000 | K43: =8000+5000 -> 13000 | L43: =8000+5000 -> 13000 | M43: =9400+8000+5000 -> 22400 | N43: =8000+5000 -> 13000 | O43: =9400+7500+8000+5000 -> 29900 | P43: =SUM(D43:I43) -> 138800 | Q43: =SUM(J43:O43) -> 104300 | R43: Verwaltung
B44: Payroll | D44: 10000 | E44: 10000 | F44: 10000 | G44: 10000 | H44: 10000 | I44: 10000 | J44: 10000 | K44: 10000 | L44: 10000 | M44: 10000 | N44: 10000 | O44: 10000 | P44: =SUM(D44:I44) -> 60000 | Q44: =SUM(J44:O44) -> 60000 | R44: AK
B45: Other Expenses | I45: 180000 | O45: 180000 | P45: =SUM(D45:I45) -> 180000 | Q45: =SUM(J45:O45) -> 180000 | R45: AK
B46: Payroll | F46: =15000*1.2 -> 18000 | G46: =15000*1.2 -> 18000 | H46: =15000*1.2 -> 18000 | I46: =15000*1.2 -> 18000 | J46: =15000*1.2 -> 18000 | K46: =15000*1.2 -> 18000 | L46: =15000*1.2 -> 18000 | M46: =15000*1.2 -> 18000 | ... O46: =15000*1.2 -> 18000 | P46: =SUM(D46:I46) -> 72000 | Q46: =SUM(J46:O46) -> 108000 | R46: C. Fitz
B47: Other Expenses | P47: =SUM(D47:I47) -> 0 | Q47: =SUM(J47:O47) -> 0
B48: Payroll | F48: =15000*1.1 -> 16500 | G48: =15000*1.1 -> 16500 | H48: =15000*1.1 -> 16500 | I48: =15000*1.1 -> 16500 | P48: =SUM(D48:I48) -> 66000 | Q48: =SUM(J48:O48) -> 0 | R48: GvH
B49: Other Expenses | P49: =SUM(D49:I49) -> 0 | Q49: =SUM(J49:O49) -> 0
B50: Other Expenses | D50: 10000 | E50: 10000 | F50: 10000 | G50: 10000 | H50: 10000 | I50: 10000 | J50: 10000 | K50: 10000 | L50: 10000 | M50: 10000 | N50: 10000 | O50: 10000 | P50: =SUM(D50:I50) -> 60000 | Q50: =SUM(J50:O50) -> 60000
B51: Payroll | F51: =10000*1.1+Oberstaufen!F159+Sylt!F159+Wiesensee!F159 -> 18715.89 | G51: =10000*1.1+Oberstaufen!G159+Sylt!G159+Wiesensee!G159 -> 19863 | H51: =10000*1.1+Oberstaufen!H159+Sylt!H159+Wiesensee!H159 -> 34601.335 | I51: =Oberstaufen!I159+Sylt!I159+Wiesensee!I159 -> 26057.407 | J51: =Oberstaufen!J159+Sylt!J159+Wiesensee!J159 -> 29183.118 | K51: =Oberstaufen!K159+Sylt!K159+Wiesensee!K159 -> 33828.089 | L51: =Oberstaufen!L159+Sylt!L159+Wiesensee!L159 -> 31507.413 | M51: =Oberstaufen!M159+Sylt!M159+Wiesensee!M159 -> 15613.841 | N51: =Oberstaufen!N159+Sylt!N159+Wiesensee!N159 -> 12105.811 | O51: =Oberstaufen!O159+Sylt!O159+Wiesensee!O159 -> 6810.6601 | P51: =SUM(D51:I51) -> 99237.631 | Q51: =SUM(J51:O51) -> 129048.93 | R51: 1 Rv, 1 Sales, 1 Marketing
B52: Other Expenses | P52: =SUM(D52:I52) -> 0 | Q52: =SUM(J52:O52) -> 0
B53: Payroll | I53: =4500*1.2 -> 5400 | J53: =4500*1.2 -> 5400 | K53: =4500*1.2 -> 5400 | L53: =4500*1.2 -> 5400 | M53: =4500*1.2 -> 5400 | N53: =4500*1.2 -> 5400 | O53: =4500*1.2 -> 5400 | P53: =SUM(D53:I53) -> 5400 | Q53: =SUM(J53:O53) -> 32400 | R53: Comercial
B54: Interest Crowd | D54: 16000 | E54: 16000 | F54: 16000 | G54: 16000 | H54: 16000 | I54: 16000 | J54: 16000 | K54: 16000 | L54: 16000 | M54: 16000 | N54: 16000 | O54: 16000 | P54: =SUM(D54:I54) -> 96000 | Q54: =SUM(J54:O54) -> 96000
B55: Rent HQ Reduction | F55: 8000 | G55: 8000 | H55: 8000 | I55: 8000 | J55: 8000 | K55: 8000 | L55: 8000 | M55: 8000 | N55: 8000 | O55: 8000 | P55: =SUM(D55:I55) -> 32000 | Q55: =SUM(J55:O55) -> 48000 | R55: 1 Etage aufgeben
B56: OL | D56: 53000 | E56: 53000 | F56: 53000 | G56: 53000 | H56: 53000 | I56: 53000 | J56: 53000 | K56: 53000 | L56: 53000 | M56: 53000 | N56: 53000 | O56: 53000 | P56: =SUM(D56:I56) -> 318000 | Q56: =SUM(J56:O56) -> 318000
B57: Nebenkosten LUG | D57: 10000 | E57: 10000 | F57: 10000 | G57: 10000 | H57: 10000 | I57: 10000 | J57: 10000 | K57: 10000 | L57: 10000 | M57: 10000 | N57: 10000 | O57: 10000 | P57: =SUM(D57:I57) -> 60000 | Q57: =SUM(J57:O57) -> 60000
B58: Adjusted EBITDA 25 | C58: =SUM(D58:O58) -> -918266.41 | D58: =D38+SUM(D39:D57) -> -328826.28 | E58: =E38+SUM(E39:E57) -> -1117143.5 | F58: =F38+SUM(F39:F57) -> -1174796.3 | G58: =G38+SUM(G39:G57) -> -209366.45 | H58: =H38+SUM(H39:H57) -> 270728.27 | I58: =I38+SUM(I39:I57) -> -290537.27 | J58: =J38+SUM(J39:J57) -> 639783.55 | K58: =K38+SUM(K39:K57) -> 561776.39 | ... O58: =O38+SUM(O39:O57) -> 16317.065 | P58: =SUM(D58:I58) -> -2849941.5 | Q58: =SUM(J58:O58) -> 1931675.1
A60: Risk adjustment Umsätze | B60: Flow through Hotels | C60: 0.65 | D60: =D6*$C$60 -> -519135.1 | E60: =E6*$C$60 -> -615361.74 | F60: =F6*$C$60 -> -835525.05 | G60: =G6*$C$60 -> -615590.04 | H60: =H6*$C$60 -> -846993.78 | I60: =I6*$C$60 -> -716944.3 | J60: =J6*$C$60 -> -208909.76 | K60: =K6*$C$60 -> -230939.19 | ... O60: =O6*$C$60 -> -220952.72 | P60: =SUM(D60:I60) -> -4149550 | Q60: =SUM(J60:O60) -> -1651181.3
B61: Flow through HQ | C61: 1 | D61: =D7*$C$61 -> -82892.167 | E61: =E7*$C$61 -> -79288.059 | F61: =F7*$C$61 -> -160587.44 | G61: =G7*$C$61 -> -91570.227 | H61: =H7*$C$61 -> -230615.83 | I61: =I7*$C$61 -> -151806.86 | J61: =J7*$C$61 -> -96237.897 | K61: =K7*$C$61 -> -97105.529 | ... O61: =O7*$C$61 -> -72746.714 | P61: =SUM(D61:I61) -> -796760.59 | Q61: =SUM(J61:O61) -> -497224.86
A63: Total 2025 | B63: EBITDA LH AG | D63: =D58+D36+D60+D61 -> -2156950.5 | E63: =E58+E36+E60+E61 -> -2772469 | F63: =F58+F36+F60+F61 -> -1253258.6 | G63: =G58+G36+G60+G61 -> -1929327.6 | H63: =H58+H36+H60+H61 -> -231787.48 | I63: =I58+I36+I60+I61 -> -1380172.2 | J63: =J58+J36+J60+J61 -> -784462.35 | K63: =K58+K36+K60+K61 -> -624213.67 | ... O63: =O58+O36+O60+O61 -> -479673.83 | P63: =SUM(D63:I63) -> -9723965.4 | Q63: =SUM(J63:O63) -> 1697623.5
A65: Portfolio Liquidity Adj. | B65: S&W | D65: =3100000-170000 -> 2930000 | E65: =3100000-170000 -> 2930000 | P65: =SUM(D65:O65) -> 5860000
B66: Rent | E66: =-(-'Budget 25 LH AG'!E136+E16+E18+E20+E22+Oberstaufen!E136+Sylt!E136+Wiesensee!E136) -> 1669433.5 | P66: =SUM(D66:O66) -> 1669433.5
A68: Adj. Liquidity | B68: Net Cash From Operations | D68: =D63+D65+D66 -> 773049.45 | E68: =E63+E65+E66 -> 1826964.5 | F68: =F63+F65+F66 -> -1253258.6 | G68: =G63+G65+G66 -> -1929327.6 | H68: =H63+H65+H66 -> -231787.48 | I68: =I63+I65+I66 -> -1380172.2 | J68: =J63+J65+J66 -> -784462.35 | K68: =K63+K65+K66 -> -624213.67 | ... O68: =O63+O65+O66 -> -479673.83 | P68: =SUM(D68:I68) -> -2194531.9 | Q68: =SUM(J68:O68) -> 1697623.5
B69: Net Cash Bank account | C69: 2500000 | D69: =C69+D68 -> 3273049.5 | E69: =D69+E68 -> 5100013.9 | F69: =E69+F68 -> 3846755.3 | G69: =F69+G68 -> 1917427.8 | H69: =G69+H68 -> 1685640.3 | I69: =H69+I68 -> 305468.09 | J69: =I69+J68 -> -478994.27 | K69: =J69+K68 -> -1103207.9 | ... O69: =N69+O68 -> 2003091.6
A71: Risk Adjustement | B71: Revenues Hotel | C71: =+'Hotels Only'!C11 -> 93365067 | D71: =+'Hotels Only'!D11 -> 5324462.5 | E71: =+'Hotels Only'!E11 -> 6311402.5 | F71: =+'Hotels Only'!F11 -> 8569487.7 | G71: =+'Hotels Only'!G11 -> 6313744 | H71: =+'Hotels Only'!H11 -> 8687115.7 | I71: =+'Hotels Only'!I11 -> 7353274.8 | J71: =+'Hotels Only'!J11 -> 6427992.7 | ... O71: =+'Hotels Only'!O11 -> 6798545.1
B72: Revenues HQ | D72: ='HQ only'!D11 -> 552614.45 | E72: ='HQ only'!E11 -> 528587.06 | F72: ='HQ only'!F11 -> 1070583 | G72: ='HQ only'!G11 -> 610468.18 | H72: ='HQ only'!H11 -> 1537438.9 | I72: ='HQ only'!I11 -> 1012045.7 | J72: ='HQ only'!J11 -> 1924757.9 | K72: ='HQ only'!K11 -> 1942110.6 | ... O72: ='HQ only'!O11 -> 1454934.3
D73: =+D71*$C$73*D60 -> 0 | E73: =+E71*$C$73*E60 -> 0 | F73: =+F71*$C$73*F60 -> 0 | G73: =+G71*$C$73*G60 -> 0 | H73: =+H71*$C$73*H60 -> 0 | I73: =+I71*$C$73*I60 -> 0 | J73: =+J71*$C$73*J60 -> 0 | K73: =+K71*$C$73*K60 -> 0 | ... O73: =+O71*$C$73*O60 -> 0
B74: Risk Adjusted Cash | C74: =+C83 -> 3442499.7 | D74: =C74+D68 -> 4215549.2 | E74: =D74+E68 -> 6042513.7 | F74: =E74+F68 -> 4789255.1 | G74: =F74+G68 -> 2859927.5 | H74: =G74+H68 -> 2628140 | I74: =H74+I68 -> 1247967.8 | J74: =I74+J68 -> 463505.46 | K74: =J74+K68 -> -160708.21 | ... O74: =N74+O68 -> 2945591.4 | P74: =P68+SUM(P60:P61) -> -7140842.5 | Q74: =Q68+SUM(Q60:Q61) -> -450782.65
A76: Revenues adjusted | D76: =SUM(D71:D72) -> 5877077 | E76: =SUM(E71:E72) -> 6839989.5 | F76: =SUM(F71:F72) -> 9640070.6 | G76: =SUM(G71:G72) -> 6924212.2 | H76: =SUM(H71:H72) -> 10224555 | I76: =SUM(I71:I72) -> 8365320.6 | J76: =SUM(J71:J72) -> 8352750.6 | K76: =SUM(K71:K72) -> 9047931.8 | ... O76: =SUM(O71:O72) -> 8253479.4
A77: EBITDA Adjusted | D77: =D63+D60+D61 -> -2758977.8 | E77: =E63+E60+E61 -> -3467118.8 | F77: =F63+F60+F61 -> -2249371.1 | G77: =G63+G60+G61 -> -2636487.8 | H77: =H63+H60+H61 -> -1309397.1 | I77: =I63+I60+I61 -> -2248923.4 | J77: =J63+J60+J61 -> -1089610 | K77: =K63+K60+K61 -> -952258.39 | ... O77: =O63+O60+O61 -> -773373.26
A78: Costs | D78: =D76-D77 -> 8636054.8 | E78: =E76-E77 -> 10307108 | F78: =F76-F77 -> 11889442 | G78: =G76-G77 -> 9560700.1 | H78: =H76-H77 -> 11533952 | I78: =I76-I77 -> 10614244 | J78: =J76-J77 -> 9442360.7 | K78: =K76-K77 -> 10000190 | ... O78: =O76-O77 -> 9026852.7
A79: Payroll | D79: -2930000 | E79: -2930000 | F79: -2930000 | G79: -2930000 | H79: -2930000 | I79: -2930000 | J79: -2930000 | K79: -2930000 | L79: -2930000 | M79: -2930000 | N79: -2930000 | O79: -2930000
A80: Rent | D80: =-'Budget 25 LH AG'!D136+D16+D18+D20+D22+Oberstaufen!D136+Sylt!D136+Wiesensee!D136 -> -1668587 | E80: =-'Budget 25 LH AG'!E136+E16+E18+E20+E22+Oberstaufen!E136+Sylt!E136+Wiesensee!E136 -> -1669433.5 | F80: =-'Budget 25 LH AG'!F136+F16+F18+F20+F22+Oberstaufen!F136+Sylt!F136+Wiesensee!F136 -> -1913683.2 | G80: =-'Budget 25 LH AG'!G136+G16+G18+G20+G22+Oberstaufen!G136+Sylt!G136+Wiesensee!G136 -> -1706675 | H80: =-'Budget 25 LH AG'!H136+H16+H18+H20+H22+Oberstaufen!H136+Sylt!H136+Wiesensee!H136 -> -1767450.7 | I80: =-'Budget 25 LH AG'!I136+I16+I18+I20+I22+Oberstaufen!I136+Sylt!I136+Wiesensee!I136 -> -1681402.1 | J80: =-'Budget 25 LH AG'!J136+J16+J18+J20+J22+Oberstaufen!J136+Sylt!J136+Wiesensee!J136 -> -1558279.2 | K80: =-'Budget 25 LH AG'!K136+K16+K18+K20+K22+Oberstaufen!K136+Sylt!K136+Wiesensee!K136 -> -1598507.6 | ... O80: =-'Budget 25 LH AG'!O136+O16+O18+O20+O22+Oberstaufen!O136+Sylt!O136+Wiesensee!O136 -> -1639394
A81: AP | D81: =SUM(D78:D80) -> 4037467.8 | E81: =SUM(E78:E80) -> 5707674.9 | F81: =SUM(F78:F80) -> 7045758.5 | G81: =SUM(G78:G80) -> 4924025.1 | H81: =SUM(H78:H80) -> 6836500.9 | I81: =SUM(I78:I80) -> 6002841.8 | J81: =SUM(J78:J80) -> 4954081.5 | K81: =SUM(K78:K80) -> 5471682.6 | ... O81: =SUM(O78:O80) -> 4457458.6
D82: =+D81/D76 -> 0.6869857 | E82: =+E81/E76 -> 0.83445667 | F82: =+F81/F76 -> 0.73088246 | G82: =+G81/G76 -> 0.71113145 | H82: =+H81/H76 -> 0.66863557 | I82: =+I81/I76 -> 0.71758659 | J82: =+J81/J76 -> 0.59310779 | K82: =+K81/K76 -> 0.60474402 | ... O82: =+O81/O76 -> 0.54007024
A83: Casflow Plan | B83: Effective Cash | C83: =Dezember24!AG50 -> 3442499.7 | D83: =Januar!AH50 -> 4095387.8 | E83: =Februar!AH50 -> 4710438.2 | F83: =März!AH50 -> 8081456.3 | G83: =April!AH50 -> 10995169 | H83: =Mai!AH50 -> 9104878.3 | I83: =Juni!AH50 -> 11225488 | J83: =I83+J63 -> 10441026 | K83: =J83+K63 -> 9816812.3 | L83: =K83+L63 -> 11103955 | M83: =L83+M63 -> 12848252 | N83: =M83+N63 -> 13402786 | O83: =N83+O63 -> 12923112 | P83: =+I83 -> 11225488 | Q83: =+O83 -> 12923112
D84: =+'Budget 25 LH AG'!D176 -> 4089864 | E84: =+'Budget 25 LH AG'!E176 -> 4537261.8 | F84: =+'Budget 25 LH AG'!F176 -> 5397098.9 | G84: =+'Budget 25 LH AG'!G176 -> 4511160 | H84: =+'Budget 25 LH AG'!H176 -> 4858036.6 | I84: =+'Budget 25 LH AG'!I176 -> 5120840.8
A85: Checks
A86: Revenues adjusted | D86: =+D71+D72 -> 5877077 | E86: =+E71+E72 -> 6839989.5 | F86: =+F71+F72 -> 9640070.6 | G86: =+G71+G72 -> 6924212.2 | H86: =+H71+H72 -> 10224555 | I86: =+I71+I72 -> 8365320.6
A87: EBITDA Adjusted | D87: =+D10 -> -2284871.9 | E87: =+E10 -> -1763626.9 | F87: =+F10 -> -132297.08 | G87: =+G10 -> -1139371.9 | H87: =+H10 -> 565331.26 | I87: =+I10 -> 130761.96
A88: Costs | D88: =D86-D87 -> 8161948.9 | E88: =E86-E87 -> 8603616.4 | F88: =F86-F87 -> 9772367.7 | G88: =G86-G87 -> 8063584.1 | H88: =H86-H87 -> 9659223.3 | I88: =I86-I87 -> 8234558.6
A89: Payroll | D89: =-D65 -> -2930000 | E89: =+D89 -> -2930000 | F89: =+E89 -> -2930000 | G89: =+F89 -> -2930000 | H89: =+G89 -> -2930000 | I89: =+H89 -> -2930000
A90: Rent | D90: =-'Budget 25 LH AG'!D136 -> -2093637.1 | E90: =-'Budget 25 LH AG'!E136 -> -2097315.5 | F90: =-'Budget 25 LH AG'!F136 -> -2288177.1 | G90: =-'Budget 25 LH AG'!G136 -> -2081749.5 | H90: =-'Budget 25 LH AG'!H136 -> -2184774.5 | I90: =-'Budget 25 LH AG'!I136 -> -2097658.8
A91: AP | D91: =SUM(D88:D90) -> 3138311.8 | E91: =SUM(E88:E90) -> 3576300.9 | F91: =SUM(F88:F90) -> 4554190.6 | G91: =SUM(G88:G90) -> 3051834.7 | H91: =SUM(H88:H90) -> 4544448.8 | I91: =SUM(I88:I90) -> 3206899.9
B92: Effekt Savings | D92: =+D91-D81 -> -899156.01 | E92: =+E91-E81 -> -2131374 | F92: =+F91-F81 -> -2491567.9 | G92: =+G91-G81 -> -1872190.4 | H92: =+H91-H81 -> -2292052.1 | I92: =+I91-I81 -> -2795942
D93: =+'Budget 25 LH AG'!D178 -> 445032.36 | E93: =+'Budget 25 LH AG'!E178 -> 475707.64 | F93: =+'Budget 25 LH AG'!F178 -> 453810.78 | G93: =+'Budget 25 LH AG'!G178 -> 558526.59 | H93: =+'Budget 25 LH AG'!H178 -> 606103.18 | I93: =+'Budget 25 LH AG'!I178 -> 681215.08
B94: MWST Umsatz | D94: =+(70%*7%+30%*19%)*D76 -> 622970.16 | E94: =+(70%*7%+30%*19%)*E76 -> 725038.89 | F94: =+(70%*7%+30%*19%)*F76 -> 1021847.5 | G94: =+(70%*7%+30%*19%)*G76 -> 733966.5 | H94: =+(70%*7%+30%*19%)*H76 -> 1083802.8 | I94: =+(70%*7%+30%*19%)*I76 -> 886723.98
B95: MWST Kosten | D95: =19%*D81 -> 767118.89 | E95: =19%*E81 -> 1084458.2 | F95: =19%*F81 -> 1338694.1 | G95: =19%*G81 -> 935564.77 | H95: =19%*H81 -> 1298935.2 | I95: =19%*I81 -> 1140540
B96: MWST Pacht | D96: =-D80*0.19 -> 317031.52 | E96: =-E80*0.19 -> 317192.36 | F96: =-F80*0.19 -> 363599.81 | G96: =-G80*0.19 -> 324268.25 | H96: =-H80*0.19 -> 335815.64 | I96: =-I80*0.19 -> 319466.39
B97: MWSt Erstattung | D97: =+D94-D95-D96 -> -461180.25 | E97: =+E94-E95-E96 -> -676611.7 | F97: =+F94-F95-F96 -> -680446.44 | G97: =+G94-G95-G96 -> -525866.52 | H97: =+H94-H95-H96 -> -550948.03 | I97: =+I94-I95-I96 -> -573282.37
A99: Massnahmen
A100: Für die Sanierung wurden die Maßnahmen, die im Rahmen der Liquiditätsplanung bereits beschrieben wurden, fortgeschrieben.
A102: - Die Liquiditätsplanung basiert auf den für 2025 detailliert erstellten Budgets auf Einzelbetriebsebene der Hotelbetriebe sowie der Hauptverwaltung.
A103: - Im Budgetprozess werden Umsätze der betriebe tagesgenau nach verschiedenen Buchungssegmenten (u.a. Geschäftskunden, Tagungen, OTAs) genau geplant in Abhängigkeit von Messen, Grossveranstaltungen, Konjunkturerwartung etc.
A104: - Darauf aufbauend werden die Kosten erfasst, die sich daraus ergeben (Reinigungskosten Zimmer, Personal, Kosten für Essen und Geränke, Energie, Marketing, Buchungsprovisionen, Instandhaltung, etc.)
A106: - Im Rahmen des Insolvenzprozesses wurden folgende zusätzliche Annahmen getroffen:
A107: * Neuverhandlungen von Mieten: für die Häuser Berlin Ku'damm, Düsseldorf Airport, Frankfurt Höchst, Frankfurt Main Plaza und Leverkusen wurden teils deutliche Mietabschläge bis 30% unterstellt.
A108: * Schließung von Betrieben: Die Betriebe Oberstaufen, Wiesensee und ggf. Sylt (bereits gekündigt) werden nicht weiter betrieben und ab Januar 2025 geschlossen.
A109: * Die Pachtverträge der Häuser Düsseldorf Seestern, Hamburg Michl, Köln Dom, Köln City Plaza, Me & all Mainz sollen grundsätzlich bestehen bleiben.
A110: * In der Hauptverwaltung wurden Aufwände sowohl auf Personalseite über bereits getroffene Maßnahmen hinaus (Vorstand, Development, Opertation, Marketing, Technik) und operative Kosten (Beratung, Sponsoring, Mietfläche) reduziert.
A111: * Budgetierte Zinszahlungen werden nicht anfallen.
A113: - Risiken aus Umsatzverlusten aufgrund des Verfahrens wurden mit einer Reduktion von 5% gegenüber dem Budget abgebildet, davon können bei den Hotelbetrieben 35% im laufenden Betrieb eingespart werden, in der Hauptverwaltung ist dies nicht möglich.

Sheet Exec Summary_Base Case
B2: Budget | C2: Total Year | D2: Jan | E2: Feb | F2: Mar | G2: Apr | H2: May | I2: Jun | J2: Jul | K2: Aug | L2: Sep | M2: Oct | N2: Nov | O2: Dec | P2: Subtotals First Half | Q2: Subtotals Second Half
A3: LH AG 2025 | B3: Revenues | C3: ='Budget 25 LH AG'!C11 -> 1.2198848e+08 | D3: ='Budget 25 LH AG'!D11 -> 7240087.4 | E3: ='Budget 25 LH AG'!E11 -> 8314846.3 | F3: ='Budget 25 LH AG'!F11 -> 11118561 | G3: ='Budget 25 LH AG'!G11 -> 8842420.1 | H3: ='Budget 25 LH AG'!H11 -> 11077677 | I3: ='Budget 25 LH AG'!I11 -> 10908122 | J3: ='Budget 25 LH AG'!J11 -> 9390566.3 | ... Q3: ='Budget 25 LH AG'!Q11 -> 64486763
B4: Hotels only | C4: ='Hotels Only'!C11 -> 93365067 | D4: ='Hotels Only'!D11 -> 5324462.5 | E4: ='Hotels Only'!E11 -> 6311402.5 | F4: ='Hotels Only'!F11 -> 8569487.7 | G4: ='Hotels Only'!G11 -> 6313744 | H4: ='Hotels Only'!H11 -> 8687115.7 | I4: ='Hotels Only'!I11 -> 7353274.8 | J4: ='Hotels Only'!J11 -> 6427992.7 | ... O4: ='Hotels Only'!O11 -> 6798545.1 | P4: =SUM(D4:I4) -> 42559487 | Q4: =SUM(E4:J4) -> 43663017
B5: HV | C5: ='HQ only'!C11 -> 15256234 | D5: ='HQ only'!D11 -> 552614.45 | E5: ='HQ only'!E11 -> 528587.06 | F5: ='HQ only'!F11 -> 1070583 | G5: ='HQ only'!G11 -> 610468.18 | H5: ='HQ only'!H11 -> 1537438.9 | I5: ='HQ only'!I11 -> 1012045.7 | J5: ='HQ only'!J11 -> 1924757.9 | ... O5: ='HQ only'!O11 -> 1454934.3 | P5: =SUM(D5:I5) -> 5311737.3 | Q5: =SUM(E5:J5) -> 6683880.8
A22: EBITDA Budgeted 2025 | B22: EBITDA LH AG | C22: =SUM(D22:O22) -> -9766378 | D22: -2284871.9 | E22: ='data entry LH AG'!I153 -> -2983068.5 | F22: ='data entry LH AG'!L153 -> -978505.11 | G22: ='data entry LH AG'!O147 -> -2095343.9 | H22: ='data entry LH AG'!R153 -> 222722.22 | I22: ='data entry LH AG'!U153 -> -1286840.4 | J22: ='data entry LH AG'!X153 -> -967883.43 | K22: ='data entry LH AG'!AA153 -> -575363.37 | L22: ='data entry LH AG'!AD153 -> 1395768.2 | M22: ='data entry LH AG'!AG153 -> 1257777.5 | N22: ='data entry LH AG'!AJ153 -> -14973.808 | O22: ='data entry LH AG'!AM153 -> -1455795.4 | P22: =SUM(D22:I22) -> -9405907.6 | Q22: =SUM(J22:O22) -> -360470.36
B23: EBITDA Hotels | C23: ='Hotels Only'!C153 -> -5924419.9 | D23: ='Hotels Only'!D153 -> -2118525.1 | E23: ='Hotels Only'!E153 -> -1714838.9 | F23: ='Hotels Only'!F153 -> 478508.93 | G23: ='Hotels Only'!G153 -> -1661239.7 | H23: ='Hotels Only'!H153 -> 247414.62 | I23: ='Hotels Only'!I153 -> -564157.2 | J23: ='Hotels Only'!J153 -> -1373154.8 | ... O23: ='Hotels Only'!O153 -> -997739.73 | P23: =SUM(D23:I23) -> -5332837.4 | Q23: =SUM(J23:O23) -> -591582.55
B24: EBITDA HQ | C24: ='HQ only'!C153 -> -4193451.4 | D24: ='HQ only'!D153 -> -468777.36 | E24: ='HQ only'!E153 -> -1268229.6 | F24: ='HQ only'!F153 -> -1457014 | G24: ='HQ only'!G153 -> -483166.92 | H24: ='HQ only'!H153 -> -24692.4 | I24: ='HQ only'!I153 -> -722683.22 | J24: ='HQ only'!J153 -> 405271.35 | ... O24: ='HQ only'!O153 -> -458055.68 | P24: =SUM(D24:I24) -> -4424563.6 | Q24: =SUM(J24:O24) -> 231112.18
A26: Hotels | B26: EBITDA 25 | C26: =C23 -> -5924419.9 | D26: =D23 -> -2118525.1 | E26: =E23 -> -1714838.9 | F26: =F23 -> 478508.93 | G26: =G23 -> -1661239.7 | H26: =H23 -> 247414.62 | I26: =I23 -> -564157.2 | J26: =J23 -> -1373154.8 | ... O26: =O23 -> -997739.73 | P26: =SUM(D26:I26) -> -5332837.4 | Q26: =SUM(J26:O26) -> -591582.55
B27: Kudamm | C27: =SUM(D27:O27) -> -1045476.7 | D27: -221766 | E27: -93835 | F27: -90858 | G27: =Kudamm!G153 -> -183430.87 | H27: =Kudamm!H153 -> -59454.73 | I27: =Kudamm!I153 -> -47923.902 | J27: =Kudamm!J153 -> -106849.36 | K27: =Kudamm!K153 -> -77288.151 | L27: =Kudamm!L153 -> 61397.206 | M27: =Kudamm!M153 -> -21469.673 | N27: =Kudamm!N153 -> -100952.25 | O27: =Kudamm!O153 -> -103045.97 | P27: =SUM(D27:I27) -> -697268.5 | Q27: =SUM(J27:O27) -> -348208.2 | R27: =P27+Q27-C27 -> 0
B28: Rent 89,8k | D28: 115755 | E28: =+D28 -> 115755 | F28: =198825.6-89790 -> 109035.6 | G28: =198825.6-89790 -> 109035.6 | H28: =198825.6-89790 -> 109035.6 | I28: =198825.6-89790 -> 109035.6 | J28: =198825.6-89790 -> 109035.6 | K28: =198825.6-89790 -> 109035.6 | L28: =198825.6-89790 -> 109035.6 | M28: =198825.6-89790 -> 109035.6 | ... O28: =198825.6-89790 -> 109035.6 | P28: =SUM(D28:I28) -> 667652.4 | Q28: =SUM(J28:O28) -> 654213.6 | R28: NT10: Pacht 89,790 netto zzgl NK
B29: DUS Airport | C29: =Airport!C153 -> -858544 | D29: =Airport!D153 -> -145619.14 | E29: =Airport!E153 -> -145124.77 | F29: =Airport!F153 -> -8064.78 | G29: =Airport!G153 -> -241808.88 | H29: =Airport!H153 -> -92663.149 | I29: =Airport!I153 -> -150106.31 | J29: =Airport!J153 -> -213821.6 | ... O29: =Airport!O153 -> -84419.19 | P29: =SUM(D29:I29) -> -783387.02 | Q29: =SUM(J29:O29) -> -75156.977 | R29: =P29+Q29-C29 -> 0
B30: Rent 20k | D30: 190110 | E30: =+D30 -> 190110 | F30: =-F29+Airport!F176 -> 179220.24 | G30: =-G29+Airport!G176 -> 179220.24 | H30: =-H29+Airport!H176 -> 164534.58 | I30: =-I29+Airport!I176 -> 144534.58 | J30: =-J29+Airport!J176 -> 144534.58 | K30: =-K29+Airport!K176 -> 144534.58 | L30: =-L29+Airport!L176 -> 144534.58 | M30: =-M29+Airport!N174 -> -115964.45 | N30: =-N29 -> -148840.48 | O30: =-O29 -> 84419.19 | P30: =SUM(D30:I30) -> 1047729.6 | Q30: =SUM(J30:O30) -> 253218 | R30: Endet am 30.09 (statt 31.12.), 20k Pacht ab 07.25, Ergebnisteilung 60/40 bzw 80/20, Abrechnung am Ende Pachtvertrag getrennt nach Perioden
B31: Höchst | C31: =Höchst!C153 -> -1205030.1 | D31: =Höchst!D153 -> -212155.9 | E31: =Höchst!E153 -> -120714.41 | F31: =Höchst!F153 -> 10949.47 | G31: =Höchst!G153 -> -263290.92 | H31: =Höchst!H153 -> -51561.218 | I31: =Höchst!I153 -> -45336.009 | J31: =Höchst!J153 -> -213719.66 | ... O31: =Höchst!O153 -> -225681.53 | P31: =SUM(D31:I31) -> -682108.99 | Q31: =SUM(J31:O31) -> -522921.09 | R31: =P31+Q31-C31 -> 0
B32: Rent 150k | D32: 295521 | E32: =+D32 -> 295521 | F32: =+Höchst!F137-150000 -> 101565.44 | G32: =+Höchst!G137-150000 -> 101565.44 | H32: =+Höchst!H137-150000 -> 106565.44 | I32: =+Höchst!I137-150000 -> 106565.44 | J32: =+Höchst!J137-150000 -> 106565.44 | K32: =+Höchst!K137-150000 -> 106565.44 | L32: =+Höchst!L137-150000 -> 106565.44 | M32: =-M31 -> -72164.392 | N32: =-N31 -> 21737.418 | O32: =-O31 -> 225681.53 | P32: =SUM(D32:I32) -> 1007303.8 | Q32: =SUM(J32:O32) -> 494950.88 | R32: Exit 30.09., bis dahin 150k Pacht, keine Ergebnispacht (ab 07.25)
B33: Main Plaza | C33: ='Main Plaza'!C153 -> -1499349.8 | D33: ='Main Plaza'!D153 -> -274552.14 | E33: ='Main Plaza'!E153 -> -166853.12 | F33: ='Main Plaza'!F153 -> -76400.01 | G33: ='Main Plaza'!G153 -> -272562.79 | H33: ='Main Plaza'!H153 -> -145846.09 | I33: ='Main Plaza'!I153 -> -98949.768 | J33: ='Main Plaza'!J153 -> -162913.04 | ... O33: ='Main Plaza'!O153 -> -109066.93 | P33: =SUM(D33:I33) -> -1035163.9 | Q33: =SUM(J33:O33) -> -464185.87 | R33: =P33+Q33-C33 -> 0
B34: Rent 45k, EBITDA Teilung | D34: 101083 | E34: =+D34 -> 101083 | F34: =-F33 -> 76400.01 | G34: =-G33 -> 272562.79 | H34: =-H33 -> 145846.09 | I34: =-I33 -> 98949.768 | J34: =172622-45000-(J33+172622-45000)*75% -> 154090.28 | K34: =172622-45000-(K33+172622-45000)*75% -> 138856.8 | L34: =172622-45000-(L33+172622-45000)*75% -> 80894.584 | M34: =-M33 -> -34585.985 | N34: =-N33 -> 18871.376 | O34: =-O33 -> 109066.93 | P34: =SUM(D34:I34) -> 795924.66 | Q34: =SUM(J34:O34) -> 467193.99 | R34: Pacht EUR 45k, EBITDA bis 30.06. an Verpächter, danach 75% an Verpächter, maximale Fees 5,5%, exit 30.09.
B35: Leverkusen | C35: =Leverkusen!C153 -> 561711.5 | D35: =Leverkusen!D153 -> 11652.16 | E35: =Leverkusen!E153 -> -16003.8 | F35: =Leverkusen!F153 -> 69980.79 | G35: =Leverkusen!G153 -> -65092.08 | H35: =Leverkusen!H153 -> 55107.465 | I35: =Leverkusen!I153 -> 47326.389 | J35: =Leverkusen!J153 -> -70594.638 | ... O35: =Leverkusen!O153 -> 45519.038 | P35: =SUM(D35:I35) -> 102970.92 | Q35: =SUM(J35:O35) -> 458740.57
B36: Rent 88k | F36: =+Leverkusen!F137-88000 -> 0 | G36: =+Leverkusen!G137-88000 -> 0 | H36: =+Leverkusen!H137-88000 -> 702.88 | I36: =+Leverkusen!I137-88000 -> 702.88 | J36: =+Leverkusen!J137-88000 -> 702.88 | K36: =+Leverkusen!K137-88000 -> 702.88 | L36: =+Leverkusen!L137-88000 -> 702.88 | M36: =+Leverkusen!M137-88000 -> 702.88 | ... O36: =+Leverkusen!O137-88000 -> 702.88 | R36: nachverhandelt, Indexierung 2025 nicht geplant
B37: Seestern | C37: =Seestern!C153 -> 587850.38 | D37: =Seestern!D153 -> -10504.74 | E37: =Seestern!E153 -> -203276.93 | F37: =Seestern!F153 -> 200126.03 | G37: =Seestern!G153 -> -52909.46 | H37: =Seestern!H153 -> 103015.5 | I37: =Seestern!I153 -> -15091.582 | J37: =Seestern!J153 -> -124845.78 | ... O37: =Seestern!O153 -> -24492.333 | P37: =SUM(D37:I37) -> 21358.82 | Q37: =SUM(J37:O37) -> 566491.56 | R37: =P37+Q37-C37 -> 0
B38: Michel | C38: =Michel!C153 -> 1498105.8 | D38: =Michel!D153 -> -164842.28 | E38: =Michel!E153 -> -196350.38 | F38: =Michel!F153 -> 89456.43 | G38: =Michel!G153 -> 100022.62 | H38: =Michel!H153 -> 384065.31 | I38: =Michel!I153 -> 256507.41 | J38: =Michel!J153 -> 101063.78 | ... O38: =Michel!O153 -> 101583.61 | P38: =SUM(D38:I38) -> 468859.11 | Q38: =SUM(J38:O38) -> 1029246.7 | R38: =P38+Q38-C38 -> 0 | X38: Gehalt + SV
B39: Köln Dom | C39: ='Köln Dom'!C153 -> 120286.13 | D39: ='Köln Dom'!D153 -> -126132.15 | E39: ='Köln Dom'!E153 -> -38758.06 | F39: ='Köln Dom'!F153 -> 79067.62 | G39: ='Köln Dom'!G153 -> 18302.69 | H39: ='Köln Dom'!H153 -> 21909.56 | I39: ='Köln Dom'!I153 -> -6044.1391 | J39: ='Köln Dom'!J153 -> -28080.17 | ... O39: ='Köln Dom'!O153 -> 12496.867 | P39: =SUM(D39:I39) -> -51654.479 | Q39: =SUM(J39:O39) -> 171940.61 | R39: PIP | W39: CS | X39: =+(26-18) -> 8 | Z39: reduziert
B40: City Plaza | C40: ='City Plza'!C153 -> 281020.43 | D40: ='City Plza'!D153 -> -208942.58 | E40: ='City Plza'!E153 -> -147468.01 | F40: ='City Plza'!F153 -> 263639.94 | G40: ='City Plza'!G153 -> -11798.61 | H40: ='City Plza'!H153 -> 32594.665 | I40: ='City Plza'!I153 -> -34034.18 | J40: ='City Plza'!J153 -> -156251.91 | ... O40: ='City Plza'!O153 -> 37185.206 | P40: =SUM(D40:I40) -> -106008.77 | Q40: =SUM(J40:O40) -> 387029.2 | R40: PIP | W40: FL, | X40: =+Z40-Y40 -> 33.6 | Y40: =13+9*0.2 -> 14.8 | Z40: 48.4 | AA40: reduziert | AC40: Simon 31.03.2025
B41: MAA Mainz | C41: ='MAA Mainz'!C153 -> 445680.01 | D41: ='MAA Mainz'!D153 -> -77260.27 | E41: ='MAA Mainz'!E153 -> -34059.46 | F41: ='MAA Mainz'!F153 -> 174602.72 | G41: ='MAA Mainz'!G153 -> -211350.75 | H41: ='MAA Mainz'!H153 -> 28420.521 | I41: ='MAA Mainz'!I153 -> 99978.832 | J41: ='MAA Mainz'!J153 -> 66832.498 | ... O41: ='MAA Mainz'!O153 -> -7567.6414 | P41: =SUM(D41:I41) -> -19668.407 | Q41: =SUM(J41:O41) -> 465348.42 | R41: =P41+Q41-C41 -> 0 | W41: Schroers, | X41: 12 | AC41: Tülay 31.03.2025
B42: Oberstaufen | C42: =Oberstaufen!C153 -> -1484990 | D42: =Oberstaufen!D153 -> -181371.5 | E42: =Oberstaufen!E153 -> -175734.32 | F42: =Oberstaufen!F153 -> -175302 | G42: =Oberstaufen!G153 -> -206233.27 | H42: =Oberstaufen!H153 -> -104388.86 | I42: =Oberstaufen!I153 -> -116504.15 | J42: =Oberstaufen!J153 -> -27307.282 | ... O42: =Oberstaufen!O153 -> -234313.74 | P42: =SUM(D42:I42) -> -959534.1 | Q42: =SUM(J42:O42) -> -525455.86 | R42: =P42+Q42-C42 -> 0 | W42: AJ | X42: 13 | AC42: Angelika Schroers 31.03.2025
B43: Schliessung | D43: =-D42 -> 181371.5 | E43: =-E42 -> 175734.32 | F43: =-F42 -> 175302 | G43: =-G42 -> 206233.27 | H43: =-H42 -> 104388.86 | I43: =-I42 -> 116504.15 | J43: =-J42 -> 27307.282 | K43: =-K42 -> -13587.221 | ... O43: =-O42 -> 234313.74 | P43: =SUM(D43:I43) -> 959534.1 | Q43: =SUM(J43:O43) -> 525455.86 | R43: Pächter gleicht Verluste aus, exit 30.06. | W43: Tülay | X43: 5.2 | AC43: Janutschek 31.03.2025
B44: Sylt | C44: =Sylt!C153 -> -333105.88 | D44: =Sylt!D153 -> -219368.6 | E44: =Sylt!E153 -> -151835.32 | F44: =Sylt!F153 -> -91474.18 | G44: =Sylt!G153 -> -45523.53 | H44: =Sylt!H153 -> 63583.046 | I44: =Sylt!I153 -> 71983.866 | J44: =Sylt!J153 -> 131600.91 | ... O44: =Sylt!O153 -> -120070.21 | P44: =SUM(D44:I44) -> -372634.72 | Q44: =SUM(J44:O44) -> 39528.835 | R44: Endet am 30.09, 50k Pacht | W44: Simon | X44: 5.9
B45: Schliessung | D45: =-D44 -> 219368.6 | E45: =-E44 -> 151835.32 | F45: =-F44 -> 91474.18 | G45: =-G44 -> 45523.53 | M45: =-M44 -> 168044.87 | N45: =-N44 -> 129757.63 | O45: =-O44 -> 120070.21 | P45: =SUM(D45:I45) -> 508201.63 | Q45: =SUM(J45:O45) -> 417872.72 | R45: 50k in FC enthalten | W45: Fabri | Y45: 6.8 | Z45: bleibt | AC45: Sophie 30.06. reduziertes Gehalt – in progress
B46: Wiesensee | C46: =Wiesensee!C153 -> -1290897.5 | D46: =Wiesensee!D153 -> -281949.18 | E46: =Wiesensee!E153 -> -216854.64 | F46: =Wiesensee!F153 -> 37373.8 | G46: =Wiesensee!G153 -> -186943.22 | H46: =Wiesensee!H153 -> -77134.587 | I46: =Wiesensee!I153 -> -89014.294 | J46: =Wiesensee!J153 -> -101077.71 | ... O46: =Wiesensee!O153 -> -183791.85 | P46: =SUM(D46:I46) -> -814522.12 | Q46: =SUM(J46:O46) -> -476375.42 | R46: =P46+Q46-C46 -> 0 | AC46: Holger 31.05.
B47: Schliessung | D47: =-D46 -> 281949.18 | E47: =-E46 -> 216854.64 | F47: =-F46 -> -37373.8 | G47: =-G46 -> 186943.22 | H47: =-H46 -> 77134.587 | I47: =-I46 -> 89014.294 | J47: =-J46 -> 101077.71 | K47: =-K46 -> -4649.9859 | ... O47: =-O46 -> 183791.85 | P47: =SUM(D47:I47) -> 814522.12 | Q47: =SUM(J47:O47) -> 476375.42 | R47: Pächter gleicht Verluste aus, exit 30.06. | W47: Scheffler | X47: 12 | AC47: Evert - in progress
W48: Mainka | X48: 5.5
B49: Adjusted EBITDA 25 | C49: =SUM(D49:O49) -> 3171351.9 | D49: =D23+D28+D30+D32+D34+D36+D43+D45+D47 -> -733366.85 | E49: =E23+E28+E30+E32+E34+E36+E43+E45+E47 -> -467945.59 | F49: =F23+F28+F30+F32+F34+F36+F43+F45+F47 -> 1174132.6 | G49: =G23+G28+G30+G32+G34+G36+G43+G45+G47 -> -560155.62 | H49: =H23+H28+H30+H32+H34+H36+H43+H45+H47 -> 955622.66 | I49: =I23+I28+I30+I32+I34+I36+I43+I45+I47 -> 101149.51 | J49: =J23+J28+J30+J32+J34+J36+J43+J45+J47 -> -729841.01 | K49: =K23+K28+K30+K32+K34+K36+K43+K45+K47 -> -430394.46 | ... O49: =O23+O28+O30+O32+O34+O36+O43+O45+O47 -> 69342.208 | P49: =SUM(D49:I49) -> 469436.71 | Q49: =SUM(J49:O49) -> 2701915.2
W50: C. Fritz | X50: 17
A51: HQ | B51: EBITDA 25 | C51: =C24 -> -4193451.4 | D51: =D24 -> -468777.36 | E51: =E24 -> -1268229.6 | F51: =F24 -> -1457014 | G51: =G24 -> -483166.92 | H51: =H24 -> -24692.4 | I51: =I24 -> -722683.22 | J51: =J24 -> 405271.35 | ... O51: =O24 -> -458055.68 | P51: =SUM(D51:I51) -> -4424563.6 | Q51: =SUM(J51:O51) -> 231112.18 | W51: Achim | Y51: bleibt
B52: Revenue Adj. Mgt. Fee | C52: =-(Oberstaufen!C159+Oberstaufen!C160+Oberstaufen!C158)-(Sylt!C158+Sylt!C159+Sylt!C160)-(Wiesensee!C158+Wiesensee!C159+Wiesensee!C160) -> -664601.57 | D52: =-(Oberstaufen!D159+Oberstaufen!D160+Oberstaufen!D158)-(Sylt!D158+Sylt!D159+Sylt!D160)-(Wiesensee!D158+Wiesensee!D159+Wiesensee!D160) -> -17048.92 | E52: =-(Oberstaufen!E159+Oberstaufen!E160+Oberstaufen!E158)-(Sylt!E158+Sylt!E159+Sylt!E160)-(Wiesensee!E158+Wiesensee!E159+Wiesensee!E160) -> -30913.83 | F52: =-(Oberstaufen!F159+Oberstaufen!F160+Oberstaufen!F158)-(Sylt!F158+Sylt!F159+Sylt!F160)-(Wiesensee!F158+Wiesensee!F159+Wiesensee!F160) -> -36758.11 | G52: =-(Oberstaufen!G159+Oberstaufen!G160+Oberstaufen!G158)-(Sylt!G158+Sylt!G159+Sylt!G160)-(Wiesensee!G158+Wiesensee!G159+Wiesensee!G160) -> -36922.53 | H52: =-(Oberstaufen!H159+Oberstaufen!H160+Oberstaufen!H158)-(Sylt!H158+Sylt!H159+Sylt!H160)-(Wiesensee!H158+Wiesensee!H159+Wiesensee!H160) -> -72040.67 | I52: =-(Oberstaufen!I159+Oberstaufen!I160+Oberstaufen!I158)-(Sylt!I158+Sylt!I159+Sylt!I160)-(Wiesensee!I158+Wiesensee!I159+Wiesensee!I160) -> -79571.455 | J52: =-(Oberstaufen!J159+Oberstaufen!J160+Oberstaufen!J158)-(Sylt!J158+Sylt!J159+Sylt!J160)-(Wiesensee!J158+Wiesensee!J159+Wiesensee!J160) -> -87430.923 | ... O52: =-(Oberstaufen!O159+Oberstaufen!O160+Oberstaufen!O158)-(Sylt!O158+Sylt!O159+Sylt!O160)-(Wiesensee!O158+Wiesensee!O159+Wiesensee!O160) -> -22097.912 | P52: =SUM(D52:I52) -> -273255.51 | Q52: =SUM(J52:O52) -> -391346.05 | R52: Puffer, da Fees weiter gezahlt werden (bis 09.25) | S52: Adjustment revenue Fees
B53: Payroll | G53: =+SUM(X40:X44)*1000 -> 69700 | H53: =+G53 -> 69700 | I53: =+H53 -> 69700 | J53: =+I53 -> 69700 | K53: =+J53 -> 69700 | L53: =+K53 -> 69700 | M53: =+L53 -> 69700 | N53: =+M53 -> 69700 | O53: =+N53 -> 69700 | P53: =SUM(D53:I53) -> 209100 | Q53: =SUM(J53:O53) -> 418200 | R53: Technik | S53: Schroers, AJ, Tülay, Simon | W53: Gabriele | X53: ersetzt Bardia | Z53: 15.3
B54: Other Expenses | F54: 3000 | G54: 3000 | H54: 3000 | I54: 3000 | J54: 4000 | K54: 4000 | L54: 4000 | M54: 4000 | N54: =3000+1000 -> 4000 | O54: =3000+1000 -> 4000 | P54: =SUM(D54:I54) -> 12000 | Q54: =SUM(J54:O54) -> 24000 | R54: Technik | X54: Holger wird COO | Z54: =200/12+9*0.2 -> 18.466667
B55: Payroll | D55: 45000 | E55: 70000 | F55: =3000*1.2+95000+8000 -> 106600 | G55: =3000*1.2+95000+8000 -> 106600 | H55: =3000*1.2+95000+8000 -> 106600 | I55: =3000*1.2+95000+8000 -> 106600 | J55: =3000*1.2+95000+8000 -> 106600 | K55: =3000*1.2+95000+8000 -> 106600 | L55: =3000*1.2+95000+8000 -> 106600 | M55: =3000*1.2+95000+8000 -> 106600 | ... O55: =3000*1.2+95000+8000 -> 106600 | P55: =SUM(D55:I55) -> 541400 | Q55: =SUM(J55:O55) -> 639600 | R55: Verwaltung | W55: Evert | X55: 17
B56: Other Expenses | D56: =5000+8000 -> 13000 | E56: =8000+5000 -> 13000 | F56: =9400+8000+5000 -> 22400 | G56: =8000+5000 -> 13000 | H56: =8000+42000+5000 -> 55000 | I56: =9400+8000+5000 -> 22400 | J56: =8000+5000 -> 13000 | K56: =8000+5000 -> 13000 | L56: =8000+5000 -> 13000 | M56: =9400+8000+5000 -> 22400 | N56: =8000+5000 -> 13000 | O56: =9400+7500+8000+5000 -> 29900 | P56: =SUM(D56:I56) -> 138800 | Q56: =SUM(J56:O56) -> 104300 | R56: Verwaltung | W56: Sophie | X56: 17
B57: Payroll | D57: 10000 | E57: 10000 | F57: 10000 | G57: 10000 | H57: 10000 | I57: 10000 | J57: 10000 | K57: 10000 | L57: 10000 | M57: 10000 | N57: 10000 | O57: 10000 | P57: =SUM(D57:I57) -> 60000 | Q57: =SUM(J57:O57) -> 60000 | R57: AK | W57: Marketing | X57: wie geplant
B58: Other Expenses | I58: 180000 | O58: 180000 | P58: =SUM(D58:I58) -> 180000 | Q58: =SUM(J58:O58) -> 180000 | R58: AK | W58: Sales | X58: anpassen
B59: Payroll | I59: =+Z54*1000 -> 18466.667 | J59: =+I59 -> 18466.667 | K59: =+J59 -> 18466.667 | L59: =+K59 -> 18466.667 | M59: =+L59 -> 18466.667 | N59: =+M59 -> 18466.667 | O59: =+N59 -> 18466.667 | P59: =SUM(D59:I59) -> 18466.667 | Q59: =SUM(J59:O59) -> 110800 | R59: Holger ab Juni | W59: Rev Mgmt | X59: Ralf | Y59: =120/12+9*0.2 -> 11.8
B60: Other Expenses | P60: =SUM(D60:I60) -> 0 | Q60: =SUM(J60:O60) -> 0
B61: Payroll | F61: =15000*1.1 -> 16500 | G61: =15000*1.1 -> 16500 | H61: =15000*1.1 -> 16500 | I61: =15000*1.1 -> 16500 | P61: =SUM(D61:I61) -> 66000 | Q61: =SUM(J61:O61) -> 0 | R61: GvH | W61: S. Doerre | X61: =70/12*1.2 -> 7
B62: Other Expenses | P62: =SUM(D62:I62) -> 0 | Q62: =SUM(J62:O62) -> 0 | U62: iberia | W62: Claudia | X62: =66/12*1.2 -> 6.6
B63: Other Expenses | D63: 10000 | E63: 10000 | F63: 10000 | G63: 10000 | H63: 10000 | I63: 10000 | J63: 10000 | K63: 10000 | L63: 10000 | M63: 10000 | N63: 10000 | O63: 10000 | P63: =SUM(D63:I63) -> 60000 | Q63: =SUM(J63:O63) -> 60000 | R63: Finance
B64: Payroll | G64: =+Y59*1000 -> 11800 | H64: =+G64 -> 11800 | I64: =+H64 -> 11800 | J64: =+I64 -> 11800 | K64: =+J64 -> 11800 | L64: =+K64 -> 11800 | M64: =+L64 -> 11800 | N64: =+M64 -> 11800 | O64: =+N64 -> 11800 | P64: =SUM(D64:I64) -> 35400 | Q64: =SUM(J64:O64) -> 70800 | R64: 1 Rv
B65: Other Expenses | P65: =SUM(D65:I65) -> 0 | Q65: =SUM(J65:O65) -> 0
B66: Payroll | I66: =4500*1.2 -> 5400 | J66: =4500*1.2 -> 5400 | K66: =4500*1.2 -> 5400 | L66: =4500*1.2 -> 5400 | M66: =4500*1.2 -> 5400 | N66: =4500*1.2 -> 5400 | O66: =4500*1.2 -> 5400 | P66: =SUM(D66:I66) -> 5400 | Q66: =SUM(J66:O66) -> 32400 | R66: Comercial
B67: Interest Crowd | D67: 16000 | E67: 16000 | F67: 16000 | G67: 16000 | H67: 16000 | I67: 16000 | J67: 16000 | K67: 16000 | L67: 16000 | M67: 16000 | N67: 16000 | O67: 16000 | P67: =SUM(D67:I67) -> 96000 | Q67: =SUM(J67:O67) -> 96000
B68: Rent HQ Reduction | H68: 8000 | I68: 8000 | J68: 8000 | K68: 8000 | L68: 8000 | M68: 8000 | N68: 8000 | O68: 8000 | P68: =SUM(D68:I68) -> 16000 | Q68: =SUM(J68:O68) -> 48000 | R68: 1 Etage aufgeben
B69: OL | D69: 53000 | E69: 53000 | F69: 53000 | G69: 53000 | H69: 53000 | I69: 53000 | J69: 53000 | K69: 53000 | L69: 53000 | M69: 53000 | N69: 53000 | O69: 53000 | P69: =SUM(D69:I69) -> 318000 | Q69: =SUM(J69:O69) -> 318000
B70: Nebenkosten LUG | D70: 10000 | E70: 10000 | F70: 10000 | G70: 10000 | H70: 10000 | I70: 10000 | J70: 10000 | K70: 10000 | L70: 10000 | M70: 10000 | N70: 10000 | O70: 10000 | P70: =SUM(D70:I70) -> 60000 | Q70: =SUM(J70:O70) -> 60000
B71: Adjusted EBITDA 25 | C71: =SUM(D71:O71) -> -819386.31 | D71: =D51+SUM(D52:D70) -> -328826.28 | E71: =E51+SUM(E52:E70) -> -1117143.5 | F71: =F51+SUM(F52:F70) -> -1246272.1 | G71: =G51+SUM(G52:G70) -> -200489.45 | H71: =H51+SUM(H52:H70) -> 272866.93 | I71: =I51+SUM(I52:I70) -> -261388.01 | J71: =J51+SUM(J52:J70) -> 653807.1 | K71: =K51+SUM(K52:K70) -> 571154.96 | ... O71: =O51+SUM(O52:O70) -> 52713.072 | P71: =SUM(D71:I71) -> -2881252.4 | Q71: =SUM(J71:O71) -> 2061866.1
A73: Total 2025 | B73: EBITDA LH AG | C73: =C49+C71 -> 2351965.6 | D73: =D71+D49 -> -1062193.1 | E73: =E71+E49 -> -1585089.1 | F73: =F71+F49 -> -72139.55 | G73: =G71+G49 -> -760645.07 | H73: =H71+H49 -> 1228489.6 | I73: =I71+I49 -> -160238.5 | J73: =J71+J49 -> -76033.917 | K73: =K71+K49 -> 140760.5 | ... O73: =O71+O49 -> 122055.28 | P73: =P49+P71 -> -2411815.7 | Q73: =Q49+Q71 -> 4763781.3
A75: Portfolio Liquidity Adj. | B75: S&W | D75: =3100000-170000 -> 2930000 | E75: =3100000-170000 -> 2930000 | P75: =SUM(D75:O75) -> 5860000
B76: Rent | E76: =-(-'Budget 25 LH AG'!E136+E28+E30+E32+E34+Oberstaufen!E136+Sylt!E136+Wiesensee!E136) -> 1176703.3 | P76: =SUM(D76:O76) -> 1176703.3
A78: Adj. Liquidity | B78: Net Cash From Operations | D78: =D73+D75+D76 -> 1867806.9 | E78: =E73+E75+E76 -> 2521614.3 | F78: =F73+F75+F76 -> -72139.55 | G78: =G73+G75+G76 -> -760645.07 | H78: =H73+H75+H76 -> 1228489.6 | I78: =I73+I75+I76 -> -160238.5 | J78: =J73+J75+J76 -> -76033.917 | K78: =K73+K75+K76 -> 140760.5 | ... O78: =O73+O75+O76 -> 122055.28 | P78: =SUM(D78:I78) -> 4624887.6 | Q78: =SUM(J78:O78) -> 4763781.3
B79: Net Cash Bank account | C79: =+Dezember24!R4 -> 3000000 | D79: =C79+D78 -> 4867806.9 | E79: =D79+E78 -> 7389421.1 | F79: =E79+F78 -> 7317281.6 | G79: =F79+G78 -> 6556636.5 | H79: =G79+H78 -> 7785126.1 | I79: =H79+I78 -> 7624887.6 | J79: =I79+J78 -> 7548853.7 | K79: =J79+K78 -> 7689614.2 | ... O79: =N79+O78 -> 12388669
A80: Rev BUD | D80: 6345075.5 | E80: 7367537.3 | F80: 9809968 | G80: 7689161.1 | H80: 9519256.8 | I80: 9058508.7 | J80: 7449197.6 | K80: 8290181.6 | L80: 10977786 | M80: 10811665 | N80: 9621684 | O80: 7304734 | P80: =SUM(D80:I80) -> 49789507 | Q80: =SUM(J80:O80) -> 54455249
A81: ADJ. (15%) | D81: -951761.33 | E81: -1105130.6 | F81: -1471495.2 | G81: -1153374.2 | H81: -1427888.5 | I81: -1358776.3 | J81: -372459.88 | K81: =-K80*$R$89 -> -829018.16 | L81: =-L80*$R$89 -> -1097778.6 | M81: =-M80*$R$89 -> -1081166.5 | N81: =-N80*$R$89 -> -962168.4 | O81: =-O80*$R$89 -> -730473.4 | P81: =SUM(D81:I81) -> -7468426.1 | Q81: =SUM(J81:O81) -> -5073065
A82: Net Adj. Risk Rev | D82: =SUM(D80:D81) -> 5393314.2 | E82: =SUM(E80:E81) -> 6262406.7 | F82: =SUM(F80:F81) -> 8338472.8 | G82: =SUM(G80:G81) -> 6535786.9 | H82: =SUM(H80:H81) -> 8091368.3 | I82: =SUM(I80:I81) -> 7699732.4 | J82: =SUM(J80:J81) -> 7076737.8 | K82: =SUM(K80:K81) -> 7461163.4 | ... O82: =SUM(O80:O81) -> 6574260.6 | P82: =SUM(D82:I82) -> 42321081 | Q82: =SUM(J82:O82) -> 49382184
A83: Rev HQ BUD | D83: 895011.81 | E83: 947309 | F83: 1308592.6 | G83: 1153259 | H83: 1558420.4 | I83: 1849613.3 | J83: 1941368.7 | K83: 1959969.7 | L83: 1919889.5 | M83: 1575560 | N83: 1173034.7 | O83: 1461691.1 | P83: =SUM(D83:I83) -> 7712206 | Q83: =SUM(J83:O83) -> 10031514
D86: =+D87/D80 -> 0.8391488 | E86: =+E87/E80 -> 0.85665022 | F86: =+F87/F80 -> 0.87354899 | G86: =+G87/G80 -> 0.82112261 | H86: =+H87/H80 -> 0.91258339 | I86: =+I87/I80 -> 0.81175335 | J86: =+J87/J80 -> 0.86291075 | K86: =+K87/K80 -> 0.85713698 | ... O86: =+O87/O80 -> 0.930704
A87: Risk Adjustement | B87: Revenues Hotel | C87: =+'Hotels Only'!C11 -> 93365067 | D87: =+'Hotels Only'!D11 -> 5324462.5 | E87: =+'Hotels Only'!E11 -> 6311402.5 | F87: =+'Hotels Only'!F11 -> 8569487.7 | G87: =+'Hotels Only'!G11 -> 6313744 | H87: =+'Hotels Only'!H11 -> 8687115.7 | I87: =+'Hotels Only'!I11 -> 7353274.8 | J87: =+'Hotels Only'!J11 -> 6427992.7 | ... O87: =+'Hotels Only'!O11 -> 6798545.1 | P87: =SUM(D87:I87) -> 42559487 | Q87: =SUM(J87:O87) -> 50805580
B88: Revenues HQ | D88: ='HQ only'!D11 -> 552614.45 | E88: ='HQ only'!E11 -> 528587.06 | F88: ='HQ only'!F11 -> 1070583 | G88: ='HQ only'!G11 -> 610468.18 | H88: ='HQ only'!H11 -> 1537438.9 | I88: ='HQ only'!I11 -> 1012045.7 | J88: ='HQ only'!J11 -> 1924757.9 | K88: ='HQ only'!K11 -> 1942110.6 | ... O88: ='HQ only'!O11 -> 1454934.3 | P88: =SUM(D88:I88) -> 5311737.3 | Q88: =SUM(J88:O88) -> 9944497.1
B89: Risk Adjustment Hotels | C89: 0.15 | L89: =L80-L87+L81 -> -669857.72 | M89: =M80-M87+M81 -> -701680.08 | N89: =N80-N87+N81 -> -831660.66 | O89: =O80-O87+O81 -> -224284.53 | P89: =SUM(D89:I89) -> 0 | Q89: =SUM(J89:O89) -> -2427483 | R89: 0.1
B90: Risk Adjustment HQ | C90: 0.15 | J90: =-J88*$R$90 -> -192475.79 | K90: =-K88*$R$90 -> -194211.06 | L90: =-L88*$R$90 -> -190091.62 | M90: =-M88*$R$90 -> -156101.11 | N90: =-N88*$R$90 -> -116076.7 | O90: =-O88*$R$90 -> -145493.43 | P90: =SUM(D90:I90) -> 0 | Q90: =SUM(J90:O90) -> -994449.71 | R90: 0.1
B91: Net Risk Adj. Hotels | D91: =D87+D89 -> 5324462.5 | E91: =E87+E89 -> 6311402.5 | F91: =F87+F89 -> 8569487.7 | G91: =G87+G89 -> 6313744 | H91: =H87+H89 -> 8687115.7 | I91: =I87+I89 -> 7353274.8 | J91: =J87+J89 -> 6427992.7 | K91: =K87+K89 -> 7105821.2 | ... O91: =O87+O89 -> 6574260.6 | P91: =SUM(D91:I91) -> 42559487 | Q91: =SUM(J91:O91) -> 48378097
B92: Var. Plan ORG | D92: =D91-D82 -> -68851.687 | E92: =E91-E82 -> 48995.739 | F92: =F91-F82 -> 231014.87 | G92: =G91-G82 -> -222042.87 | H92: =H91-H82 -> 595747.39 | I92: =I91-I82 -> -346457.58
B93: Flow through Hotels | C93: 0.65 | D93: =D89*$C$93 -> 0 | E93: =E89*$C$93 -> 0 | F93: =F89*$C$93 -> 0 | G93: =G89*$C$93 -> 0 | H93: =H89*$C$93 -> 0 | I93: =I89*$C$93 -> 0 | J93: =J89*$C$93 -> 0 | K93: =K89*$C$93 -> 0 | ... O93: =O89*$C$93 -> -145784.95 | P93: =SUM(D93:I93) -> 0 | Q93: =SUM(J93:O93) -> -1577863.9
B94: Flow through HQ | C94: 1 | D94: =D90*$C$94 -> 0 | E94: =E90*$C$94 -> 0 | F94: =F90*$C$94 -> 0 | G94: =G90*$C$94 -> 0 | H94: =H90*$C$94 -> 0 | I94: =I90*$C$94 -> 0 | J94: =J90*$C$94 -> -192475.79 | K94: =K90*$C$94 -> -194211.06 | ... O94: =O90*$C$94 -> -145493.43 | P94: =SUM(D94:I94) -> 0 | Q94: =SUM(J94:O94) -> -994449.71
D95: =+D87*$C$95*D93 -> 0 | E95: =+E87*$C$95*E93 -> 0 | F95: =+F87*$C$95*F93 -> 0 | G95: =+G87*$C$95*G93 -> 0 | H95: =+H87*$C$95*H93 -> 0 | I95: =+I87*$C$95*I93 -> 0 | J95: =+J87*$C$95*J93 -> 0 | K95: =+K87*$C$95*K93 -> 0 | ... O95: =+O87*$C$95*O93 -> 0
B96: Risk Adjusted Cash | C96: =+C105 -> 3442499.7 | D96: =Januar!AG50 -> 4095387.8 | E96: =+Februar!AH50 -> 4710438.2 | F96: =+März!AH50 -> 8081456.3 | G96: =+April!AH50 -> 10995169 | H96: =+Mai!AH50 -> 9104878.3 | I96: =+Juni!AH50 -> 11225488 | J96: =I96+J78+SUM(J93:J94) -> 10956979 | K96: =J96+K78+SUM(K93:K94) -> 10903528 | L96: =K96+L78+SUM(L93:L94) -> 12339921 | M96: =L96+M78+SUM(M93:M94) -> 13546465 | N96: =M96+N78+SUM(N93:N94) -> 13586179 | O96: =N96+O78+SUM(O93:O94) -> 13416956 | P96: =P78+SUM(P93:P94) -> 4624887.6 | Q96: =Q78+SUM(Q93:Q94) -> 2191467.7
A97: ISOverwalter | E97: -1500000 | L97: -2400000
A98: Revenues adjusted | D98: =SUM(D87:D90) -> 5877077 | E98: =SUM(E87:E90) -> 6839989.5 | F98: =SUM(F87:F90) -> 9640070.6 | G98: =SUM(G87:G90) -> 6924212.2 | H98: =SUM(H87:H90) -> 10224555 | I98: =SUM(I87:I90) -> 8365320.6 | J98: =SUM(J87:J90) -> 8160274.9 | K98: =SUM(K87:K90) -> 8853720.8 | ... O98: =SUM(O87:O90) -> 7883701.4
A99: EBITDA Adjusted | D99: =D73+D93+D94 -> -1062193.1 | E99: =E73+E93+E94 -> -1585089.1 | F99: =F73+F93+F94 -> -72139.55 | G99: =G73+G93+G94 -> -760645.07 | H99: =H73+H93+H94 -> 1228489.6 | I99: =I73+I93+I94 -> -160238.5 | J99: =J73+J93+J94 -> -268509.71 | K99: =K73+K93+K94 -> -53450.555 | ... O99: =O73+O93+O94 -> -169223.1
A100: Costs | D100: =D98-D99 -> 6939270.1 | E100: =E98-E99 -> 8425078.6 | F100: =F98-F99 -> 9712210.2 | G100: =G98-G99 -> 7684857.3 | H100: =H98-H99 -> 8996065 | I100: =I98-I99 -> 8525559.1 | J100: =J98-J99 -> 8428784.6 | K100: =K98-K99 -> 8907171.3 | ... O100: =O98-O99 -> 8052924.5
A101: Payroll | D101: -2930000 | E101: -2930000 | F101: -2930000 | G101: -2930000 | H101: -2930000 | I101: -2930000 | J101: -2930000 | K101: -2930000 | L101: -2930000 | M101: -2930000 | N101: -2930000 | O101: -2930000
A102: Rent | D102: =-'Budget 25 LH AG'!D136+D28+D30+D32+D34+Oberstaufen!D136+Sylt!D136+Wiesensee!D136 -> -1175856.8 | E102: =-'Budget 25 LH AG'!E136+E28+E30+E32+E34+Oberstaufen!E136+Sylt!E136+Wiesensee!E136 -> -1176703.3 | F102: =-'Budget 25 LH AG'!F136+F28+F30+F32+F34+Oberstaufen!F136+Sylt!F136+Wiesensee!F136 -> -1657200.7 | G102: =-'Budget 25 LH AG'!G136+G28+G30+G32+G34+Oberstaufen!G136+Sylt!G136+Wiesensee!G136 -> -1254029.8 | H102: =-'Budget 25 LH AG'!H136+H28+H30+H32+H34+Oberstaufen!H136+Sylt!H136+Wiesensee!H136 -> -1451207.9 | I102: =-'Budget 25 LH AG'!I136+I28+I30+I32+I34+Oberstaufen!I136+Sylt!I136+Wiesensee!I136 -> -1432055.5 | J102: =-'Budget 25 LH AG'!J136+J28+J30+J32+J34+Oberstaufen!J136+Sylt!J136+Wiesensee!J136 -> -1301325.7 | K102: =-'Budget 25 LH AG'!K136+K28+K30+K32+K34+Oberstaufen!K136+Sylt!K136+Wiesensee!K136 -> -1356787.6 | ... O102: =-'Budget 25 LH AG'!O136+O28+O30+O32+O34+Oberstaufen!O136+Sylt!O136+Wiesensee!O136 -> -1368463.3
A103: AP | D103: =SUM(D100:D102) -> 2833413.3 | E103: =SUM(E100:E102) -> 4318375.3 | F103: =SUM(F100:F102) -> 5125009.4 | G103: =SUM(G100:G102) -> 3500827.5 | H103: =SUM(H100:H102) -> 4614857.1 | I103: =SUM(I100:I102) -> 4163503.5 | J103: =SUM(J100:J102) -> 4197458.8 | K103: =SUM(K100:K102) -> 4620383.7 | ... O103: =SUM(O100:O102) -> 3754461.3
D104: =+D103/D98 -> 0.48211267 | E104: =+E103/E98 -> 0.63134238 | F104: =+F103/F98 -> 0.53163609 | G104: =+G103/G98 -> 0.50559218 | H104: =+H103/H98 -> 0.45135043 | I104: =+I103/I98 -> 0.49770998 | J104: =+J103/J98 -> 0.51437714 | K104: =+K103/K98 -> 0.52185785 | ... O104: =+O103/O98 -> 0.47623078
A105: Casflow Plan | B105: Effective Cash | C105: =Dezember24!AG50 -> 3442499.7 | D105: =Januar!AH50 -> 4095387.8 | E105: =Februar!AH50 -> 4710438.2 | F105: =März!AH50 -> 8081456.3 | G105: =April!AH50 -> 10995169 | H105: =Mai!AH50 -> 9104878.3 | I105: =Juni!AH50 -> 11225488 | J105: =Juli!AH50 -> 8492524.3 | K105: =August!AH50 -> 5940023.1 | L105: =September!AH50 -> 4468895.1
B106: Last Plan (14.03.) | D106: 4095387.8 | E106: 4737443.6 | F106: 4506287.6 | G106: 3871694.7 | H106: 4206911 | I106: 1467728.3
D107: =+'Budget 25 LH AG'!D176 -> 4089864 | E107: =+'Budget 25 LH AG'!E176 -> 4537261.8 | F107: =+'Budget 25 LH AG'!F176 -> 5397098.9 | G107: =+'Budget 25 LH AG'!G176 -> 4511160 | H107: =+'Budget 25 LH AG'!H176 -> 4858036.6 | I107: =+'Budget 25 LH AG'!I176 -> 5120840.8
A109: Checks
A110: Revenues adjusted | D110: =+D87+D88 -> 5877077 | E110: =+E87+E88 -> 6839989.5 | F110: =+F87+F88 -> 9640070.6 | G110: =+G87+G88 -> 6924212.2 | H110: =+H87+H88 -> 10224555 | I110: =+I87+I88 -> 8365320.6
A111: EBITDA Adjusted | D111: =+D22 -> -2284871.9 | E111: =+E22 -> -2983068.5 | F111: =+F22 -> -978505.11 | G111: =+G22 -> -2095343.9 | H111: =+H22 -> 222722.22 | I111: =+I22 -> -1286840.4
A112: Costs | D112: =D110-D111 -> 8161948.9 | E112: =E110-E111 -> 9823058 | F112: =F110-F111 -> 10618576 | G112: =G110-G111 -> 9019556.1 | H112: =H110-H111 -> 10001832 | I112: =I110-I111 -> 9652161
A113: Payroll | D113: =-D75 -> -2930000 | E113: =+D113 -> -2930000 | F113: =+E113 -> -2930000 | G113: =+F113 -> -2930000 | H113: =+G113 -> -2930000 | I113: =+H113 -> -2930000
A114: Rent | D114: =-'Budget 25 LH AG'!D136 -> -2093637.1 | E114: =-'Budget 25 LH AG'!E136 -> -2097315.5 | F114: =-'Budget 25 LH AG'!F136 -> -2288177.1 | G114: =-'Budget 25 LH AG'!G136 -> -2081749.5 | H114: =-'Budget 25 LH AG'!H136 -> -2184774.5 | I114: =-'Budget 25 LH AG'!I136 -> -2097658.8
A115: AP | D115: =SUM(D112:D114) -> 3138311.8 | E115: =SUM(E112:E114) -> 4795742.5 | F115: =SUM(F112:F114) -> 5400398.7 | G115: =SUM(G112:G114) -> 4007806.6 | H115: =SUM(H112:H114) -> 4887057.9 | I115: =SUM(I112:I114) -> 4624502.2
B116: Effekt Savings | D116: =+D115-D103 -> 304898.52 | E116: =+E115-E103 -> 477367.27 | F116: =+F115-F103 -> 275389.24 | G116: =+G115-G103 -> 506979.1 | H116: =+H115-H103 -> 272200.79 | I116: =+I115-I103 -> 460998.7
D117: =+'Budget 25 LH AG'!D178 -> 445032.36 | E117: =+'Budget 25 LH AG'!E178 -> 475707.64 | F117: =+'Budget 25 LH AG'!F178 -> 453810.78 | G117: =+'Budget 25 LH AG'!G178 -> 558526.59 | H117: =+'Budget 25 LH AG'!H178 -> 606103.18 | I117: =+'Budget 25 LH AG'!I178 -> 681215.08
B118: MWST Umsatz | D118: =+(70%*7%+30%*19%)*D98 -> 622970.16 | E118: =+(70%*7%+30%*19%)*E98 -> 725038.89 | F118: =+(70%*7%+30%*19%)*F98 -> 1021847.5 | G118: =+(70%*7%+30%*19%)*G98 -> 733966.5 | H118: =+(70%*7%+30%*19%)*H98 -> 1083802.8 | I118: =+(70%*7%+30%*19%)*I98 -> 886723.98
B119: MWST Kosten | D119: =19%*D103 -> 538348.53 | E119: =19%*E103 -> 820491.3 | F119: =19%*F103 -> 973751.79 | G119: =19%*G103 -> 665157.23 | H119: =19%*H103 -> 876822.85 | I119: =19%*I103 -> 791065.67
B120: MWST Pacht | D120: =-D102*0.19 -> 223412.79 | E120: =-E102*0.19 -> 223573.63 | F120: =-F102*0.19 -> 314868.14 | G120: =-G102*0.19 -> 238265.65 | H120: =-H102*0.19 -> 275729.5 | I120: =-I102*0.19 -> 272090.55
B121: MWSt Erstattung | D121: =+D118-D119-D120 -> -138791.16 | E121: =+E118-E119-E120 -> -319026.04 | F121: =+F118-F119-F120 -> -266772.45 | G121: =+G118-G119-G120 -> -169456.39 | H121: =+H118-H119-H120 -> -68749.562 | I121: =+I118-I119-I120 -> -176432.24
J123: Control

Sheet Dezember24
A1: Januar | B1: 22
B2: Monatswerte | C2: 45627 | D2: 45628 | E2: 45629 | F2: 45630 | G2: 45631 | H2: 45632 | I2: 45633 | J2: 45634 | K2: 45635 | L2: 45636 | M2: 45637 | N2: 45638 | O2: 45639 | P2: 45640 | Q2: 45641 | R2: 45642 | S2: 45643 | T2: 45644 | U2: 45645 | V2: 45646 | W2: 45647 | X2: 45648 | Y2: 45649 | Z2: 45650 | AA2: 45651 | AB2: 45652 | AC2: 45653 | AD2: 45654 | AE2: 45655 | AF2: 45656 | AG2: 45657 | AH2: Monatswerte | AJ2: F.Plan | AK2: Var. | AL2: Kommentierung
A3: geplant/IST | C3: 1. | D3: 2. | E3: 3. | F3: 4. | G3: 5. | H3: 6. | I3: 7. | J3: 8. | K3: 9. | L3: 10. | M3: 11. | N3: 12. | O3: 13. | P3: 14. | Q3: 15. | R3: 16. | S3: 17. | T3: 18. | U3: 19. | V3: 20. | W3: 21. | X3: 22. | Y3: 23. | Z3: 24. | AA3: 25. | AB3: 26. | AC3: 27. | AD3: 28. | AE3: 29. | AF3: 30. | AG3: 31. | AH3: gesamt
A4: Valuta | B4: 0 | C4: =B4 -> 0 | D4: =+C50 -> 0 | E4: =+D50 -> 0 | F4: =+E50 -> 0 | G4: =+F50 -> 0 | H4: =+G50 -> 0 | I4: =+H50 -> 0 | J4: =+I50 -> 0 | K4: =+J50 -> 0 | ... Q4: =+P50 -> 0 | R4: 3000000 | S4: =+R50 -> 3000000 | T4: =+S50 -> 3000000 | U4: =+T50 -> 3000000 | V4: =+U50 -> 3000000 | W4: =+V50 -> 3000000 | X4: =+W50 -> 3000000 | Y4: =+X50 -> 3000000 | Z4: =+Y50 -> 3413609.9 | ... AG4: =+AF50 -> 3442499.7 | AH4: =+B4 -> 0 | AJ4: 0
A5: Tagesgeld | B5: 0 | C5: 0 | D5: 0 | E5: 0 | F5: 0 | G5: 0 | H5: 0 | I5: 0 | J5: 0 | K5: 0 | L5: 0 | M5: 0 | N5: 0 | O5: 0 | P5: 0 | Q5: 0 | R5: 0 | S5: 0 | T5: 0 | U5: 0 | V5: 0 | W5: 0 | X5: 0 | Y5: 0 | Z5: 0 | AA5: 0 | AB5: 0 | AC5: 0 | AD5: 0 | AE5: 0 | AF5: 0 | AG5: 0 | AH5: =+B5 -> 0 | AJ5: 0
A6: Summe | B6: =+B4+B5 -> 0 | C6: =+C4+C5 -> 0 | D6: =+D4+D5 -> 0 | E6: =+E4+E5 -> 0 | F6: =+F4+F5 -> 0 | G6: =+G4+G5 -> 0 | H6: =+H4+H5 -> 0 | I6: =+I4+I5 -> 0 | ... AG6: =+AG4+AG5 -> 3442499.7 | AH6: =AH5+AH4 -> 0 | AJ6: 0
A7: AUSGABEN | AH7: =SUM(R7:AG7) -> 0 | AJ7: 0
A8: Pacht | B8: =SUM(C8:AG8) -> 0 | AH8: =SUM(R8:AG8) -> 0 | AJ8: 0
A9: Annuität ext. | B9: =SUM(C9:AG9) -> 0 | AH9: =SUM(R9:AG9) -> 0 | AJ9: 0
A10: Kreditorenzahlungen | B10: =SUM(C10:AG10) -> 65390 | Y10: 61990 | AF10: 3400 | AH10: =SUM(R10:AG10) -> 65390 | AJ10: 1250000 | AK10: =AH10-AJ10 -> -1184610 | AL10: Zahlungen konnten noch nicht durchgeführt werden
A11: Aktivbank/Progros | AH11: =SUM(R11:AG11) -> 0 | AJ11: 0
A12: Lastschriften | B12: =SUM(C12:AG12) -> 0 | C12: =SUM(C13:C22) -> 0 | D12: =SUM(D13:D22) -> 0 | E12: =SUM(E13:E22) -> 0 | F12: =SUM(F13:F22) -> 0 | G12: =SUM(G13:G22) -> 0 | H12: =SUM(H13:H22) -> 0 | I12: =SUM(I13:I22) -> 0 | J12: =SUM(J13:J22) -> 0 | ... AG12: =SUM(AG13:AG22) -> 0 | AH12: =SUM(R12:AG12) -> 0 | AJ12: 0
A13: Energiedienstleister | AH13: =SUM(C13:AG13) -> 0 | AJ13: 0
A14: Telekommunikation | AH14: =SUM(C14:AG14) -> 0 | AJ14: 0
A15: Gebühren CC | AH15: =SUM(C15:AG15) -> 0 | AJ15: 0
A16: Provisonen( Booking, Expedia | AH16: =SUM(C16:AG16) -> 0 | AJ16: 0
A17: KFZ Leasing | AH17: =SUM(C17:AG17) -> 0 | AJ17: 0
A18: Jobtickets | AH18: =SUM(C18:AG18) -> 0 | AJ18: 0
A19: Leasing | AH19: =SUM(C19:AG19) -> 0 | AJ19: 0
A20: Gema/GEZ/Sky | AH20: =SUM(C20:AG20) -> 0 | AJ20: 0
A21: Sonepar/Haustechnik | AH21: =SUM(C21:AG21) -> 0 | AJ21: 0
A22: Airplus | AH22: =SUM(C22:AG22) -> 0 | AJ22: 0
A23: BGN/Schwerbeh.abgabe | B23: =SUM(C23:AG23) -> 0 | AH23: =SUM(R23:AG23) -> 0 | AJ23: 0
A24: interne Zahlungen | B24: =SUM(C24:AG24) -> 0 | AH24: =SUM(C24:AG24) -> 0 | AJ24: 0
A25: City Taxes | AH25: =SUM(R25:AG25) -> 0 | AJ25: 0
A26: L&G | B26: =SUM(C26:AG26) -> 0 | AH26: =SUM(R26:AG26) -> 0 | AJ26: 170000 | AK26: =AH26-AJ26 -> -170000 | AL26: Über Beitragsbemessungsgrenze nicht im Dez bezahlt sondern Jan
A27: Krankenkasse | B27: =SUM(C27:AG27) -> 0 | AH27: =SUM(R27:AG27) -> 0 | AJ27: 0
A28: Lohnsteuer | B28: =SUM(C28:AG28) -> 0 | AH28: =SUM(R28:AG28) -> 0 | AJ28: 0
A29: UST | B29: =SUM(C29:AG29) -> 0 | AH29: =SUM(R29:AG29) -> 0 | AJ29: 0
A30: Berater-/ Verfahrenskosten Insolvenzverfahren | B30: =SUM(C30:AG30) -> 0 | AH30: =SUM(R30:AG30) -> 0 | AJ30: 0
A31: div. Abbuchungen | B31: =SUM(C31:AG31) -> 0 | AH31: =SUM(R31:AG31) -> 0 | AJ31: 0
A32: Summe Ausgaben | B32: =SUM(B8:B31) -> 65390 | C32: =SUM(C8:C31)-C12 -> 0 | D32: =SUM(D8:D31)-D12 -> 0 | E32: =SUM(E8:E31)-E12 -> 0 | F32: =SUM(F8:F31)-F12 -> 0 | G32: =SUM(G8:G31)-G12 -> 0 | H32: =SUM(H8:H31)-H12 -> 0 | I32: =SUM(I8:I31)-I12 -> 0 | J32: =SUM(J8:J31)-J12 -> 0 | ... AG32: =SUM(AG8:AG31)-AG12 -> 0 | AH32: =SUM(R32:AG32) -> 65390 | AJ32: 1420000 | AK32: =AH32-AJ32 -> -1354610
AH33: =SUM(R33:AG33) -> 0 | AJ33: 0
A34: EINNAHMEN | AH34: =SUM(R34:AG34) -> 0 | AJ34: 0
A35: Vorauszahlungen | B35: =SUM(C35:AG35) -> 0 | AH35: =SUM(C35:AG35) -> 0 | AJ35: 0
A36: Bareinzahlungen | B36: =SUM(C36:AG36) -> 0 | D36: 0 | E36: 0 | K36: 0 | L36: 0 | R36: 0 | S36: 0 | Y36: 0 | Z36: 0 | AA36: 0 | AB36: 0 | AF36: 0 | AG36: 0 | AH36: =SUM(C36:AG36) -> 0 | AJ36: 0
A37: Umbuchungen S-Zentral | B37: =SUM(C37:AG37) -> 0 | AH37: =SUM(C37:AG37) -> 0 | AJ37: 0
A38: interne Zahlungen | B38: =SUM(C38:AG38) -> 0 | AH38: =SUM(C38:AG38) -> 0 | AJ38: 0 | AM38: =+AK42-AK38 -> -2673579
A39: Besonderheiten | B39: =SUM(C39:AG39) -> 0 | AH39: =SUM(R39:AG39) -> 0 | AJ39: 0 | AO39: 16
A40: Kreditkarten | B40: =SUM(C40:AG40) -> 475599.89 | Y40: =25405.89+56689.28+32317.84+104131.66+82155.19+56422.07+23947.44+27960+52621.65+8236.65+5712.22 -> 475599.89 | AH40: =SUM(R40:AG40) -> 475599.89 | AJ40: 967750 | AK40: =AH40-AJ40 -> -492150.11 | AL40: 400k werden im Januar bezahlt
A41: Debitoren | B41: =SUM(C41:AG41) -> 32289.84 | AF41: =30000+1942.35+347.49 -> 32289.84 | AH41: =SUM(R41:AG41) -> 32289.84 | AJ41: 2213718.8 | AK41: =AH41-AJ41 -> -2181428.9 | AL41: 1500k werden im Januar bezahlt | AM41: Umsätze brutto | AN41: =3500000*70%*1.07+3500000*30%*1.19 -> 3871000 | AO41: =+AN41/$AO$39 -> 241937.5
A42: Summe Einnahmen | B42: =SUM(B40:B41) -> 507889.73 | C42: =SUM(C35:C41) -> 0 | D42: =SUM(D35:D41) -> 0 | E42: =SUM(E35:E41) -> 0 | F42: =SUM(F35:F41) -> 0 | G42: =SUM(G35:G41) -> 0 | H42: =SUM(H35:H41) -> 0 | I42: =SUM(I35:I41) -> 0 | J42: =SUM(J35:J41) -> 0 | ... AG42: =SUM(AG35:AG41) -> 0 | AH42: =SUM(R42:AG42) -> 507889.73 | AJ42: 3181468.8 | AK42: =AH42-AJ42 -> -2673579 | AM42: Anteil CC | AN42: =AN41*AP42 -> 967750 | AO42: =+AN42/$AO$39 -> 60484.375 | AP42: 0.25 | AQ42: =AN41*25% -> 967750
AH43: =SUM(R43:AG43) -> 0 | AJ43: 0 | AM43: Anteil Debitoren | AN43: =AN41*AP43 -> 967750 | AO43: =+AN43/$AO$39 -> 60484.375 | AP43: 0.25
A44: Zwischensumme | C44: =C42-C32 -> 0 | D44: =D42-D32 -> 0 | E44: =E42-E32 -> 0 | F44: =F42-F32 -> 0 | G44: =G42-G32 -> 0 | H44: =H42-H32 -> 0 | I44: =I42-I32 -> 0 | J44: =J42-J32 -> 0 | ... AG44: =AG42-AG32 -> 0 | AH44: =SUM(R44:AG44) -> 442499.73 | AJ44: 1761468.8 | AK44: =AH44-AJ44 -> -1318969 | AM44: Anteil M-1 | AN44: 500000 | AO44: =+AN44/$AO$39 -> 31250 | AP44: 0.125
AH45: =SUM(R45:AG45) -> 0 | AJ45: 0 | AM45: Anteil M-2 | AN45: 500000 | AO45: =+AN45/$AO$39 -> 31250 | AP45: 0.125
A46: Liquiditätshilfe | B46: 0 | AH46: =SUM(R46:AG46) -> 0 | AJ46: 0
B47: 0 | AH47: =SUM(R47:AG47) -> 0 | AJ47: 0 | AM47: Check | AN47: =+AN42+AN43+Januar!AP44+Februar!AN45+AQ42 -> 4354875
B48: 0 | AH48: =SUM(R48:AG48) -> 0 | AJ48: 0
A50: Neuer Saldo | B50: =B6+B44-B46-B47-B48 -> 0 | C50: =C6+C44-C46-C47-C48 -> 0 | D50: =D6+D44-D46-D47-D48 -> 0 | E50: =E6+E44-E46-E47-E48 -> 0 | F50: =F6+F44-F46-F47-F48 -> 0 | G50: =G6+G44-G46-G47-G48 -> 0 | H50: =H6+H44-H46-H47-H48 -> 0 | I50: =I6+I44-I46-I47-I48 -> 0 | ... AH50: =AH6+AH44-AH46-AH47-AH48 -> 442499.73 | AJ50: 1761468.8 | AK50: =AH50-AJ50 -> -1318969
A51: Valuta ohne RL | B51: =+B5 -> 0 | C51: -663361.96 | D51: =+D50-D52 -> -1785226.9 | E51: =+E50-E52 -> -1785226.9 | F51: =+F50-F52 -> -1785226.9 | G51: =+G50-G52 -> -1785226.9 | H51: =+H50-H52 -> -1785226.9 | I51: =+I50-I52 -> -1785226.9 | J51: =+J50-J52 -> -1785226.9 | K51: =+K50-K52 -> -1785226.9 | ... AH51: =+AH50-AH52 -> -1342727.2 | AJ51: 4761469
A52: Anteil RL | C52: 1785226.9 | D52: =+C52 -> 1785226.9 | E52: =+D52 -> 1785226.9 | F52: =+E52 -> 1785226.9 | G52: =+F52 -> 1785226.9 | H52: =+G52 -> 1785226.9 | I52: =+H52 -> 1785226.9 | J52: =+I52 -> 1785226.9 | K52: =+J52 -> 1785226.9 | ... AH52: =+AG52 -> 1785226.9
R57: Notiz: Dec 2023 wurden zwischen dem 17 und dem 31, 1,8 Mio.EUR CC Einnahmen und 1,8 Mio. EUR Debitoren Verifizieren der Nexi Einnahmen - kann nicht sein mit 1,3 Mio.EUR bis 07.01

Sheet Januar
A1: Januar | B1: 22 | AJ1: 45686 | AL1: 45672
B2: Monatswerte | C2: 45658 | D2: 45659 | E2: 45660 | F2: 45661 | G2: 45662 | H2: 45663 | I2: 45664 | J2: 45665 | K2: 45666 | L2: 45667 | M2: 45668 | N2: 45669 | O2: 45670 | P2: 45671 | Q2: 45672 | R2: 45673 | S2: 45674 | T2: 45675 | U2: 45676 | V2: 45677 | W2: 45678 | X2: 45679 | Y2: 45680 | Z2: 45681 | AA2: 45682 | AB2: 45683 | AC2: 45684 | AD2: 45685 | AE2: 45686 | AF2: 45687 | AG2: 45688 | AH2: Monatswerte | AL2: Planungswert | AM2: Variance
A3: geplant/IST | C3: 1. | D3: 2. | E3: 3. | F3: 4. | G3: 5. | H3: 6. | I3: 7. | J3: 8. | K3: 9. | L3: 10. | M3: 11. | N3: 12. | O3: 13. | P3: 14. | Q3: 15. | R3: 16. | S3: 17. | T3: 18. | U3: 19. | V3: 20. | W3: 21. | X3: 22. | Y3: 23. | Z3: 24. | AA3: 25. | AB3: 26. | AC3: 27. | AD3: 28. | AE3: 29. | AF3: 30. | AG3: 31. | AH3: gesamt | AL3: 45672
A4: Valuta | B4: =+Dezember24!AG50 -> 3442499.7 | C4: =B4 -> 3442499.7 | D4: =+C50 -> 3442499.7 | E4: =+D50 -> 3439804.6 | F4: =+E50 -> 3276049.9 | G4: =+F50 -> 3276049.9 | H4: =+G50 -> 3276049.9 | I4: =+H50 -> 3284936.6 | J4: =+I50 -> 2103691.7 | K4: =+J50 -> 1913556.5 | ... AG4: =+AF50 -> 4458528.1 | AH4: =+B4 -> 3442499.7
A5: Tagesgeld | B5: 0 | C5: 0 | D5: 0 | E5: 0 | F5: 0 | G5: 0 | H5: 0 | I5: 0 | J5: 0 | K5: 0 | L5: 0 | M5: 0 | N5: 0 | O5: 0 | P5: 0 | Q5: 0 | R5: 0 | S5: 0 | T5: 0 | U5: 0 | V5: 0 | W5: 0 | X5: 0 | Y5: 0 | Z5: 0 | AA5: 0 | AB5: 0 | AC5: 0 | AD5: 0 | AE5: 0 | AF5: 0 | AG5: 0 | AH5: =+B5 -> 0
A6: Summe | B6: =+B4+B5 -> 3442499.7 | C6: =+C4+C5 -> 3442499.7 | D6: =+D4+D5 -> 3442499.7 | E6: =+E4+E5 -> 3439804.6 | F6: =+F4+F5 -> 3276049.9 | G6: =+G4+G5 -> 3276049.9 | H6: =+H4+H5 -> 3276049.9 | I6: =+I4+I5 -> 3284936.6 | ... AG6: =+AG4+AG5 -> 4458528.1 | AH6: =AH5+AH4 -> 3442499.7
A7: AUSGABEN | AL7: 0
A8: Pacht | B8: =SUM(D8:AG8) -> 1336978.3 | I8: 1109251.3 | R8: 227727 | AH8: =SUM(D8:AG8) -> 1336978.3 | AJ8: 1336978 | AL8: 1985625.6 | AM8: =AH8-AL8 -> -648647.27 | AN8: zusätzliche Pachten, Höchst, Airport, Kudamm etc
A9: Annuität ext. | B9: =SUM(C9:AG9) -> 0 | AH9: =SUM(C9:AG9) -> 0 | AJ9: 0 | AL9: 0 | AM9: =AH9-AL9 -> 0
A10: Kreditorenzahlungen | B10: =SUM(C10:AG10) -> 2712411.1 | D10: =12474.47+10000 -> 22474.47 | E10: =62095+25124.39+694.73 -> 87914.12 | H10: 14122.62 | I10: =70000+22176.84 -> 92176.84 | J10: =33000+22000+868.7 -> 55868.7 | K10: =13262.14+833.5+9000 -> 23095.64 | L10: 46910.34 | O10: 77887.86 | P10: =1410.88+730.64 -> 2141.52 | Q10: 683.53 | R10: 23622.78 | S10: =17394+22868+29904+61317.48+27103.84+18386.78+48842.37 -> 225816.47 | V10: =500+271.44+330+510+47684.53+250 -> 49545.97 | W10: =9214.75+28821.31+2287.21+20+42464.28+18876.56+52598.55+3451.22+20+74008.16+5+46114.91+35746.68+68031.3+6174.5+79317.59+19922.06 -> 487074.08 | X10: =9007.92+4726.89+5701.62+2534.3+3048.64+5592.65+9149.87+3235.51+13045.38+3440.28+15564.61+22101.43+2173.97 -> 99323.07 | Y10: =906.77+1848.16+426.71+185.18+3386.48+94.47+3135.68+746.35+1474.89+915.65 -> 13120.34 | Z10: =65297.96+39733.09+21010.8+1818.3+16129.37+77803.93+7581.1+96876.75+28157.81+9848.25+42395.39+12756.56 -> 419409.31 | AC10: 51765.88 | AD10: =5697+269.49+5474+13359.96+21130.93+6523.49+5213.91+61154.34+11667.12+17362.56+9017.32+7526.23+270.73 -> 164667.08 | AF10: =167586.84+3598.09+3120 -> 174304.93 | AG10: =9764.65+48838.15+357114.71-16000+3677.53+12728.12+21065.58+47654.67+21008.91+31911.82+4316.24+7294.29+21058.65+10052.18 -> 580485.5 | AH10: =SUM(C10:AG10) -> 2712411.1 | AJ10: 4245652.4 | AK10: Backlog Kreditoren | AL10: 4050000 | AM10: =AH10-AL10 -> -1337588.9 | AN10: reduzierte Ausgaben plus Verschiebung Jan
A11: Aktivbank/Progros | E11: 80069 | AH11: =SUM(C11:AG11) -> 80069 | AJ11: 80069 | AL11: 0
A12: Lastschriften | B12: =SUM(C12:AG12) -> 541051.79 | C12: =SUM(C13:C22) -> 0 | D12: =SUM(D13:D22) -> 0 | E12: =SUM(E13:E22) -> 0 | F12: =SUM(F13:F22) -> 0 | G12: =SUM(G13:G22) -> 0 | H12: =SUM(H13:H22) -> 11000 | I12: =SUM(I13:I22) -> 0 | J12: =SUM(J13:J22) -> 105000 | ... AH12: =SUM(AH13:AH22) -> 541051.79 | AJ12: 541051.79 | AL12: 0
A13: Energiedienstleister | H13: 11000 | J13: =20000+14000+22000+12000+24000+13000 -> 105000 | K13: =14000+18000 -> 32000 | AH13: =SUM(C13:AG13) -> 148000 | AJ13: 148000 | AL13: 0
A14: Telekommunikation | K14: 393051.79 | AH14: =SUM(C14:AG14) -> 393051.79 | AJ14: 393051.79 | AL14: 0
A15: Gebühren CC | AH15: =SUM(C15:AG15) -> 0 | AJ15: 0 | AL15: 0
A16: Provisonen( Booking, Expedia | AH16: =SUM(C16:AG16) -> 0 | AJ16: 0 | AL16: 0
A17: KFZ Leasing | AH17: =SUM(C17:AG17) -> 0 | AJ17: 0 | AL17: 0
A18: Jobtickets | AH18: =SUM(C18:AG18) -> 0 | AJ18: 0 | AL18: 0
A19: Leasing | AH19: =SUM(C19:AG19) -> 0 | AJ19: 0 | AL19: 0
A20: Gema/GEZ/Sky | AH20: =SUM(C20:AG20) -> 0 | AJ20: 0 | AL20: 0
A21: Sonepar/Haustechnik | AH21: =SUM(C21:AG21) -> 0 | AJ21: 0 | AL21: 0
A22: Airplus | AH22: =SUM(C22:AG22) -> 0 | AJ22: 0 | AL22: 0
A23: BGN/Schwerbeh.abgabe | B23: =SUM(C23:AG23) -> 0 | AH23: =SUM(C23:AG23) -> 0 | AJ23: 0 | AL23: 60000 | AM23: =AH23-AL23 -> -60000
A24: interne Zahlungen | B24: =SUM(C24:AG24) -> 0 | AH24: =SUM(C24:AG24) -> 0 | AJ24: 50000 | AK24: Verschiebung auf Februar | AL24: 100000 | AM24: =AH24-AL24 -> -100000
A25: City Taxes | AH25: =SUM(C25:AG25) -> 0 | AJ25: 130000 | AL25: 180000 | AM25: =AH25-AL25 -> -180000
A26: L&G | B26: =SUM(C26:AG26) -> 42140 | J26: 42140 | AH26: =SUM(C26:AG26) -> 42140 | AJ26: 150140 | AL26: 170000 | AM26: =AH26-AL26 -> -127860
A27: Krankenkasse | B27: =SUM(C27:AG27) -> 0 | AH27: =SUM(C27:AG27) -> 0 | AJ27: 0 | AL27: 0
A28: Lohnsteuer | B28: =SUM(C28:AG28) -> 0 | AH28: =SUM(C28:AG28) -> 0 | AJ28: 90000 | AL28: 0
A29: UST | B29: =SUM(C29:AG29) -> 0 | AH29: =SUM(C29:AG29) -> 0 | AJ29: 0 | AL29: -350314.99 | AM29: =AH29-AL29 -> 350314.99 | AN29: Korrektur Fehler ursprüngliche Planung
A30: Berater-/ Verfahrenskosten Insolvenzverfahren | B30: =SUM(C30:AG30) -> 0 | AH30: =SUM(C30:AG30) -> 0 | AJ30: 0 | AL30: 0
A31: div. Abbuchungen | B31: =SUM(C31:AG31) -> 0 | AH31: =SUM(C31:AG31) -> 0 | AJ31: 0 | AL31: 0
A32: Summe Ausgaben | B32: =SUM(B8:B31) -> 4632581.2 | C32: =SUM(C8:C31)-C12 -> 0 | D32: =SUM(D8:D31)-D12 -> 22474.47 | E32: =SUM(E8:E31)-E12 -> 167983.12 | F32: =SUM(F8:F31)-F12 -> 0 | G32: =SUM(G8:G31)-G12 -> 0 | H32: =SUM(H8:H31)-H12 -> 25122.62 | I32: =SUM(I8:I31)-I12 -> 1201428.2 | J32: =SUM(J8:J31)-J12 -> 203008.7 | ... AH32: =SUM(AH8:AH31)-AH12 -> 4712650.2 | AJ32: 6623891.2 | AL32: 6195310.6 | AM32: =AH32-AL32 -> -1482660.4
A34: EINNAHMEN
A35: Vorauszahlungen | B35: =SUM(C35:AG35) -> 0 | AH35: =SUM(C35:AG35) -> 0 | AJ35: 0 | AL35: 0
A36: Bareinzahlungen | B36: =SUM(C36:AG36) -> 0 | D36: 0 | E36: 0 | K36: 0 | L36: 0 | R36: 0 | S36: 0 | Y36: 0 | Z36: 0 | AA36: 0 | AB36: 0 | AF36: 0 | AG36: 0 | AH36: =SUM(C36:AG36) -> 0 | AJ36: 0 | AL36: 0
A37: Umbuchungen S-Zentral | B37: =SUM(C37:AG37) -> 0 | AH37: =SUM(C37:AG37) -> 0 | AJ37: 0 | AL37: 0
A38: interne Zahlungen | B38: =SUM(C38:AG38) -> 0 | AH38: =SUM(C38:AG38) -> 0 | AJ38: 0 | AL38: 0 | AO38: 31 | AQ38: =1048000/3 -> 349333.33
A39: Besonderheiten | B39: =SUM(C39:AG39) -> 0 | AH39: =SUM(C39:AG39) -> 0 | AJ39: 0 | AL39: 0
A40: Kreditkarten | B40: =SUM(C40:AG40) -> 3810010.6 | E40: 2500 | L40: =365.16+105+275.6+152.1+1143.77+40.5+1112.6+69+637.38+416.8+13.5+629.7+75+178.88+806.63 -> 6021.62 | O40: =3597.7+75863.96+117862.43+66806.17+138226.37+115543.85+170886+71946+79179+73057+188411+100906 -> 1202285.5 | P40: =1080.4+916.6+1437.45+1337.7+2252.96+3763 -> 10788.11 | Q40: =3171.3+601.8+1544.9+174.2+975.54+1019.5+12+1565.92+324+46.9+36+1269.1+60+570.98+760.56+3616 -> 15748.7 | R40: =66164.12+1004.92+26+291+1195.1+425.1+10036+1341+1879.1+62+1582.2-6.85+1240.74+1246.21+319.5+88.5 -> 86894.64 | S40: =36349+30707.01+270.44+1268.28+5095.51+571.79+22873.01+81.71+38235.07+52968.75+63801.61+1658.68+1758.82+1231.71+223.5+76000+807.27+21055.27+1602.35+28719.78+2798.21+61200+16065.42+140.34 -> 465483.53 | V40: =8873.89+388.11+3808+4402+11628+5153+14726.35+1471.87+1123.55+1336.44+1109.16+13250.47+8003.02+3807.21+5110 -> 84191.07 | W40: =240.5+34.5+1850+514+788.13+7 -> 3434.13 | X40: =8314.5+6+410+1291.75+1800+1307+13+278+2477.55+1105 -> 17002.8 | Y40: =618+1067.4+1334.9+142.1+3353.9+19427.11+2000+363.52 -> 28306.93 | Z40: =3699+13652.69+800+16258.74+11970.7+1500+22453+14121+5689.76+6341.2+7380+10249.78+11000+1744.32 -> 126860.19 | AC40: =5137.7+73210.11+18779.57+2622.57+38413.84+42255.66+89389.67+32608.31+72897.59+20071.4+57590.8+60024.45+10583-41057 -> 482527.67 | AD40: =934.68+184178+69500+4575.64+13396+8904+49466+5680+111752+49781+45373.72+7205+22483 -> 573229.04 | AE40: =371.8+903.28+5048+6184+74.48+341.05+85817+83727.77+123122+63040+12166+12914+4504+73626+2113.33 -> 473952.71 | AF40: =326.22+7731+3463+1742+20410+9866+10740+23220+12631+8699+8875+6436+2007 -> 116146.22 | AG40: =23+9807+7472+13738+21511+11849+23376+11938+4402+7666+2855.75 -> 114637.75 | AH40: =SUM(C40:AG40) -> 3810010.6 | AJ40: 3863346.7 | AL40: 4370953.1 | AM40: =AH40-AL40 -> -560942.47 | AN40: 840k reduzierte Einnahmen FC var Nexi Einbehalt 250k
A41: Debitoren | B41: =SUM(C41:AG41) -> 1555527.7 | D41: =15190+2800.2+398.65+1390.5 -> 19779.35 | E41: =739.97+338.5+649.9 -> 1728.37 | H41: =21310.17+60.6+301+1271.01+2668+3070.35+1423+642+3263.2 -> 34009.33 | I41: =2139.9+16300.5+231+1511.9 -> 20183.3 | J41: =1919.8+5201.78+2339.39+568+423+2421.5 -> 12873.47 | K41: =30+622+27217 -> 27869 | L41: =5087.3+7301.84+910+238+140.24+129.8+1056+115+138+164+709.44+5235+1596.5+125.49+51018.54 -> 73965.15 | O41: =893.5+4437+6721+2000+1003.92+8391+1067.91+5573 -> 30087.33 | P41: =29013+98.1+1078.5+12591-3763 -> 39017.6 | Q41: =1836+1246+228+126+6326+11235+1740+422.2+118.98+870.24+25101.59 -> 49250.01 | R41: =89+2142.4+127+127+127+2739+28545+15930+6767.62+522.12+8280.53+1972.6+123.2 -> 67492.47 | S41: =21941+838.5+3427+6+3356.5+1000+2350+360+140000+12402+11000.5+141+5206+8549+930.7+1039.8+314 -> 212862 | V41: =1149.01+5119.2+4308+2350+248.46+458.83+1595.62+5437+560 -> 21226.12 | W41: =139+2277.2+30885.29+102+10242.44+4009+9030+1292.75+5580+4632.25+1604.4 -> 69794.33 | X41: =6539.1+1544.12+5760+212+12115+7544+591+390.21+3090.76+21189.43+1335.4 -> 60311.02 | Y41: =16069+131+743+15037.94+8347.53+1051.47+26028.89+9846 -> 77254.83 | Z41: =8220+1471+8680+6027+128+1500+20607+23053+13349.94+38732+1000+39131+3461+3428.21 -> 168788.15 | AC41: =1000+5000+10000+8500 -> 24500 | AD41: =131+279.2+11297.2+1461+4658+38439+4051+3439+7526+46714 -> 117995.4 | AE41: =4816+1449+23792+6283+678+5892+1801+2880+2445+1812 -> 51848 | AF41: =2094+23685+2795+3927+5185+1628+8073+20345+159+2010+201739+345 -> 271985 | AG41: =2576+1637.37+975.09+8419+9164+18121+34616+394+394+7725+18686 -> 102707.46 | AH41: =SUM(C41:AG41) -> 1555527.7 | AJ41: 2063786.2 | AL41: 3177414 | AM41: =AH41-AL41 -> -1621886.3 | AN41: Verschiebung Einzahlungen Debitoren | AO41: Umsätze brutto | AP41: ='Exec Summary_Base Case'!D98*70%*1.07+'Exec Summary_Base Case'!D98*30%*1.19 -> 6500047.1 | AQ41: =+AP41/$AO$38 -> 209678.94
A42: Summe Einnahmen | B42: =SUM(B40:B41) -> 5365538.3 | C42: =SUM(C35:C41) -> 0 | D42: =SUM(D35:D41) -> 19779.35 | E42: =SUM(E35:E41) -> 4228.37 | F42: =SUM(F35:F41) -> 0 | G42: =SUM(G35:G41) -> 0 | H42: =SUM(H35:H41) -> 34009.33 | I42: =SUM(I35:I41) -> 20183.3 | J42: =SUM(J35:J41) -> 12873.47 | ... AG42: =SUM(AG35:AG41) -> 217345.21 | AH42: =SUM(C42:AG42) -> 5365538.3 | AJ42: 5927132.9 | AL42: 7548367.1 | AM42: =AH42-AL42 -> -2182828.8 | AO42: Anteil CC | AP42: =AP41*AR42 -> 3250023.6 | AQ42: =+AP42/$AO$38 -> 104839.47 | AR42: 0.5 | AS42: plus 600k dez
AO43: Anteil Debitoren | AP43: =AP41*AR43 -> 1625011.8 | AQ43: =+AP43/$AO$38 -> 52419.735 | AR43: 0.25 | AS43: plus 920k Dez
A44: Zwischensumme | C44: =-C32+C42 -> 0 | D44: =D42-D32 -> -2695.12 | E44: =E42-E32 -> -163754.75 | F44: =F42-F32 -> 0 | G44: =G42-G32 -> 0 | H44: =H42-H32 -> 8886.71 | I44: =I42-I32 -> -1181244.9 | J44: =J42-J32 -> -190135.23 | K44: =K42-K32 -> -420278.43 | ... AH44: =AH42-AH32 -> 652888.1 | AJ44: -696758.36 | AL44: 1353056.5 | AM44: =AH44-AL44 -> -700168.37 | AO44: Anteil M-1 | AP44: =AR44*Dezember24!AN41*1.5 -> 725812.5 | AQ44: =+AP44/$AO$38 -> 23413.306 | AR44: 0.125
AO45: Anteil M-2 | AP45: =500000*1.5 -> 750000 | AQ45: =+AP45/$AO$38 -> 24193.548 | AR45: 0.125
A46: Liquiditätshilfe | B46: 0 | AH46: =SUM(C46:AG46) -> 0 | AJ46: 0 | AL46: 0
B47: 0 | AH47: =SUM(C47:AG47) -> 0 | AJ47: 0 | AL47: 0 | AP47: =+AP42+AP43+Februar!AN44+März!AN45 -> 6500047.1
B48: 0 | AH48: =SUM(C48:AG48) -> 0 | AJ48: 0 | AL48: 0
A50: Neuer Saldo | B50: =B6+B44-B46-B47-B48 -> 3442499.7 | C50: =C6+C44-C46-C47-C48 -> 3442499.7 | D50: =D6+D44-D46-D47-D48 -> 3439804.6 | E50: =E6+E44-E46-E47-E48 -> 3276049.9 | F50: =F6+F44-F46-F47-F48 -> 3276049.9 | G50: =G6+G44-G46-G47-G48 -> 3276049.9 | H50: =H6+H44-H46-H47-H48 -> 3284936.6 | I50: =I6+I44-I46-I47-I48 -> 2103691.7 | ... AH50: =AH6+AH44-AH46-AH47-AH48 -> 4095387.8 | AJ50: 2745741.4 | AL50: 6114525.2 | AM50: =AH50-AL50 -> -2019137.4
I51: 1048000 | L51: =L50-K50 -> 33076.43 | O51: =122299.43+75863.96+4491.2+66806.17+138226.37+115543.85+177606.44+73946.03+80183.48+81447.91+189479.38+106478.7 -> 1232372.9 | P51: =1080.4-1410.88+1535.55+29013+916.6-730.64+1078.5+1337.7+2252.96+12590.86 -> 47664.05 | Q51: =5609.1-683.53+2965.1+1385.5+975.54+8262.57+14340.1+570.98+1301.74+25101.59+4486.24 -> 64314.93 | R51: =69426.44+291+1195.1+806.1+12774.75+31827.39-251349.37+1582.2-6.85+17170.74+6767.62+10048.86+2503.8 -> -96962.22 | S51: =58289.23+33084.23-17394+5095.51-22868-29904+30316.01+38235.07+52968.75-61317.48+72384.32-27103.84+140000+88402.1+34606.39+36723.55+69749.16-18386.78-48842.37+18490.56 -> 452528.41 | V51: =1149.01-500+8873.89+388.11-271.44-330+3808.01+9521.65+15936.56-510+7503.09-47684.53+14726.35-250+1471.87+5872.06+30498.11+5660.21 -> 55862.95 | W51: =-9214.75+2416.2-31128.52+30885.29-42464.28-18876.56+377-56069.77+10242.44-74013.16+5858.8-46114.91+9543.85-35746.68+1292.75-68031.3+5581-6174.5+788.13-79317.59+4632.25-19922.06+1611.5 -> -413844.87 | X51: =-9007.92+8314.5-4726.89-5701.62+6539.1-2534.3+6-3048.64+1954.52-5592+7263.75+13914.88-9149.87-3235.51+9141.5-13045.38+2477.55-3440.28+2086.52-15564.61+3089.76-22101.43+21189.43 -> -21170.94 | Y51: =16069-906.77-1848.16+1685.4-426.71+2351-185.18+3353.9+15037.94-3386.48+19427.11-94.47+10347.53-3135.68+363.52+1051.47-746.35+26028.89-1474.89+9846-915.65 -> 92441.42 | Z51: =-65297.96+11918.93-39733.09+13652.69+10949.82-21010.8+35755.97-1818.3+128-16129.37+22107.01-77803.93+45506.07+13349.94-7581.1-96876.75+52852.62+28157.81+6689.76-9848.25+10249.78-42395.39+14428.21-12756.56+1744.32 -> -123760.57
A53: Kontrolle | Z53: =-Z51+Z44 -> -0.4 | AN53: Entnahme CC 250k Einbehalt

Sheet Februar
A1: Februar | B1: 21
B2: Monatswerte | C2: 45689 | D2: 45690 | E2: 45691 | F2: 45692 | G2: 45693 | H2: 45694 | I2: 45695 | J2: 45696 | K2: 45697 | L2: 45698 | M2: 45699 | N2: 45700 | O2: 45701 | P2: 45702 | Q2: 45703 | R2: 45704 | S2: 45705 | T2: 45706 | U2: 45707 | V2: 45708 | W2: 45709 | X2: 45710 | Y2: 45711 | Z2: 45712 | AA2: 45713 | AB2: 45714 | AC2: 45715 | AD2: 45716 | AH2: Monatswerte | AJ2: Planungswert | AK2: Variance
A3: geplant/IST | C3: 1. | D3: 2. | E3: 3. | F3: 4. | G3: 5. | H3: 6. | I3: 7. | J3: 8. | K3: 9. | L3: 10. | M3: 11. | N3: 12. | O3: 13. | P3: 14. | Q3: 15. | R3: 16. | S3: 17. | T3: 18. | U3: 19. | V3: 20. | W3: 21. | X3: 22. | Y3: 23. | Z3: 24. | AA3: 25. | AB3: 26. | AC3: 27. | AD3: 28. | AH3: gesamt
A4: Valuta inkl RL | B4: =+Januar!AG50 -> 4095387.8 | C4: =B4 -> 4095387.8 | D4: =+C50 -> 4095387.8 | E4: =+D50 -> 4095387.8 | F4: =+E50 -> 4544569.4 | G4: =+F50 -> 4620588 | H4: =+G50 -> 4883984.2 | I4: =+H50 -> 5169302.3 | J4: =+I50 -> 5398011.4 | K4: =+J50 -> 5398011.4 | ... AG4: =+AF50 -> 4710438.2 | AH4: =+B4 -> 4095387.8
A5: Tagesgeld | B5: 0 | C5: 0 | D5: 0 | E5: 0 | F5: 0 | G5: 0 | H5: 0 | I5: 0 | J5: 0 | K5: 0 | L5: 0 | M5: 0 | N5: 0 | O5: 0 | P5: 0 | Q5: 0 | R5: 0 | S5: 0 | T5: 0 | U5: 0 | V5: 0 | W5: 0 | X5: 0 | Y5: 0 | Z5: 0 | AA5: 0 | AB5: 0 | AC5: 0 | AD5: 0 | AE5: 0 | AF5: 0 | AG5: 0 | AH5: =+B5 -> 0
A6: Summe | B6: =+B4+B5 -> 4095387.8 | C6: =+C4+C5 -> 4095387.8 | D6: =+D4+D5 -> 4095387.8 | E6: =+E4+E5 -> 4095387.8 | F6: =+F4+F5 -> 4544569.4 | G6: =+G4+G5 -> 4620588 | H6: =+H4+H5 -> 4883984.2 | I6: =+I4+I5 -> 5169302.3 | ... AG6: =+AG4+AG5 -> 4710438.2 | AH6: =AH5+AH4 -> 4095387.8
A7: AUSGABEN | AH7: =SUM(C7:AG7) -> 0 | AJ7: 0
A8: Pacht | B8: =SUM(C8:AG8) -> -227726.6 | F8: =-222947.74-4778.86 -> -227726.6 | AH8: =SUM(C8:AG8) -> -227726.6 | AJ8: 0 | AK8: =AH8-AJ8 -> -227726.6 | AM8: Indexanpassungen
A9: Annuität ext. | B9: =SUM(C9:AG9) -> 0 | AH9: =SUM(C9:AG9) -> 0 | AJ9: 0 | AK9: =AH9-AJ9 -> 0
A10: Kreditorenzahlungen | B10: =SUM(C10:AG10) -> 5020228.1 | E10: =16488.05+37926.29+8441.35 -> 62855.69 | F10: =49432.49+31626.73+26444.98+12300+2734.98+19179.89+13971.5+28333.23+32410.68+29413.9+28353.69+63726.73+23089.95 -> 361018.75 | G10: 17500 | L10: =10724.49+30198+74719+41195+28990+45762+74471+138517+72600+3712+16279+160352+6317 -> 703836.49 | M10: 657 | N10: =48645+13300+1040 -> 62985 | O10: 4832.09 | P10: =462593.5+3478.64+24389.44+23773.22+11967.79+24704.7+61071.52+83659.42+50845.05+54882.82+18333.13+56625.02+23186.68 -> 899510.93 | S10: =21908.08+1448.59+710.61+346.61+531+5679+507+1181+324 -> 32635.89 | T10: =10235.2+481.58 -> 10716.78 | U10: =9923.96+23084.39+16197.25+1077.5+25191.88+48603.7+11904.35+14587.69+8895.06+14+36091.73 -> 195571.51 | V10: =9421+35891+43963+9725+38977+32910+100375+72505+54837+26110+21366+62396+35638 -> 544114 | W10: =33604+5675+29796+6207+2468+21289+20742+68029+14977+20479+8045+10786+56397+29132 -> 327626 | Z10: =219407+11761+706+21930+26661+47662+1241 -> 329368 | AA10: 70000 | AC10: 26000 | AD10: =750000+100000+45000+26000+450000 -> 1371000 | AH10: =SUM(C10:AG10) -> 5020228.1 | AJ10: 5142904.9 | AK10: =AH10-AJ10 -> -122676.8 | AL10: Kostenreduzierung vs. Umsatz | AM10: ='Exec Summary_Base Case'!E103*1.19-AH25 -> 5138866.6 | AN10: =AM10/4 -> 1284716.6
A11: Aktivbank/Progros | AH11: =SUM(C11:AG11) -> 0 | AJ11: 0
A12: Lastschriften | B12: =SUM(C12:AG12) -> 0 | AH12: =SUM(C12:AG12) -> 0 | AJ12: 0
A13: Energiedienstleister | AH13: =SUM(C13:AG13) -> 0 | AJ13: 0
A14: Telekommunikation | AH14: =SUM(C14:AG14) -> 0 | AJ14: 0
A15: Gebühren CC | AH15: =SUM(C15:AG15) -> 0 | AJ15: 0
A16: Provisonen( Booking, Expedia | AH16: =SUM(C16:AG16) -> 0 | AJ16: 0
A17: KFZ Leasing | AH17: =SUM(C17:AG17) -> 0 | AJ17: 0
A18: Jobtickets | AH18: =SUM(C18:AG18) -> 0 | AJ18: 0
A19: Leasing | AH19: =SUM(C19:AG19) -> 0 | AJ19: 0
A20: Gema/GEZ/Sky | AH20: =SUM(C20:AG20) -> 0 | AJ20: 0
A21: Sonepar/Haustechnik | AH21: =SUM(C21:AG21) -> 0 | AJ21: 0
A22: Airplus | AH22: =SUM(C22:AG22) -> 0 | AJ22: 0
A23: BGN/Schwerbeh.abgabe | B23: =SUM(C23:AG23) -> 0 | AH23: =SUM(C23:AG23) -> 0 | AJ23: 0 | AK23: =AH23-AJ23 -> 0
A24: interne Zahlungen | B24: =SUM(C24:AG24) -> 0 | AH24: =SUM(C24:AG24) -> 0 | AJ24: 100000 | AK24: =AH24-AJ24 -> -100000 | AL24: Verschiebung von Jan auf Feb
A25: City Taxes | AH25: =SUM(C25:AG25) -> 0 | AJ25: 10000 | AK25: =AH25-AJ25 -> -10000
A26: L&G | B26: =SUM(C26:AG26) -> 170000 | AD26: 170000 | AH26: =SUM(C26:AG26) -> 170000 | AJ26: 170000 | AK26: =AH26-AJ26 -> 0
A27: Krankenkasse | B27: =SUM(C27:AG27) -> 0 | AH27: =SUM(C27:AG27) -> 0 | AJ27: 0
A28: Lohnsteuer | B28: =SUM(C28:AG28) -> 0 | AH28: =SUM(C28:AG28) -> 0 | AJ28: 0 | AL28: Verschiebung der Monate
A29: UST/Quellensteuer | AH29: =SUM(C29:AG29) -> 0 | AJ29: -73565.065 | AK29: =AH29-AJ29 -> 73565.065
A30: Berater-/ Verfahrenskosten Insolvenzverfahren | B30: =SUM(C30:AG30) -> 1500000 | AB30: 1500000 | AH30: =SUM(C30:AG30) -> 1500000 | AJ30: 1500000
A31: div. Abbuchungen | B31: =SUM(C31:AG31) -> 98500 | L31: 98500 | AH31: =SUM(C31:AG31) -> 98500 | AJ31: 0
A32: Summe Ausgaben | B32: =SUM(B8:B31) -> 6561001.5 | C32: =SUM(C8:C31)-C12 -> 0 | D32: =SUM(D8:D31)-D12 -> 0 | E32: =SUM(E8:E31)-E12 -> 62855.69 | F32: =SUM(F8:F31)-F12 -> 133292.15 | G32: =SUM(G8:G31)-G12 -> 17500 | H32: =SUM(H8:H31)-H12 -> 0 | I32: =SUM(I8:I31)-I12 -> 0 | J32: =SUM(J8:J31)-J12 -> 0 | ... AH32: =SUM(AH8:AH31)-AH12 -> 6561001.5 | AJ32: 6849339.9 | AK32: =AH32-AJ32 -> -288338.33
A34: EINNAHMEN
A35: Vorauszahlungen | B35: =SUM(C35:AG35) -> 0 | AH35: =SUM(C35:AG35) -> 0 | AJ35: 0
A36: Bareinzahlungen | B36: =SUM(C36:AG36) -> 0 | F36: 0 | G36: 0 | M36: 0 | N36: 0 | T36: 0 | U36: 0 | AA36: 0 | AB36: 0 | AH36: =SUM(C36:AG36) -> 0 | AJ36: 0
A37: Umbuchungen S-Zentral | B37: =SUM(C37:AG37) -> 0 | AH37: =SUM(C37:AG37) -> 0 | AJ37: 0
A38: interne Zahlungen | B38: =SUM(C38:AG38) -> 0 | AH38: =SUM(C38:AG38) -> 0 | AJ38: 0
A39: Besonderheiten | B39: =SUM(C39:AG39) -> 20889.36 | E39: 20889.36 | AH39: =SUM(C39:AG39) -> 20889.36 | AJ39: 0 | AO39: 28
A40: Kreditkarten | B40: =SUM(C40:AG40) -> 4298434.4 | E40: =3290+1781+13877+13072+19922+47811+37991+67137+26308+58347+19766+61184+9559.93 -> 380045.93 | F40: =3954.5+333.14+12232+6289+1352.72+4195+7952+10468+23358+11310+8144+5595+14776+7299 -> 117258.36 | G40: =4688+48.57+2547+47949+23.93+6533.98+7046+12869+28557+10131+8414+4993+8649+4161.68 -> 146611.16 | H40: =121.05+1039+353.68+278.42+13331+5387+16229+11627+19730+18483+16696+19961+6779+21891+994 -> 152900.15 | I40: =2664.58+2951.68+12336+500.39+12340+16626.56+14513+25547+11238+24037+5121+23499+1485-22724 -> 130135.21 | L40: =5668+1289+42889+2261.46+25579+51243+35306+64956+78355+39068+57895+72758+16851 -> 494118.46 | M40: =56.75+922+5984+1019+5060+8113+16513+19013+31274+15162+5906+18550+5923 -> 133495.75 | N40: =2274+2696+6799+840+12217+6731+10688+30914+34565+12269+4056+17959+2610-1432+41047 -> 184233 | O40: =590.8+12016+5959.51+33483+17487+15716+15517+40573+9929+1562+45794+2750 -> 201377.31 | P40: =829+3595+12973+1227+20698+21090+25135+35432+22741+9307+7241+18379+1628.81 -> 180275.81 | S40: =6168.2+198.78+44243+32855+7804.76+36200+21063+56328+63737+35953+36572.28+21832.96+78781+17363 -> 459099.98 | T40: =2024.2+13972.2+6+15500+17796+6040+13108+41443+26933+7941+9744+10280+13877 -> 178664.4 | U40: =4705.52+6261+6235+1330.7+18989+6449+14956.72+24367+11188+7177+18791.77+8813+3249 -> 132512.71 | V40: =2716+7556+9039+34404+10866+13341+21390+15550+7928+41927+18174+2077 -> 184968 | W40: =4824+4762+9177+6038+20572+17011+28426+23401+15731+9180+16373+14375+1928 -> 171798 | Z40: =11001+21793+33952+13042+24751+59741+59425+109262+78665+47413+41387+68900+15855+25394 -> 610581 | AA40: =+$AO$42 -> 135089.79 | AB40: =+$AO$42 -> 135089.79 | AC40: =+$AO$42 -> 135089.79 | AD40: =+$AO$42-100000 -> 35089.793 | AH40: =SUM(C40:AG40) -> 4298434.4 | AJ40: 3908393.5 | AK40: =AH40-AJ40 -> 390040.89
